Workbook

Sheet FBA FEES
C1: Size Tire | D1: Additional Fees Per LB
C2: 3 to 20 (LB) | D2: 0.32 | I2: 15.1 | K2: Weight | L2: Shipping weight/Size tier | M2: Large bulky | N2: Extra-large 0 to 50 lb | O2: Extra-large 50+ to 70 lb | P2: Extra-large 70+ to 150 lb | Q2: Extra-large 150+ lb | S2: Tier
K3: LB | L3: OZ | M3: DIMS-59*33*33 Girth - 130 | N3: 59+*33+*33+ Girth - 130 | O3: 59+*33+*33+ Girth - 130 | P3: 59+*33+*33+ Girth - 130 | Q3: 59+*33+*33+ Girth - 130 | S3: =IF(AND($I$12<=P44,$D$8<=M44,$D$9<=N44,$D$10<=O44),K44,IF(AND($I$12<=P45,$D$8<=M45,$D$9<=N45,$D$10<=O45),K45,IF(AND($D$8<=M46,$D$9<=N46,$D$10<=O46,$I$12<=P46),K46,IF(AND($I$12<=P47,OR(N$8>M47,$D$9>N47,$D$10>O47)),K47,IF(AND($I$12>P47,$I$12<=P48),K48,IF(AND($I$12>P48,$I$12<=P49),K49,K50)))))) -> 47
K4: 1 | L4: =K4*16 -> 16 | M4: 9.61 | N4: 26.33 | S4: Fees
K5: 2 | L5: =K5*16 -> 32 | M5: =$I$10+(K4*$I$18) -> 9.99 | N5: =$I$11+(K4*$I$18) -> 26.71 | S5: =IFERROR(VLOOKUP(ROUNDUP($D$7,0),'FBA FEES'!$L$2:$Q$203,MATCH(S3,'FBA FEES'!$L$2:$Q$2,0),FALSE),VLOOKUP(ROUNDUP($D$7,0),'FBA FEES'!$C$6:$F$123,MATCH(S3,'FBA FEES'!$C$6:$F$6,0),FALSE)) -> #VALUE!
B6: Weight | C6: Shipping weight/Size tier | D6: Small standard-size | E6: Large standard | F6: Large standard-size | K6: 3 | L6: =K6*16 -> 48 | M6: =$I$10+(K5*$I$18) -> 10.37 | N6: =$I$11+(K5*$I$18) -> 27.09 | S6: =ROUND(MAX($D$11,$D$12),0) -> 3
A7: SR.NO | B7: LB | C7: OZ | D7: 15*12*0.75 (16 oz) | E7: 18*14*8 (20 LB) | F7: Final Fees Charged | K7: 4 | L7: =K7*16 -> 64 | M7: =$I$10+(K6*$I$18) -> 10.75 | N7: =$I$11+(K6*$I$18) -> 27.47
A8: =ROUND(B8,2) -> 0.04 | B8: 0.04 | C8: 1 | D8: 3.06 | E8: 3.68 | F8: =IF(B8<=3,E8,IF(B8<=20,E8+((B8-3)*$D$2),)) -> 3.68 | K8: 5 | L8: =K8*16 -> 80 | M8: =$I$10+(K7*$I$18) -> 11.13 | N8: =$I$11+(K7*$I$18) -> 27.85
A9: =ROUND(B9,2) -> 0.13 | B9: 0.125 | C9: 2 | D9: 3.06 | E9: 3.68 | F9: =IF(B9<=3,E9,IF(B9<=20,E9+((B9-3)*$D$2),)) -> 3.68 | G9: Additional fee applicable | H9: Size Tire | I9: Fixed FBA Fees | K9: 6 | L9: =K9*16 -> 96 | M9: =$I$10+(K8*$I$18) -> 11.51 | N9: =$I$11+(K8*$I$18) -> 28.23
A10: =ROUND(B10,2) -> 0.19 | B10: 0.1875 | C10: 3 | D10: 3.15 | E10: 3.68 | F10: =IF(B10<=3,E10,IF(B10<=20,E10+((B10-3)*$D$2),)) -> 3.68 | G10: above first lb | H10: Large Bulky | I10: 9.61 | K10: 7 | L10: =K10*16 -> 112 | M10: =$I$10+(K9*$I$18) -> 11.89 | N10: =$I$11+(K9*$I$18) -> 28.61
A11: =ROUND(B11,2) -> 0.25 | B11: 0.25 | C11: 4 | D11: 3.15 | E11: 3.68 | F11: =IF(B11<=3,E11,IF(B11<=20,E11+((B11-3)*$D$2),)) -> 3.68 | G11: above first lb | H11: Extra-large 0 to 50 lb | I11: 26.33 | K11: 8 | L11: =K11*16 -> 128 | M11: =$I$10+(K10*$I$18) -> 12.27 | N11: =$I$11+(K10*$I$18) -> 28.99
A12: =ROUND(B12,2) -> 0.31 | B12: 0.3125 | C12: 5 | D12: 3.24 | E12: 3.9 | F12: =IF(B12<=3,E12,IF(B12<=20,E12+((B12-3)*$D$2),)) -> 3.9 | G12: above 51 lb | H12: Extra-large 50 to 70 lb | I12: 40.12 | K12: 9 | L12: =K12*16 -> 144 | M12: =$I$10+(K11*$I$18) -> 12.65 | N12: =$I$11+(K11*$I$18) -> 29.37
A13: =ROUND(B13,2) -> 0.38 | B13: 0.375 | C13: 6 | D13: 3.24 | E13: 3.9 | F13: =IF(B13<=3,E13,IF(B13<=20,E13+((B13-3)*$D$2),)) -> 3.9 | G13: above 71 lb | H13: Extra-large 70 to 150 lb | I13: 54.81 | K13: 10 | L13: =K13*16 -> 160 | M13: =$I$10+(K12*$I$18) -> 13.03 | N13: =$I$11+(K12*$I$18) -> 29.75
A14: =ROUND(B14,2) -> 0.44 | B14: 0.4375 | C14: 7 | D14: 3.33 | E14: 3.9 | F14: =IF(B14<=3,E14,IF(B14<=20,E14+((B14-3)*$D$2),)) -> 3.9 | G14: above 151 lb | H14: Extra-large 150+++ lb | I14: 194.95 | K14: 11 | L14: =K14*16 -> 176 | M14: =$I$10+(K13*$I$18) -> 13.41 | N14: =$I$11+(K13*$I$18) -> 30.13
A15: =ROUND(B15,2) -> 0.5 | B15: 0.5 | C15: 8 | D15: 3.33 | E15: 3.9 | F15: =IF(B15<=3,E15,IF(B15<=20,E15+((B15-3)*$D$2),)) -> 3.9 | K15: 12 | L15: =K15*16 -> 192 | M15: =$I$10+(K14*$I$18) -> 13.79 | N15: =$I$11+(K14*$I$18) -> 30.51
A16: =ROUND(B16,2) -> 0.56 | B16: 0.5625 | C16: 9 | D16: 3.43 | E16: 4.15 | F16: =IF(B16<=3,E16,IF(B16<=20,E16+((B16-3)*$D$2),)) -> 4.15 | K16: 13 | L16: =K16*16 -> 208 | M16: =$I$10+(K15*$I$18) -> 14.17 | N16: =$I$11+(K15*$I$18) -> 30.89
A17: =ROUND(B17,2) -> 0.63 | B17: 0.625 | C17: 10 | D17: 3.43 | E17: 4.15 | F17: =IF(B17<=3,E17,IF(B17<=20,E17+((B17-3)*$D$2),)) -> 4.15 | H17: Size Tire | I17: Additional Fees Per LB | K17: 14 | L17: =K17*16 -> 224 | M17: =$I$10+(K16*$I$18) -> 14.55 | N17: =$I$11+(K16*$I$18) -> 31.27
A18: =ROUND(B18,2) -> 0.69 | B18: 0.6875 | C18: 11 | D18: 3.53 | E18: 4.15 | F18: =IF(B18<=3,E18,IF(B18<=20,E18+((B18-3)*$D$2),)) -> 4.15 | H18: 0 to 50 (LB) | I18: 0.38 | K18: 15 | L18: =K18*16 -> 240 | M18: =$I$10+(K17*$I$18) -> 14.93 | N18: =$I$11+(K17*$I$18) -> 31.65
A19: =ROUND(B19,2) -> 0.75 | B19: 0.75 | C19: 12 | D19: 3.53 | E19: 4.15 | F19: =IF(B19<=3,E19,IF(B19<=20,E19+((B19-3)*$D$2),)) -> 4.15 | H19: 50 to 150 (LB) | I19: 0.75 | K19: 16 | L19: =K19*16 -> 256 | M19: =$I$10+(K18*$I$18) -> 15.31 | N19: =$I$11+(K18*$I$18) -> 32.03
A20: =ROUND(B20,2) -> 0.81 | B20: 0.8125 | C20: 13 | D20: 3.6 | E20: 4.55 | F20: =IF(B20<=3,E20,IF(B20<=20,E20+((B20-3)*$D$2),)) -> 4.55 | H20: 150+++ (LB) | I20: 0.19 | K20: 17 | L20: =K20*16 -> 272 | M20: =$I$10+(K19*$I$18) -> 15.69 | N20: =$I$11+(K19*$I$18) -> 32.41
A21: =ROUND(B21,2) -> 0.88 | B21: 0.875 | C21: 14 | D21: 3.6 | E21: 4.55 | F21: =IF(B21<=3,E21,IF(B21<=20,E21+((B21-3)*$D$2),)) -> 4.55 | K21: 18 | L21: =K21*16 -> 288 | M21: =$I$10+(K20*$I$18) -> 16.07 | N21: =$I$11+(K20*$I$18) -> 32.79
A22: =ROUND(B22,2) -> 0.94 | B22: 0.9375 | C22: 15 | D22: 3.65 | E22: 4.55 | F22: =IF(B22<=3,E22,IF(B22<=20,E22+((B22-3)*$D$2),)) -> 4.55 | K22: 19 | L22: =K22*16 -> 304 | M22: =$I$10+(K21*$I$18) -> 16.45 | N22: =$I$11+(K21*$I$18) -> 33.17
A23: =ROUND(B23,2) -> 1 | B23: 1 | C23: 16 | D23: 3.65 | E23: 4.55 | F23: =IF(B23<=3,E23,IF(B23<=20,E23+((B23-3)*$D$2),)) -> 4.55 | K23: 20 | L23: =K23*16 -> 320 | M23: =$I$10+(K22*$I$18) -> 16.83 | N23: =$I$11+(K22*$I$18) -> 33.55
A24: =ROUND(B24,2) -> 1.06 | B24: 1.0625 | C24: 17 | E24: 4.99 | F24: =IF(B24<=3,E24,IF(B24<=20,E24+((B24-3)*$D$2),)) -> 4.99 | K24: 21 | L24: =K24*16 -> 336 | M24: =$I$10+(K23*$I$18) -> 17.21 | N24: =$I$11+(K23*$I$18) -> 33.93
A25: =ROUND(B25,2) -> 1.13 | B25: 1.125 | C25: 18 | E25: 4.99 | F25: =IF(B25<=3,E25,IF(B25<=20,E25+((B25-3)*$D$2),)) -> 4.99 | K25: 22 | L25: =K25*16 -> 352 | M25: =$I$10+(K24*$I$18) -> 17.59 | N25: =$I$11+(K24*$I$18) -> 34.31
A26: =ROUND(B26,2) -> 1.19 | B26: 1.1875 | C26: 19 | E26: 4.99 | F26: =IF(B26<=3,E26,IF(B26<=20,E26+((B26-3)*$D$2),)) -> 4.99 | K26: 23 | L26: =K26*16 -> 368 | M26: =$I$10+(K25*$I$18) -> 17.97 | N26: =$I$11+(K25*$I$18) -> 34.69
A27: =ROUND(B27,2) -> 1.25 | B27: 1.25 | C27: 20 | E27: 4.99 | F27: =IF(B27<=3,E27,IF(B27<=20,E27+((B27-3)*$D$2),)) -> 4.99 | K27: 24 | L27: =K27*16 -> 384 | M27: =$I$10+(K26*$I$18) -> 18.35 | N27: =$I$11+(K26*$I$18) -> 35.07
A28: =ROUND(B28,2) -> 1.31 | B28: 1.3125 | C28: 21 | E28: 5.37 | F28: =IF(B28<=3,E28,IF(B28<=20,E28+((B28-3)*$D$2),)) -> 5.37 | K28: 25 | L28: =K28*16 -> 400 | M28: =$I$10+(K27*$I$18) -> 18.73 | N28: =$I$11+(K27*$I$18) -> 35.45
A29: =ROUND(B29,2) -> 1.38 | B29: 1.375 | C29: 22 | E29: 5.37 | F29: =IF(B29<=3,E29,IF(B29<=20,E29+((B29-3)*$D$2),)) -> 5.37 | K29: 26 | L29: =K29*16 -> 416 | M29: =$I$10+(K28*$I$18) -> 19.11 | N29: =$I$11+(K28*$I$18) -> 35.83
A30: =ROUND(B30,2) -> 1.44 | B30: 1.4375 | C30: 23 | E30: 5.37 | F30: =IF(B30<=3,E30,IF(B30<=20,E30+((B30-3)*$D$2),)) -> 5.37 | K30: 27 | L30: =K30*16 -> 432 | M30: =$I$10+(K29*$I$18) -> 19.49 | N30: =$I$11+(K29*$I$18) -> 36.21
A31: =ROUND(B31,2) -> 1.5 | B31: 1.5 | C31: 24 | E31: 5.37 | F31: =IF(B31<=3,E31,IF(B31<=20,E31+((B31-3)*$D$2),)) -> 5.37 | K31: 28 | L31: =K31*16 -> 448 | M31: =$I$10+(K30*$I$18) -> 19.87 | N31: =$I$11+(K30*$I$18) -> 36.59
A32: =ROUND(B32,2) -> 1.56 | B32: 1.5625 | C32: 25 | E32: 5.52 | F32: =IF(B32<=3,E32,IF(B32<=20,E32+((B32-3)*$D$2),)) -> 5.52 | K32: 29 | L32: =K32*16 -> 464 | M32: =$I$10+(K31*$I$18) -> 20.25 | N32: =$I$11+(K31*$I$18) -> 36.97
A33: =ROUND(B33,2) -> 1.63 | B33: 1.625 | C33: 26 | E33: 5.52 | F33: =IF(B33<=3,E33,IF(B33<=20,E33+((B33-3)*$D$2),)) -> 5.52 | K33: 30 | L33: =K33*16 -> 480 | M33: =$I$10+(K32*$I$18) -> 20.63 | N33: =$I$11+(K32*$I$18) -> 37.35
A34: =ROUND(B34,2) -> 1.69 | B34: 1.6875 | C34: 27 | E34: 5.52 | F34: =IF(B34<=3,E34,IF(B34<=20,E34+((B34-3)*$D$2),)) -> 5.52 | K34: 31 | L34: =K34*16 -> 496 | M34: =$I$10+(K33*$I$18) -> 21.01 | N34: =$I$11+(K33*$I$18) -> 37.73
A35: =ROUND(B35,2) -> 1.75 | B35: 1.75 | C35: 28 | E35: 5.52 | F35: =IF(B35<=3,E35,IF(B35<=20,E35+((B35-3)*$D$2),)) -> 5.52 | K35: 32 | L35: =K35*16 -> 512 | M35: =$I$10+(K34*$I$18) -> 21.39 | N35: =$I$11+(K34*$I$18) -> 38.11
... A53: =ROUND(B53,2) -> 2.88 | B53: 2.875 | C53: 46 | E53: 6.62 | F53: =IF(B53<=3,E53,IF(B53<=20,E53+((B53-3)*$D$2),)) -> 6.62 | K53: 50 | L53: =K53*16 -> 800 | M53: =$I$10+(K52*$I$18) -> 28.23 | N53: =$I$11+(K52*$I$18) -> 44.95
A54: =ROUND(B54,2) -> 2.94 | B54: 2.9375 | C54: 47 | E54: 6.62 | F54: =IF(B54<=3,E54,IF(B54<=20,E54+((B54-3)*$D$2),)) -> 6.62 | K54: 51 | L54: =K54*16 -> 816 | O54: 40.12
A55: =ROUND(B55,2) -> 3 | B55: 3 | C55: 48 | E55: 6.62 | F55: =IF(B55<=3,E55,IF(B55<=20,E55+((B55-3)*$D$2),)) -> 6.62 | K55: 52 | L55: =K55*16 -> 832 | O55: =IF(K54<=50,$I$11+(K54*$I$18),IF(K54<=70,$I$12+((K54-50)*$I$19),"-")) -> 40.87
A56: =ROUND(B56,2) -> 3.25 | B56: 3.25 | C56: 52 | E56: 6.92 | F56: =IF(B56<=3,E56,IF(B56<=20,E56+((B56-3)*$D$2),)) -> 7 | K56: 53 | L56: =K56*16 -> 848 | O56: =IF(K55<=50,$I$11+(K55*$I$18),IF(K55<=70,$I$12+((K55-50)*$I$19),"-")) -> 41.62
A57: =ROUND(B57,2) -> 3.5 | B57: 3.5 | C57: 56 | E57: 6.92 | F57: =IF(B57<=3,E57,IF(B57<=20,E57+((B57-3)*$D$2),)) -> 7.08 | K57: 54 | L57: =K57*16 -> 864 | O57: =IF(K56<=50,$I$11+(K56*$I$18),IF(K56<=70,$I$12+((K56-50)*$I$19),"-")) -> 42.37
A58: =ROUND(B58,2) -> 3.75 | B58: 3.75 | C58: 60 | E58: 6.92 | F58: =IF(B58<=3,E58,IF(B58<=20,E58+((B58-3)*$D$2),)) -> 7.16 | K58: 55 | L58: =K58*16 -> 880 | O58: =IF(K57<=50,$I$11+(K57*$I$18),IF(K57<=70,$I$12+((K57-50)*$I$19),"-")) -> 43.12
A59: =ROUND(B59,2) -> 4 | B59: 4 | C59: 64 | E59: 6.92 | F59: =IF(B59<=3,E59,IF(B59<=20,E59+((B59-3)*$D$2),)) -> 7.24 | K59: 56 | L59: =K59*16 -> 896 | O59: =IF(K58<=50,$I$11+(K58*$I$18),IF(K58<=70,$I$12+((K58-50)*$I$19),"-")) -> 43.87
A60: =ROUND(B60,2) -> 4.25 | B60: 4.25 | C60: 68 | E60: 6.92 | F60: =IF(B60<=3,E60,IF(B60<=20,E60+((B60-3)*$D$2),)) -> 7.32 | K60: 57 | L60: =K60*16 -> 912 | O60: =IF(K59<=50,$I$11+(K59*$I$18),IF(K59<=70,$I$12+((K59-50)*$I$19),"-")) -> 44.62
A61: =ROUND(B61,2) -> 4.5 | B61: 4.5 | C61: 72 | E61: 6.92 | F61: =IF(B61<=3,E61,IF(B61<=20,E61+((B61-3)*$D$2),)) -> 7.4 | K61: 58 | L61: =K61*16 -> 928 | O61: =IF(K60<=50,$I$11+(K60*$I$18),IF(K60<=70,$I$12+((K60-50)*$I$19),"-")) -> 45.37
A62: =ROUND(B62,2) -> 4.75 | B62: 4.75 | C62: 76 | E62: 6.92 | F62: =IF(B62<=3,E62,IF(B62<=20,E62+((B62-3)*$D$2),)) -> 7.48 | K62: 59 | L62: =K62*16 -> 944 | O62: =IF(K61<=50,$I$11+(K61*$I$18),IF(K61<=70,$I$12+((K61-50)*$I$19),"-")) -> 46.12
A63: =ROUND(B63,2) -> 5 | B63: 5 | C63: 80 | E63: 6.92 | F63: =IF(B63<=3,E63,IF(B63<=20,E63+((B63-3)*$D$2),)) -> 7.56 | K63: 60 | L63: =K63*16 -> 960 | O63: =IF(K62<=50,$I$11+(K62*$I$18),IF(K62<=70,$I$12+((K62-50)*$I$19),"-")) -> 46.87
A64: =ROUND(B64,2) -> 5.25 | B64: 5.25 | C64: 84 | E64: 6.92 | F64: =IF(B64<=3,E64,IF(B64<=20,E64+((B64-3)*$D$2),)) -> 7.64 | K64: 61 | L64: =K64*16 -> 976 | O64: =IF(K63<=50,$I$11+(K63*$I$18),IF(K63<=70,$I$12+((K63-50)*$I$19),"-")) -> 47.62
A65: =ROUND(B65,2) -> 5.5 | B65: 5.5 | C65: 88 | E65: 6.92 | F65: =IF(B65<=3,E65,IF(B65<=20,E65+((B65-3)*$D$2),)) -> 7.72 | K65: 62 | L65: =K65*16 -> 992 | O65: =IF(K64<=50,$I$11+(K64*$I$18),IF(K64<=70,$I$12+((K64-50)*$I$19),"-")) -> 48.37
A66: =ROUND(B66,2) -> 5.75 | B66: 5.75 | C66: 92 | E66: 6.92 | F66: =IF(B66<=3,E66,IF(B66<=20,E66+((B66-3)*$D$2),)) -> 7.8 | K66: 63 | L66: =K66*16 -> 1008 | O66: =IF(K65<=50,$I$11+(K65*$I$18),IF(K65<=70,$I$12+((K65-50)*$I$19),"-")) -> 49.12
... A73: =ROUND(B73,2) -> 7.5 | B73: 7.5 | C73: 120 | E73: 6.92 | F73: =IF(B73<=3,E73,IF(B73<=20,E73+((B73-3)*$D$2),)) -> 8.36 | K73: 70 | L73: =K73*16 -> 1120 | O73: =IF(K72<=50,$I$11+(K72*$I$18),IF(K72<=70,$I$12+((K72-50)*$I$19),"-")) -> 54.37
A74: =ROUND(B74,2) -> 7.75 | B74: 7.75 | C74: 124 | E74: 6.92 | F74: =IF(B74<=3,E74,IF(B74<=20,E74+((B74-3)*$D$2),)) -> 8.44 | K74: 71 | L74: =K74*16 -> 1136 | P74: 54.81
A75: =ROUND(B75,2) -> 8 | B75: 8 | C75: 128 | E75: 6.92 | F75: =IF(B75<=3,E75,IF(B75<=20,E75+((B75-3)*$D$2),)) -> 8.52 | K75: 72 | L75: =K75*16 -> 1152 | P75: =IF(K74<=50,$I$11+(K74*$I$18),IF(K74<=70,$I$12+((K74-50)*$I$19),IF(K74<=150,$I$13+((K74-70)*$I$19),))) -> 55.56
A76: =ROUND(B76,2) -> 8.25 | B76: 8.25 | C76: 132 | E76: 6.92 | F76: =IF(B76<=3,E76,IF(B76<=20,E76+((B76-3)*$D$2),)) -> 8.6 | K76: 73 | L76: =K76*16 -> 1168 | P76: =IF(K75<=50,$I$11+(K75*$I$18),IF(K75<=70,$I$12+((K75-50)*$I$19),IF(K75<=150,$I$13+((K75-70)*$I$19),))) -> 56.31
A77: =ROUND(B77,2) -> 8.5 | B77: 8.5 | C77: 136 | E77: 6.92 | F77: =IF(B77<=3,E77,IF(B77<=20,E77+((B77-3)*$D$2),)) -> 8.68 | K77: 74 | L77: =K77*16 -> 1184 | P77: =IF(K76<=50,$I$11+(K76*$I$18),IF(K76<=70,$I$12+((K76-50)*$I$19),IF(K76<=150,$I$13+((K76-70)*$I$19),))) -> 57.06
A78: =ROUND(B78,2) -> 8.75 | B78: 8.75 | C78: 140 | E78: 6.92 | F78: =IF(B78<=3,E78,IF(B78<=20,E78+((B78-3)*$D$2),)) -> 8.76 | K78: 75 | L78: =K78*16 -> 1200 | P78: =IF(K77<=50,$I$11+(K77*$I$18),IF(K77<=70,$I$12+((K77-50)*$I$19),IF(K77<=150,$I$13+((K77-70)*$I$19),))) -> 57.81
A79: =ROUND(B79,2) -> 9 | B79: 9 | C79: 144 | E79: 6.92 | F79: =IF(B79<=3,E79,IF(B79<=20,E79+((B79-3)*$D$2),)) -> 8.84 | K79: 76 | L79: =K79*16 -> 1216 | P79: =IF(K78<=50,$I$11+(K78*$I$18),IF(K78<=70,$I$12+((K78-50)*$I$19),IF(K78<=150,$I$13+((K78-70)*$I$19),))) -> 58.56
A80: =ROUND(B80,2) -> 9.25 | B80: 9.25 | C80: 148 | E80: 6.92 | F80: =IF(B80<=3,E80,IF(B80<=20,E80+((B80-3)*$D$2),)) -> 8.92 | K80: 77 | L80: =K80*16 -> 1232 | P80: =IF(K79<=50,$I$11+(K79*$I$18),IF(K79<=70,$I$12+((K79-50)*$I$19),IF(K79<=150,$I$13+((K79-70)*$I$19),))) -> 59.31
A81: =ROUND(B81,2) -> 9.5 | B81: 9.5 | C81: 152 | E81: 6.92 | F81: =IF(B81<=3,E81,IF(B81<=20,E81+((B81-3)*$D$2),)) -> 9 | K81: 78 | L81: =K81*16 -> 1248 | P81: =IF(K80<=50,$I$11+(K80*$I$18),IF(K80<=70,$I$12+((K80-50)*$I$19),IF(K80<=150,$I$13+((K80-70)*$I$19),))) -> 60.06
A82: =ROUND(B82,2) -> 9.75 | B82: 9.75 | C82: 156 | E82: 6.92 | F82: =IF(B82<=3,E82,IF(B82<=20,E82+((B82-3)*$D$2),)) -> 9.08 | K82: 79 | L82: =K82*16 -> 1264 | P82: =IF(K81<=50,$I$11+(K81*$I$18),IF(K81<=70,$I$12+((K81-50)*$I$19),IF(K81<=150,$I$13+((K81-70)*$I$19),))) -> 60.81
A83: =ROUND(B83,2) -> 10 | B83: 10 | C83: 160 | E83: 6.92 | F83: =IF(B83<=3,E83,IF(B83<=20,E83+((B83-3)*$D$2),)) -> 9.16 | K83: 80 | L83: =K83*16 -> 1280 | P83: =IF(K82<=50,$I$11+(K82*$I$18),IF(K82<=70,$I$12+((K82-50)*$I$19),IF(K82<=150,$I$13+((K82-70)*$I$19),))) -> 61.56
A84: =ROUND(B84,2) -> 10.25 | B84: 10.25 | C84: 164 | E84: 6.92 | F84: =IF(B84<=3,E84,IF(B84<=20,E84+((B84-3)*$D$2),)) -> 9.24 | K84: 81 | L84: =K84*16 -> 1296 | P84: =IF(K83<=50,$I$11+(K83*$I$18),IF(K83<=70,$I$12+((K83-50)*$I$19),IF(K83<=150,$I$13+((K83-70)*$I$19),))) -> 62.31
A85: =ROUND(B85,2) -> 10.5 | B85: 10.5 | C85: 168 | E85: 6.92 | F85: =IF(B85<=3,E85,IF(B85<=20,E85+((B85-3)*$D$2),)) -> 9.32 | K85: 82 | L85: =K85*16 -> 1312 | P85: =IF(K84<=50,$I$11+(K84*$I$18),IF(K84<=70,$I$12+((K84-50)*$I$19),IF(K84<=150,$I$13+((K84-70)*$I$19),))) -> 63.06
A86: =ROUND(B86,2) -> 10.75 | B86: 10.75 | C86: 172 | E86: 6.92 | F86: =IF(B86<=3,E86,IF(B86<=20,E86+((B86-3)*$D$2),)) -> 9.4 | K86: 83 | L86: =K86*16 -> 1328 | P86: =IF(K85<=50,$I$11+(K85*$I$18),IF(K85<=70,$I$12+((K85-50)*$I$19),IF(K85<=150,$I$13+((K85-70)*$I$19),))) -> 63.81
... A123: =ROUND(B123,2) -> 20 | B123: 20 | C123: 320 | E123: 6.92 | F123: =IF(B123<=3,E123,IF(B123<=20,E123+((B123-3)*$D$2),)) -> 12.36 | K123: 120 | L123: =K123*16 -> 1920 | P123: =IF(K122<=50,$I$11+(K122*$I$18),IF(K122<=70,$I$12+((K122-50)*$I$19),IF(K122<=150,$I$13+((K122-70)*$I$19),))) -> 91.56
K124: 121 | L124: =K124*16 -> 1936 | P124: =IF(K123<=50,$I$11+(K123*$I$18),IF(K123<=70,$I$12+((K123-50)*$I$19),IF(K123<=150,$I$13+((K123-70)*$I$19),))) -> 92.31
K125: 122 | L125: =K125*16 -> 1952 | P125: =IF(K124<=50,$I$11+(K124*$I$18),IF(K124<=70,$I$12+((K124-50)*$I$19),IF(K124<=150,$I$13+((K124-70)*$I$19),))) -> 93.06
K126: 123 | L126: =K126*16 -> 1968 | P126: =IF(K125<=50,$I$11+(K125*$I$18),IF(K125<=70,$I$12+((K125-50)*$I$19),IF(K125<=150,$I$13+((K125-70)*$I$19),))) -> 93.81
K127: 124 | L127: =K127*16 -> 1984 | P127: =IF(K126<=50,$I$11+(K126*$I$18),IF(K126<=70,$I$12+((K126-50)*$I$19),IF(K126<=150,$I$13+((K126-70)*$I$19),))) -> 94.56
K128: 125 | L128: =K128*16 -> 2000 | P128: =IF(K127<=50,$I$11+(K127*$I$18),IF(K127<=70,$I$12+((K127-50)*$I$19),IF(K127<=150,$I$13+((K127-70)*$I$19),))) -> 95.31
K129: 126 | L129: =K129*16 -> 2016 | P129: =IF(K128<=50,$I$11+(K128*$I$18),IF(K128<=70,$I$12+((K128-50)*$I$19),IF(K128<=150,$I$13+((K128-70)*$I$19),))) -> 96.06
K130: 127 | L130: =K130*16 -> 2032 | P130: =IF(K129<=50,$I$11+(K129*$I$18),IF(K129<=70,$I$12+((K129-50)*$I$19),IF(K129<=150,$I$13+((K129-70)*$I$19),))) -> 96.81
K131: 128 | L131: =K131*16 -> 2048 | P131: =IF(K130<=50,$I$11+(K130*$I$18),IF(K130<=70,$I$12+((K130-50)*$I$19),IF(K130<=150,$I$13+((K130-70)*$I$19),))) -> 97.56
K132: 129 | L132: =K132*16 -> 2064 | P132: =IF(K131<=50,$I$11+(K131*$I$18),IF(K131<=70,$I$12+((K131-50)*$I$19),IF(K131<=150,$I$13+((K131-70)*$I$19),))) -> 98.31
K133: 130 | L133: =K133*16 -> 2080 | P133: =IF(K132<=50,$I$11+(K132*$I$18),IF(K132<=70,$I$12+((K132-50)*$I$19),IF(K132<=150,$I$13+((K132-70)*$I$19),))) -> 99.06
K134: 131 | L134: =K134*16 -> 2096 | P134: =IF(K133<=50,$I$11+(K133*$I$18),IF(K133<=70,$I$12+((K133-50)*$I$19),IF(K133<=150,$I$13+((K133-70)*$I$19),))) -> 99.81
K135: 132 | L135: =K135*16 -> 2112 | P135: =IF(K134<=50,$I$11+(K134*$I$18),IF(K134<=70,$I$12+((K134-50)*$I$19),IF(K134<=150,$I$13+((K134-70)*$I$19),))) -> 100.56
... K153: 150 | L153: =K153*16 -> 2400 | P153: =IF(K152<=50,$I$11+(K152*$I$18),IF(K152<=70,$I$12+((K152-50)*$I$19),IF(K152<=150,$I$13+((K152-70)*$I$19),))) -> 114.06
K154: 151 | L154: =K154*16 -> 2416 | Q154: 194.95
K155: 152 | L155: =K155*16 -> 2432 | Q155: =IF(K154<=50,$I$11+(K154*$I$18),IF(K154<=70,$I$12+((K154-50)*$I$19),IF(K154<=150,$I$13+((K154-70)*$I$19),IF(K154>150,$I$14+((K154-150)*$I$20))))) -> 195.14
K156: 153 | L156: =K156*16 -> 2448 | Q156: =IF(K155<=50,$I$11+(K155*$I$18),IF(K155<=70,$I$12+((K155-50)*$I$19),IF(K155<=150,$I$13+((K155-70)*$I$19),IF(K155>150,$I$14+((K155-150)*$I$20))))) -> 195.33
K157: 154 | L157: =K157*16 -> 2464 | Q157: =IF(K156<=50,$I$11+(K156*$I$18),IF(K156<=70,$I$12+((K156-50)*$I$19),IF(K156<=150,$I$13+((K156-70)*$I$19),IF(K156>150,$I$14+((K156-150)*$I$20))))) -> 195.52
K158: 155 | L158: =K158*16 -> 2480 | Q158: =IF(K157<=50,$I$11+(K157*$I$18),IF(K157<=70,$I$12+((K157-50)*$I$19),IF(K157<=150,$I$13+((K157-70)*$I$19),IF(K157>150,$I$14+((K157-150)*$I$20))))) -> 195.71
K159: 156 | L159: =K159*16 -> 2496 | Q159: =IF(K158<=50,$I$11+(K158*$I$18),IF(K158<=70,$I$12+((K158-50)*$I$19),IF(K158<=150,$I$13+((K158-70)*$I$19),IF(K158>150,$I$14+((K158-150)*$I$20))))) -> 195.9
K160: 157 | L160: =K160*16 -> 2512 | Q160: =IF(K159<=50,$I$11+(K159*$I$18),IF(K159<=70,$I$12+((K159-50)*$I$19),IF(K159<=150,$I$13+((K159-70)*$I$19),IF(K159>150,$I$14+((K159-150)*$I$20))))) -> 196.09
K161: 158 | L161: =K161*16 -> 2528 | Q161: =IF(K160<=50,$I$11+(K160*$I$18),IF(K160<=70,$I$12+((K160-50)*$I$19),IF(K160<=150,$I$13+((K160-70)*$I$19),IF(K160>150,$I$14+((K160-150)*$I$20))))) -> 196.28
K162: 159 | L162: =K162*16 -> 2544 | Q162: =IF(K161<=50,$I$11+(K161*$I$18),IF(K161<=70,$I$12+((K161-50)*$I$19),IF(K161<=150,$I$13+((K161-70)*$I$19),IF(K161>150,$I$14+((K161-150)*$I$20))))) -> 196.47
K163: 160 | L163: =K163*16 -> 2560 | Q163: =IF(K162<=50,$I$11+(K162*$I$18),IF(K162<=70,$I$12+((K162-50)*$I$19),IF(K162<=150,$I$13+((K162-70)*$I$19),IF(K162>150,$I$14+((K162-150)*$I$20))))) -> 196.66
K164: 161 | L164: =K164*16 -> 2576 | Q164: =IF(K163<=50,$I$11+(K163*$I$18),IF(K163<=70,$I$12+((K163-50)*$I$19),IF(K163<=150,$I$13+((K163-70)*$I$19),IF(K163>150,$I$14+((K163-150)*$I$20))))) -> 196.85
K165: 162 | L165: =K165*16 -> 2592 | Q165: =IF(K164<=50,$I$11+(K164*$I$18),IF(K164<=70,$I$12+((K164-50)*$I$19),IF(K164<=150,$I$13+((K164-70)*$I$19),IF(K164>150,$I$14+((K164-150)*$I$20))))) -> 197.04
K166: 163 | L166: =K166*16 -> 2608 | Q166: =IF(K165<=50,$I$11+(K165*$I$18),IF(K165<=70,$I$12+((K165-50)*$I$19),IF(K165<=150,$I$13+((K165-70)*$I$19),IF(K165>150,$I$14+((K165-150)*$I$20))))) -> 197.23
... K203: 200 | L203: =K203*16 -> 3200 | Q203: =IF(K202<=50,$I$11+(K202*$I$18),IF(K202<=70,$I$12+((K202-50)*$I$19),IF(K202<=150,$I$13+((K202-70)*$I$19),IF(K202>150,$I$14+((K202-150)*$I$20))))) -> 204.26

Sheet MAIN
A1: SKU | B1: LOCATION | C1: DC LIST | D1: CAT | E1: LO-1 | F1: LO-2 | G1: AVG. SALES | H1: RANK | I1: P. COST | J1: Stock Sheet | K1: Freight-FBA | L1: Freight-Canada | M1: Freight-WFS | N1: OLD/NEW | O1: NEW SKU(IMPR.) | P1: TOP 127
A2: B10 | B2: C11-6249-B10 | D2: CFB | E2: Tushar | F2: Darshan | G2: 70 | H2: 13 | I2: 51.06 | J2: 1 | K2: -16.759967 | L2: -52.7 | N2: OLD | P2: TOP 127
A3: B10J | B3: A03-0077-B10J | D3: CFB | E3: Tushar | F3: Darshan | G3: 5 | H3: 314 | I3: 6.71 | J3: 2 | K3: -7.004 | L3: -2.4853295 | N3: OLD
A4: B10X | B4: C12-6285-B10X | D4: CFB | E4: Tushar | F4: Darshan | G4: 17 | H4: 123 | I4: 14.51 | J4: 3 | K4: -10.486876 | L4: -9.3312077 | N4: OLD | P4: TOP 127
A5: B11 | B5: C11-6256-B11 | D5: CFB | E5: Tushar | F5: Darshan | G5: 8 | H5: 108 | I5: 40.44 | J5: 4 | K5: -19.1712 | L5: -31.54 | N5: OLD
A6: B12 | B6: C11-6262-B12 | D6: CFB | E6: Tushar | F6: Darshan | G6: 14 | H6: 76 | I6: 49.59 | J6: 5 | K6: -21.690171 | L6: -38.300555 | N6: OLD | P6: TOP 127
A7: B12F | B7: A07-0273-B12F | D7: CFB | E7: Tushar | F7: Darshan | G7: 13 | H7: 119 | I7: 4.27 | J7: 6 | K7: -1.54 | L7: -3.57 | N7: OLD
A8: B12H | B8: B2-4070-B12H | D8: CFB | E8: Tushar | F8: Darshan | G8: 8 | H8: 232 | I8: 9.42 | J8: 7 | K8: -8.4795737 | L8: -8.277391 | N8: OLD
A9: B12J | B9: C12-6281-B12J | D9: CFB | E9: Tushar | F9: Darshan | G9: 7 | H9: 236 | I9: 14.72 | J9: 8 | K9: -15.036053 | L9: -12.200814 | N9: OLD
A10: B12X | B10: C4-6059-B12X | D10: CFB | E10: Tushar | F10: Darshan | G10: 22 | H10: 103 | I10: 26.98 | J10: 9 | K10: -15.760168 | L10: -7.5770381 | N10: OLD | P10: TOP 127
A11: B9J | B11: A07-0269-B9J | D11: CFB | E11: Tushar | F11: Darshan | G11: 40 | H11: 131 | I11: 3.99 | J11: 10 | K11: -6.0278534 | L11: -2.8322584 | N11: OLD | P11: TOP 127
A12: BS10 | B12: C10-6199-BS10 | D12: CFB | E12: Tushar | F12: Darshan | G12: 44 | H12: 57 | I12: 26.17 | J12: 11 | K12: -14.822188 | L12: -29.8 | N12: OLD | P12: TOP 127
A13: BS9 | B13: C12-6277-BS9 | D13: CFB | E13: Tushar | F13: Darshan | G13: 13 | H13: 157 | I13: 18.93 | J13: 12 | K13: -15.404284 | L13: -12.39 | N13: OLD | P13: TOP 127
A14: CP-1-2425F | B14: A28-1033-CP-1-2425F | D14: CP | E14: Shubham | F14: Darshan | G14: 6 | H14: 213 | I14: 19.8 | J14: 13 | K14: -6.2999778 | L14: -1.9356284 | N14: OLD | P14: TOP 127
A15: CP-2-2425F | B15: A07-0281-CP-2-2425F | D15: CP | E15: Shubham | F15: Darshan | G15: 3 | H15: 251 | I15: 37.68 | J15: 14 | K15: -2.9065608 | L15: NA | N15: OLD
A16: CP-3-2425F | B16: C12-6323-CP-3-2425F | D16: CP | E16: Shubham | F16: Darshan | G16: 3 | H16: 248 | I16: 51.7 | J16: 15 | K16: -7.745 | L16: -3.8545329 | N16: OLD | P16: TOP 127
A17: CT-AM04 | B17: A27-1021-CT-AM04 | D17: CT | E17: Ronak | F17: Darshan | G17: 42 | H17: 129 | I17: 6.07 | J17: 16 | K17: -1.4121591 | L17: -0.8 | N17: OLD | P17: TOP 127
A18: CT-AM125 | B18: B1-4023-CT-AM125 | D18: CT | E18: Ronak | F18: Darshan | G18: 13 | H18: 120 | I18: 17.17 | J18: 17 | K18: -5.2866667 | L18: NA | N18: OLD
A19: CT-AS10 | B19: B1-4029-CT-AS10 | D19: CT | E19: Ronak | F19: Darshan | G19: 9 | H19: 220 | I19: 11.91 | J19: 18 | K19: NA | L19: NA | N19: OLD
A20: CT-TC22 | B20: B5-4253-CT-TC22 | D20: CT | E20: Ronak | F20: Darshan | G20: 24 | H20: 49 | I20: 60.85 | J20: 19 | K20: -11.560109 | L20: -2.27 | N20: OLD | P20: TOP 127
A21: CT-WK22 | B21: B1-4049-CT-WK22 | C21: DC 25 | D21: CT | E21: Ronak DC | F21: DC2 | G21: 6 | H21: 134 | I21: 29.72 | J21: 20 | K21: -12.96875 | L21: NA | N21: OLD
A22: EH-03 | B22: A26-0966-EH-03 | D22: EH | E22: Tejas | F22: Darshan | G22: 12 | H22: 178 | I22: 10.52 | J22: 21 | K22: -0.5725 | L22: -0.38 | N22: OLD
A23: FP-61 | B23: A27-1023-FP-61 | D23: FP | E23: Shubham | F23: Darshan | G23: 49 | H23: 158 | I23: 3.03 | J23: 22 | K23: -0.68279167 | L23: -0.42867746 | N23: OLD | P23: TOP 127
A24: FP-64 | B24: A25-0929-FP-64 | D24: FP | E24: Shubham | F24: Darshan | G24: 8 | H24: 468 | I24: 3.03 | J24: 23 | K24: -0.47813953 | L24: NA | N24: OLD
A25: FP-68 | B25: A25-0935-FP-68 | D25: FP | E25: Shubham | F25: Darshan | G25: 80 | H25: 78 | I25: 3.03 | J25: 24 | K25: -0.56966667 | L25: -0.12 | N25: OLD
A26: FP-71 | B26: A07-0285-FP-71 | D26: FP | E26: Shubham | F26: Darshan | G26: 89 | H26: 56 | I26: 8.8 | J26: 25 | K26: -1.3845455 | L26: -1.4809243 | N26: OLD | P26: TOP 127
A27: FPB-02 | B27: A26-0980-FPB-02 | C27: SEA | D27: FPB | E27: Tejas | F27: Darshan | G27: 0 | I27: 22 | J27: 26 | K27: -3.7722222 | L27: NA | N27: OLD
A28: HB-10P | B28: C9-6161-HB-10P | D28: HB | E28: Ronak | F28: Darshan | G28: 54 | H28: 8 | I28: 39.15 | J28: 27 | K28: -6.8771632 | L28: -5.4783643 | M28: -4 | N28: OLD | P28: TOP 127
A29: HB-18 | B29: B2-4073-HB-18 | D29: HB | E29: Ronak | F29: Darshan | G29: 9 | H29: 69 | I29: 30.4 | J29: 28 | K29: -4.21 | L29: -16.651551 | N29: OLD
A30: HB-25 | B30: B2-4059-HB-25 | D30: HB | E30: Ronak | F30: Darshan | G30: 12 | H30: 67 | I30: 33.86 | J30: 29 | K30: -7.8242874 | L30: -20.125094 | N30: OLD | P30: TOP 127
A31: HB-35 | B31: B1-4031-HB-35 | D31: HB | E31: Ronak | F31: Darshan | G31: 7 | H31: 104 | I31: 46.04 | J31: 30 | K31: -10.635167 | L31: -43.190765 | N31: OLD
A32: IB-A06 | B32: C5-6071-IB-A06 | D32: IB | E32: Tushar | F32: Darshan | G32: 43 | H32: 52 | I32: 13.21 | J32: 31 | K32: -5.5303333 | L32: -3.7730392 | N32: OLD | P32: TOP 127
A33: IB-A16 | B33: D7-8026-IB-A16 | D33: IB | E33: Tushar | F33: Darshan | G33: 77 | H33: 20 | I33: 29.04 | J33: 32 | K33: -11.962972 | L33: -11.385153 | N33: OLD | P33: TOP 127
A34: IB-C05 | B34: B2-4091-IB-C05 | D34: IB | E34: Tushar | F34: Darshan | G34: 28 | H34: 63 | I34: 14.92 | J34: 33 | K34: -5.64 | L34: -3.514046 | N34: OLD | P34: TOP 127
A35: IB-C12 | B35: D6-8023-IB-C12 | C35: DC 25 | D35: IB | E35: Tushar DC | F35: DC2 | G35: 54 | H35: 30 | I35: 31.35 | J35: 34 | K35: -12.644096 | L35: -7.2306863 | M35: -6.24 | N35: OLD | P35: TOP 127
A36: IB-D10 | B36: D8-8032-IB-D10 | C36: DC 25 | D36: IB | E36: Tushar DC | F36: DC2 | G36: 10 | H36: 64 | I36: 33.55 | J36: 35 | K36: -11.815 | L36: -11.5434 | N36: OLD
A37: IB-F08 | B37: D10-8039-IB-F08 | D37: IB | E37: Tushar | F37: Darshan | G37: 22 | H37: 45 | I37: 32.14 | J37: 36 | K37: -9.4857188 | L37: -20.864074 | N37: OLD | P37: TOP 127
A38: IB-G08 | B38: D7-8028-IB-G08 | C38: DC 25 | D38: IB | E38: Tushar DC | F38: DC2 | G38: 52 | H38: 24 | I38: 41.8 | J38: 37 | K38: -8.6113379 | L38: -14.534708 | N38: OLD | P38: TOP 127
A39: JMT-02 | B39: D11-8043-JMT-02 | D39: JMT | E39: Shubham | F39: Darshan | G39: 2 | H39: 216 | I39: 127.96 | J39: 38 | K39: -23.323333 | L39: -31.465189 | N39: OLD | P39: TOP 127
A40: JMT-03 | B40: D6-8021-JMT-03 | D40: JMT | E40: Shubham | F40: Darshan | G40: 4 | H40: 44 | I40: 160.06 | J40: 39 | K40: -21.772033 | L40: -39.025253 | N40: OLD | P40: TOP 127
A41: JMT-103 | B41: A04-0145-JMT-103 | D41: JMT | E41: Shubham | F41: Darshan | G41: 54 | H41: 43 | I41: 13.2 | J41: 40 | K41: -0.9078 | L41: -0.40616381 | M41: -0.34904762 | N41: OLD | P41: TOP 127
A42: JMT-118 | B42: A07-0283-JMT-118 | D42: JMT | E42: Shubham | F42: Darshan | G42: 166 | H42: 15 | I42: 8.8 | J42: 41 | K42: -1.4822336 | L42: -0.81093903 | M42: -0.723 | N42: OLD | P42: TOP 127
A43: JMT-25 | B43: C4-6064-JMT-25 | D43: JMT | E43: Shubham | F43: Darshan | G43: 2 | H43: 175 | I43: 66 | J43: 42 | K43: -10.48723 | L43: -3.7375334 | N43: OLD | P43: TOP 127
A44: JMT-59 | B44: D11-8042-JMT-59 | D44: JMT | E44: Shubham | F44: Darshan | G44: 157 | H44: 6 | I44: 55 | J44: 43 | K44: -9.3976845 | L44: -3.34 | N44: OLD | P44: TOP 127
A45: JMT-96 | B45: A24-0841-JMT-96 | D45: JMT | E45: Shubham | F45: Darshan | G45: 34 | H45: 72 | I45: 9.69 | J45: 44 | K45: -1.7146751 | L45: -4.43 | N45: OLD
A46: MFI-13 | B46: E1-9001-MFI-13 | D46: PF | E46: Shubham | F46: Darshan | G46: 1 | H46: 37 | I46: 200.2 | J46: 45 | K46: -37.47 | L46: NA | N46: OLD
A47: PFB-01 | B47: A05-0169-PFB-01 | D47: PFB | E47: Shubham | F47: Darshan | G47: 11 | H47: 109 | I47: 40.7 | J47: 46 | K47: -3.5766667 | L47: -19.464676 | N47: OLD
A48: PFI-10 | B48: D25-8099-PFI-10 | D48: PF | E48: Shubham | F48: Darshan | G48: 381 | H48: 1 | I48: 63.8 | J48: 47 | K48: -11.77136 | L48: -15.885518 | M48: -6.2844 | N48: OLD | P48: TOP 127
A49: PFI-20 | B49: D21-8082-PFI-20 | D49: PF | E49: Shubham | F49: Darshan | G49: 364 | H49: 2 | I49: 83.6 | J49: 48 | K49: -16.206324 | L49: -10.39 | M49: -6.33 | N49: OLD | P49: TOP 127
A50: PFO-10 | B50: D19-8073-PFO-10 | D50: PF | E50: Shubham DC | F50: DC2 | G50: 30 | H50: 23 | I50: 66 | J50: 49 | K50: -6.0437037 | L50: -22.934577 | N50: OLD
A51: RCB-02 | B51: A24-0877-RCB-02 | D51: RCB | E51: Tushar | F51: Darshan | G51: 33 | H51: 83 | I51: 22 | J51: 50 | K51: -1.74975 | L51: -0.96079149 | N51: OLD | P51: TOP 127
A52: RCB-03 | B52: B4-4205-RCB-03 | D52: RCB | E52: Tushar | F52: Darshan | G52: 13 | H52: 159 | I52: 20.35 | J52: 51 | K52: -8.341 | L52: NA | N52: OLD
A53: RCB-06 | B53: B5-4259-RCB-06 | D53: RCB | E53: Tushar | F53: Darshan | G53: 26 | H53: 41 | I53: 14.85 | J53: 52 | K53: -4.542 | L53: -8.531523 | N53: OLD | P53: TOP 127
A54: RCB-07 | B54: C1-6027-RCB-07 | D54: RCB | E54: Tushar | F54: Darshan | G54: 227 | H54: 14 | I54: 4.4 | J54: 53 | K54: -1.397933 | L54: -1.6804157 | N54: OLD | P54: TOP 127
A55: RCB-09 | B55: A05-0207-RCB-09 | D55: RCB | E55: Tushar | F55: Darshan | G55: 3 | H55: 423 | I55: 5.84 | J55: 54 | K55: -1.7246875 | L55: NA | N55: OLD
A56: S21 | B56: C12-6279-S21 | D56: HS | E56: Tushar | F56: Darshan | G56: 9 | H56: 138 | I56: 27.5 | J56: 55 | K56: -10.037134 | L56: -8.1197536 | N56: OLD | P56: TOP 127
A57: S21X | B57: A04-0121-S21X | D57: HS | E57: Tushar | F57: Darshan | G57: 2 | H57: 316 | I57: 14.3 | J57: 56 | K57: -7.4497834 | L57: -7.17 | N57: OLD
A58: S25 | B58: C2-6033-S25 | D58: HS | E58: Tushar | F58: Darshan | G58: 9 | H58: 162 | I58: 30.8 | J58: 57 | K58: -12.176047 | L58: -16.06 | N58: OLD | P58: TOP 127
A59: S25J | B59: A03-0073-S25J | D59: HS | E59: Tushar | F59: Darshan | G59: 12 | H59: 155 | I59: 8.8 | J59: 58 | K59: -4.6684807 | L59: -5.33 | N59: OLD
A60: S25X | B60: C12-6287-S25X | D60: HS | E60: Tushar | F60: Darshan | G60: 2 | H60: 130 | I60: 17.05 | J60: 59 | K60: -7.28329 | L60: -8.6701117 | N60: OLD | P60: TOP 127
A61: S9J | B61: A28-1040-S9J | D61: HS | E61: Tushar | F61: Darshan | G61: 5 | H61: 271 | I61: 6.64 | J61: 60 | K61: -6.0791067 | L61: -5.41 | N61: OLD
A62: S9X | B62: A06-0217-S9X | D62: HS | E62: Tushar | F62: Darshan | G62: 6 | H62: 246 | I62: 12.1 | J62: 61 | K62: -5.458534 | L62: -5.4790975 | N62: OLD | P62: TOP 127
A63: V2 | B63: C8-6128-V2 | D63: VB | E63: Tushar | F63: Darshan | G63: 59 | H63: 25 | I63: 18.7 | J63: 62 | K63: -7.8330575 | L63: -3.6999724 | N63: OLD | P63: TOP 127
A64: V2-1212 | B64: C9-6157-V2-1212 | D64: VB | E64: Tushar | F64: Darshan | G64: 48 | H64: 86 | I64: 4.4 | J64: 63 | K64: -1.5114706 | L64: -2.1 | N64: OLD | P64: TOP 127
A65: V2-1224 | B65: C9-6156-V2-1224 | D65: VB | E65: Tushar | F65: Darshan | G65: 37 | H65: 60 | I65: 9.35 | J65: 64 | K65: -6.7716868 | L65: -9.1401007 | N65: OLD | P65: TOP 127
A66: V2-1824 | B66: C4-6058-V2-1824 | D66: VB | E66: Tushar | F66: Darshan | G66: 70 | H66: 33 | I66: 10.07 | J66: 65 | K66: -7.1279447 | L66: -4.05 | N66: OLD | P66: TOP 127
A67: V2E | B67: C3-6047-V2E | D67: VB | E67: Tushar | F67: Darshan | G67: 19 | H67: 107 | I67: 13.75 | J67: 66 | K67: -7.0962811 | L67: -7.6806032 | N67: OLD | P67: TOP 127
A68: V2F | B68: C1-6001-V2F | D68: VB | E68: Tushar | F68: Darshan | G68: 14 | H68: 82 | I68: 20.9 | J68: 67 | K68: -8.9927748 | L68: -18.59 | N68: OLD | P68: TOP 127
A69: V4 | B69: C1-6007-V4 | D69: VB | E69: Tushar | F69: Darshan | G69: 12 | H69: 66 | I69: 25.55 | J69: 68 | K69: -10.925857 | L69: -6.8435617 | N69: OLD | P69: TOP 127
A70: V4-1212 | B70: C9-6153-V4-1212 | D70: VB | E70: Tushar | F70: Darshan | G70: 14 | H70: 142 | I70: 6.6 | J70: 69 | K70: -1.623125 | L70: -2.5031725 | N70: OLD
A71: V4-1224 | B71: C8-6131-V4-1224 | D71: VB | E71: Tushar | F71: Darshan | G71: 59 | H71: 38 | I71: 11.32 | J71: 70 | K71: -5.354388 | L71: -3.0794302 | N71: OLD | P71: TOP 127
A72: V4-1824 | B72: C4-6061-V4-1824 | D72: VB | E72: Tushar | F72: Darshan | G72: 68 | H72: 35 | I72: 16.5 | J72: 71 | K72: -6.0848173 | L72: -4.35 | N72: OLD | P72: TOP 127
A73: V4E | B73: C5-6074-V4E | D73: VB | E73: Tushar | F73: Darshan | G73: 7 | H73: 124 | I73: 23.1 | J73: 72 | K73: -10.062052 | L73: -10.45 | N73: OLD
A74: V4F | B74: C8-6129-V4F | D74: VB | E74: Tushar | F74: Darshan | G74: 15 | H74: 68 | I74: 30.8 | J74: 73 | K74: -6.8184204 | L74: -12.44 | N74: OLD | P74: TOP 127
A75: V5 | B75: C1-6011-V5 | D75: VB | E75: Tushar | F75: Darshan | G75: 6 | H75: 144 | I75: 41.8 | J75: 74 | K75: -12.103559 | L75: -28.331021 | N75: OLD
A76: V6 | B76: D10-8038-V6 | D76: VB | E76: Tushar | F76: Darshan | G76: 37 | H76: 26 | I76: 51.33 | J76: 75 | K76: -12.455389 | L76: -14.89 | N76: OLD | P76: TOP 127
A77: V7 | B77: D6-8022-V7 | D77: VB | E77: Tushar | F77: Darshan | G77: 5 | H77: 110 | I77: 69.62 | J77: 76 | K77: -14.774333 | L77: -30.772677 | N77: OLD
A78: WR-A118 | B78: A06-0233-WR-A118 | D78: WR | E78: Shubham | F78: Darshan | G78: 7 | H78: 262 | I78: 7.7 | J78: 77 | K78: -1.0382143 | L78: NA | N78: OLD
A79: WR-A124 | B79: A27-1011-WR-A124 | D79: WR | E79: Shubham | F79: Darshan | G79: 1 | H79: 444 | I79: 12.25 | J79: 78 | K79: NA | L79: NA | N79: OLD
A80: WR-A130 | B80: A23-0824-WR-A130 | D80: WR | E80: Shubham | F80: Darshan | G80: 2 | H80: 369 | I80: 10.45 | J80: 79 | K80: NA | L80: NA | N80: OLD
A81: WR-A136 | B81: A25-0903-WR-A136 | D81: WR | E81: Shubham | F81: Darshan | G81: 1 | H81: 516 | I81: 14.3 | J81: 80 | K81: NA | L81: NA | N81: OLD
A82: WR-A142 | B82: A27-0998-WR-A142 | D82: WR | E82: Shubham | F82: Darshan | G82: 1 | H82: 548 | I82: 19.8 | J82: 81 | K82: NA | L82: NA | N82: OLD
A83: WR-A160 | B83: A06-0263-WR-A160 | D83: WR | E83: Shubham | F83: Darshan | G83: 2 | H83: 453 | I83: 27.5 | J83: 82 | K83: NA | L83: NA | N83: OLD
A84: WR-A212 | B84: A04-0133-WR-A212 | D84: WR | E84: Shubham | F84: Darshan | G84: 152 | H84: 29 | I84: 6.36 | J84: 83 | K84: -1.0146091 | L84: -0.93143648 | N84: OLD | P84: TOP 127
A85: WR-A218 | B85: A25-0905-WR-A218 | D85: WR | E85: Shubham | F85: Darshan | G85: 20 | H85: 87 | I85: 11.09 | J85: 84 | K85: -1.329 | L85: -1.5552255 | N85: OLD
A86: WR-A224 | B86: A24-0871-WR-A224 | D86: WR | E86: Shubham | F86: Darshan | G86: 3 | H86: 292 | I86: 17.64 | J86: 85 | K86: -1.637 | L86: NA | N86: OLD
A87: WR-A230 | B87: A28-1067-WR-A230 | D87: WR | E87: Shubham | F87: Darshan | G87: 20 | H87: 102 | I87: 16.37 | J87: 86 | K87: -1.9075595 | L87: -1.5235656 | N87: OLD | P87: TOP 127
A88: WR-A236 | B88: A24-0868-WR-A236 | D88: WR | E88: Shubham | F88: Darshan | G88: 3 | H88: 284 | I88: 19.8 | J88: 87 | K88: -2.1991667 | L88: NA | N88: OLD
A89: WR-A242 | B89: A03-0089-WR-A242 | D89: WR | E89: Shubham | F89: Darshan | G89: 6 | H89: 115 | I89: 24.5 | J89: 88 | K89: -2.523 | L89: -15.94917 | N89: OLD
A90: WR-A260 | B90: A28-1085-WR-A260 | D90: WR | E90: Shubham | F90: Darshan | G90: 10 | H90: 97 | I90: 29.45 | J90: 89 | K90: -3.6988889 | L90: -18.41579 | N90: OLD
A91: WR-B215 | B91: A26-0967-WR-B215 | D91: WR | E91: Shubham | F91: Darshan | G91: 9 | H91: 201 | I91: 14.85 | J91: 90 | K91: NA | L91: NA | N91: OLD
A92: WR-B224 | B92: A03-0099-WR-B224 | D92: WR | E92: Shubham | F92: Darshan | G92: 2 | H92: 328 | I92: 23.1 | J92: 91 | K92: NA | L92: NA | N92: OLD
A93: Z4 | B93: C11-6259-Z4 | D93: CFB | E93: Tushar | F93: Darshan | G93: 20 | H93: 46 | I93: 66.11 | J93: 92 | K93: -19.213333 | L93: -44.89 | N93: OLD | P93: TOP 127
A94: Z4F | B94: A03-0114-Z4F | D94: CFB | E94: Tushar | F94: Darshan | G94: 107 | H94: 40 | I94: 2.72 | J94: 93 | K94: -0.89333333 | L94: -3.93 | M94: -0.2290625 | N94: OLD | P94: TOP 127
A95: Z4F2 | B95: C12-6289-Z4F2 | D95: CFB | E95: Tushar | F95: Darshan | G95: 75 | H95: 55 | I95: 5.25 | J95: 94 | K95: -1.2253571 | L95: -4.4790496 | M95: -0.458125 | N95: OLD | P95: TOP 127
A96: PFB-03 | B96: A06-0221-PFB-03 | D96: PFB | E96: Shubham | F96: Darshan | G96: 15 | H96: 71 | I96: 46.45 | J96: 95 | K96: -7.0595833 | L96: -6.28 | N96: OLD
A97: PFB-08 | B97: A24-0847-PFB-08 | D97: PFB | E97: Shubham | F97: Darshan | G97: 1 | H97: 163 | I97: 31.91 | J97: 96 | K97: -6.715 | L97: -21.204632 | N97: OLD
A98: JMT-134 | B98: A03-0111-JMT-134 | D98: JMT | E98: Shubham | F98: Darshan | G98: 28 | H98: 85 | I98: 10.18 | J98: 97 | K98: -6.3928222 | L98: -1.56 | N98: OLD | P98: TOP 127
A99: HB-31P | B99: B3-4145-HB-31P | D99: HB | E99: Ronak | F99: Darshan | G99: 10 | H99: 95 | I99: 53.3 | J99: 98 | K99: -12.684805 | L99: -17.33 | N99: OLD
A100: FAB-44 | B100: C10-6215-FAB-44 | C100: IMP 502 | D100: FAB | E100: DC | F100: DC2 | G100: 16 | H100: 42 | I100: 92.35 | J100: 99 | K100: -15.363 | L100: -19.288982 | N100: OLD | O100: FAB-502 | P100: TOP 127
...

Sheet State
A1: Row Labels | B1: Real State | C1: Remarks
A2: AA | B2: AA
A3: AB | B3: AB
A4: AE | B4: AE
A5: Aguascalientes | B5: AG
A6: AK | B6: AK
A7: AL | B7: AL
A8: ALABAMA | B8: AL
A9: Alaska | B9: AK
A10: Alberta | B10: AB
A11: Antioquia | B11: CO-ANT
A12: AP | B12: AP
A13: AR | B13: AR
... A19: BC | B19: BC
A20: Bogotá | B20: 0
A21: Bolívar | B21: 0
A22: British Columbia | B22: BC
A23: CA | B23: CA
A24: Ca. | B24: CA
A25: Cali | B25: CA
A26: CALIFORNIA | B26: CA
A27: CHIAPAS | B27: CS
A28: CO | B28: CO
A29: Colorado | B29: CO
A30: Connecticut | B30: CT
A31: Ct | B31: CT
A32: DC | B32: DC
A33: DE | B33: DE
... A39: GEORGIA | B39: GA
A40: Girón | B40: 0
A41: GU | B41: GU
A42: GUANAJUATO | B42: GJ
A43: HAWAII | B43: HI
A44: HI | B44: HI
A45: HIDALGO | B45: HD
A46: IA | B46: IA
A47: ID | B47: ID
A48: Idaho | B48: ID
A49: IL | B49: IL
A50: ILLINOIS | B50: IL
A51: IN | B51: IN
A52: Indiana | B52: IN
... A121: Québec | B121: QC
A122: Región metropolitana | B122: 0
A123: Rhode Island | B123: RI
A124: RI | B124: RI
A125: Saskatchewan | B125: SK
A126: SC | B126: SC
A127: SD | B127: SD
A128: SK | B128: SK
A129: SOUTH CAROLINA | B129: SC
A130: TENNESSEE | B130: TN
A131: TEXAS | B131: TX
A132: TN | B132: TN
A133: TX | B133: TX
A134: Ut | B134: UT
... A161: N.Y. | B161: NY
A162: Lithrodontas
A163: Antioquia /Medellín / barrio laureles | B163: CO | C163: (in COLOMBIA)
A164: Colombia | B164: CO
A165: South Dakota | B165: SD
A166: Kuwait | B166: KW
A167: Meta
A168: Eastern Province
A169: Tn.
A170: CIUDAD DE MÉXICO | B170: CDMX
A171: Norte de Santander | B171: CO-NSA
A172: Aichi-ken
A173: Callao | B173: PE CLL
A174: Valparaiso | B174: IN
A175: NSW | B175: NSW
A176: San Martin | B176: MF
A177: Bogota D.C.
A178: Cordoba/Montería
A179: CIUDAD DE MEXICO | B179: CDMX
A180: TODOS SANTOS
A181: Gauteng | B181: ZA-GP
A182: Queensland | B182: QLD
A183: JALISCO | B183: JA
A184: wi.
A185: Israel | B185: IL
A186: Caldas | B186: CO-CAL
A187: Antwerpen | B187: AN
A188: Roslev
A189: Mexico city | B189: MX
A190: VA - Virginia | B190: VA
A191: BOGOTA_DC
A192: Norte
A193: San José, Costa Rica | B193: CSTR
A194: TARAPACA
A195: Nouveau-Brunswick | B195: NB
A196: Arequipa - Arequipa
A197: Jeju-Do
A198: Danmark | B198: DK
A199: La Paz
A200: BAJA CALIFORNIA
A201: N.J.
A202: Pichincha
A203: Mi.
A204: SONORA
...

Sheet ALL SKU
A1: Row Labels | B1: SKU WITH BRACKET
A2: 00001Q01T | B2: CB-S1
A3: 00002Q01T | B3: CB-S2
A4: 00003Q01T | B4: CB-Z1
A5: 00004Q01T | B5: CB-Z2
A6: 00005Q01A | B6: CR-1
A7: 00006Q01A | B7: CR-2
A8: 00007Q01A | B8: CR-3
A9: 00008Q01A | B9: CR-4
A10: 00009Q01T | B10: B10J
A11: 00010Q01T | B11: B10X
A12: 00011Q01P | B12: B11
... A11975: FAB-432 + FAB-435 (HB) | B11975: FAB-432+FAB-435

Sheet Listing Price
A1: Row Labels | B1: No | C1: 5% discount | D1: Lower Price Limit
A2: B10 | B2: 1 | C2: 112.2926 | D2: 112.29
A3: B10J | B3: 2 | C3: 31.350059 | D3: 31.35
A4: B10X | B4: 3 | C4: 58.91674 | D4: 58.92
A5: B11 | B5: 4 | C5: 103.29737 | D5: 103.3
A6: B12 | B6: 5 | C6: 128.31234 | D6: 128.31
A7: B12F | B7: 6 | C7: 24.379923 | D7: 24.38
A8: B12H | B8: 7 | C8: 38.220803 | D8: 38.22
A9: B12J | B9: 8 | C9: 51.414559 | D9: 51.41
A10: B12X | B10: 9 | C10: 75.953353 | D10: 75.95
A11: B9J | B11: 10 | C11: 24.864766 | D11: 24.86
A12: BS10 | B12: 11 | C12: 82.755802 | D12: 82.76
A13: BS13 | B13: 12 | C13: 84.0405 | D13: 84.04
... A479: RCB-13 | B479: 740 | C479: 21.499556 | D479: 21.5
A480: UPF-POT | B480: NA | C480: 59.375 | D480: 59.38
A481: JMT-120 | B481: NA | C481: 23.845 | D481: 23.85
A482: JMT-91 | B482: NA | C482: 20.00519 | D482: 20.01
A483: UPFR-10 | B483: NA | C483: 30.1853 | D483: 30.19
A484: UFAB-94 | B484: NA | C484: 47.9655 | D484: 47.97
A485: UPO-AC2 | B485: NA | C485: 51.7655 | D485: 51.77
A486: UFAB-339 | B486: NA | C486: 30.4855 | D486: 30.49
A487: BA-H05 | B487: NA | C487: 15.6655 | D487: 15.67
A488: FAB-36 | B488: NA | C488: 37.8955 | D488: 37.9
A489: JMT-116 | B489: NA | C489: 33.7155 | D489: 33.72
A490: PF-10 | B490: NA | C490: 69.8155 | D490: 69.82
A491: UPFI-O10 | B491: NA | C491: 40.736 | D491: 40.74
... A675: UJMT-59 | B675: NA | C675: 54.8948 | D675: 54.89
A676: CR-3 | B676: 20 | C676: 0 | D676: 0
A677: CR-G1510 | B677: 21 | C677: 0 | D677: 0
A678: CR-G1905 | B678: 22 | C678: 0 | D678: 0
A679: CR-G2505 | B679: 23 | C679: 0 | D679: 0
A680: CR-G5005 | B680: 24 | C680: 0 | D680: 0
A681: FB-0303 | B681: 33 | C681: 0 | D681: 0
A682: FP-66 | B682: 37 | C682: 0 | D682: 0
A683: FP-69 | B683: 39 | C683: 0 | D683: 0
A684: FPB-01 | B684: 44 | C684: 0 | D684: 0
A685: FPB-02 | B685: 45 | C685: 0 | D685: 0
A686: FPB-03 | B686: 46 | C686: 0 | D686: 0
A687: GT-12 | B687: 47 | C687: 0 | D687: 0
... A945: ARPZ007 | B945: 748 | C945: 0 | D945: 0

Sheet CALCULATOR MAIN
F4: FBA FEES CALCULATOR | O4: Removal Fees Calculator | W4: Liquidation Fees
W5: Weight (lb) | X5: Processing Fee ($)
G6: Enter Values | J6: Tier | P6: Enter Values | S6: Tier | T6: Size Tier | W6: ='[1]Main Sheet'!D6 -> 29 | X6: =IF(W6<=0.5, 0.25, IF(W6<=1, 0.3, IF(W6<=2, 0.35, IF(W6>2, 0.4 + 0.2 * (W6 - 2), "")))) -> 5.8
G7: Weight(oz) | H7: =M12*16 -> 464 | P7: Weight(oz) | Q7: =#REF!*16 -> #REF!
G8: Longest | H8: 61 | J8: Small standard-size | M8: Tier | P8: Tier | Q8: =VLOOKUP($M$9,'[1]REMOVAL FEES'!$K$1:$L$7,2,FALSE) -> 2 | S8: 1 | T8: Small standard-size
G9: Median | H9: 9 | J9: Large standard-size | M9: =IF(AND($M$12<=J50,$H$8<=G50,$H$9<=H50,$H$10<=I50),A50,IF(AND($M$12<=J51,$H$8<=G51,$H$9<=H51,$H$10<=I51),A51,IF(AND($H$8<=G52,$H$9<=H52,$H$10<=I52,$M$12<=J52),A52,IF(AND($M$12<=J53,OR(H$8>G53,$H$9>H53,$H$10>I53)),A53,IF(AND($M$12>J53,$M$12<=J54),A54,IF(AND($M$12>J54,$M$12<=J55),A55,A56)))))) -> Extra-large 0 to 50 lb | P9: Weight (lb) | Q9: =M12 -> 29 | T9: Large standard-size
G10: Shortest | H10: 6 | J10: Large bulky | M10: Fees | P10: Qty | Q10: 1 | S10: 2 | T10: Large bulky
G11: Weight(lbs) | H11: ='[1]Main Sheet'!D6 -> 29 | J11: Extra-large 0 to 50 lb | M11: =IFERROR(VLOOKUP(ROUNDUP($H$7,0),'FBA FEES'!$L$2:$Q$203,MATCH(M9,'FBA FEES'!$L$2:$Q$2,0),FALSE),VLOOKUP(ROUNDUP($H$7,0),'FBA FEES'!$C$6:$F$123,MATCH(M9,'FBA FEES'!$C$6:$F$6,0),FALSE)) -> 36.97 | T11: Extra-large 0 to 50 lb
G12: Diemensional Weight (lb) | H12: =(H8*H9*H10)/139 -> 23.697842 | J12: Extra-large 50+ to 70 lb | M12: =ROUND(MAX($H$11,$H$12),0) -> 29 | P12: Tier | Q12: ='[1]REMOVAL CHART'!$B$20 -> Large bulky, extra-large and special handling items | T12: Extra-large 50+ to 70 lb | W12: Grade and Resell Fees
J13: Extra-large 70+ to 150 lb | P13: Fees | Q13: ='[1]REMOVAL CHART'!$B$21 -> 15.38 | T13: Extra-large 70+ to 150 lb | W13: Price ($) | X13: Weight (lb) | Y13: Amazon Fee ($) | Z13: Profit ($)
G14: =M10 -> Fees | H14: =M11 -> 36.97 | J14: Extra-large 150+ lb | T14: Extra-large 150+ lb | W14: ='[1]Main Sheet'!J6 -> 12 | X14: ='[1]Main Sheet'!D6 -> 29 | Y14: =IF(X14<=1, 1.5, IF(X14<=21, 1.8, IF(X14<=151, 2.65, 4.1))) -> 2.65 | Z14: =W14-Y14 -> 9.35
M17: =IF(AND($H10<=J50,$A10<=G50,$F10<=H50,$G10<=I50),A50,IF(AND($H10<=J51,$A10<=G51,$F10<=H51,$G10<=I51),A51,IF(AND($A10<=G52,$F10<=H52,$G10<=I52,$H10<=J52),A52,IF(AND($H10<=J53,OR($A10>G53,$F10>H53,$G10>I53)),A53,IF(AND($H10>J53,$H10<=J54),A54,IF(AND($H10>J54,$H10<=J55),A55,A56)))))) -> Extra-large 0 to 50 lb
M18: =IFERROR(VLOOKUP(ROUNDUP($H$7,0),'FBA FEES'!$L$2:$Q$203,MATCH(M9,'FBA FEES'!$L$2:$Q$2,0),FALSE),VLOOKUP(ROUNDUP($H$7,0),'FBA FEES'!$C$6:$F$123,MATCH(M9,'FBA FEES'!$C$6:$F$6,0),FALSE)) -> 36.97
M19: =IF(AND($M$12<=J50,$H$8<=G50,$H$9<=H50,$H$10<=I50),A50,IF(AND($M$12<=J51,$H$8<=G51,$H$9<=H51,$H$10<=I51),A51,IF(AND($H$8<=G52,$H$9<=H52,$H$10<=I52,$M$12<=J52),A52,IF(AND($M$12<=J53,OR(H$8>G53,$H$9>H53,$H$10>I53)),A53,IF(AND($M$12>J53,$M$12<=J54),A54,IF(AND($M$12>J54,$M$12<=J55),A55,A56)))))) -> Extra-large 0 to 50 lb
P23: Length + girth | Q23: Weight
A24: Shipping weight1 | F24: Longest side | G24: Median side | H24: Shortest side | I24: Length + girth | J24: Product size tier | L24: Shipping weight1 | M24: Longest side | N24: Median side | O24: Shortest side | Q24: 1
A25: Up to 16 oz | F25: Up to 15 inches | G25: Up to 12 inches | H25: Up to 0.75 inch | I25: n/a | J25: Small standard-size | K25: 1 | L25: Up to 16 oz | M25: 15 | N25: 12 | O25: 0.75 | Q25: 20
A26: Up to 20 lb | F26: Up to 18 inches | G26: Up to 14 inches | H26: Up to 8 inches | I26: n/a | J26: Large standard-size | K26: 2 | L26: Up to 20 lb | M26: 18 | N26: 14 | O26: 8 | S26: Size tier | U26: Shipping weight | V26: Removal fee per unit
A27: Up to 50 lb | F27: Up to 59 inches | G27: Up to 33 inches | H27: Up to 33 inches | I27: Up to 130 inches | J27: LARGE | K27: 3 | S27: Standard size | T27: Small standard-size | U27: 0 to 0.5 lb | V27: $1.04
A28: Up to 50 lb | F28: Extra-large exceeds 59 inches for the longest side or 33 inches for the median side or 33 inches for the shortest side or 130 inches for length + girth, or if the product’s greater of unit weight or dimensional weight exceeds 50 lb. | O28: =IF(AND(H8<=M25,H11<=Q24),K25,IF(AND(H8<=M26,H11>Q24,H11<=Q25),K26,J27)) -> LARGE | U28: 0.5+ to 1.0 lb | V28: $1.53 | X28: SIZE | Y28: Tier | Z28: Longest side | AA28: Median side | AB28: Shortest side | AC28: Weight
A29: 50+ to 70 lb | O29: =IF(H9<=N25,K25,IF(H9<=N26,K26,IF(H9<=N42,K42,IF(H9>N43,K43,IF(H9>N44,K44,IF(H9>N45,K45,IF(H9>N46,K46))))))) -> 1 | T29: Large standard-size | U29: 1.0+ to 2.0 lb | V29: $2.27 | X29: Small standard-size | Y29: 1 | Z29: 15 | AA29: 12 | AB29: 0.75 | AC29: 1
A30: 70+ to 150 lb | O30: =IF(H10<=O25,K25,IF(H10<=O26,K26,IF(H10<=O42,K42,IF(H10>O43,K43,IF(H10>O44,K44,IF(H10>O45,K45,IF(H10>O46,K46))))))) -> 2 | U30: More than 2 lb | V30: $2.89 + $1.06/lb above 2 lb | X30: Large standard-size | Y30: 2 | Z30: 18 | AA30: 14 | AB30: 8 | AC30: 20
A31: Over 150 lb | O31: =IF(H11<=Q24,K25,IF(H11<=Q25,K26,IF(H11<=Q41,K42,IF(H11<=Q42,K43,IF(AND(H11>=Q43,H11>Q42),K44,IF(H11>Q44,K45,IF(H11>Q45,K46))))))) -> 3 | S31: Large bulky, extra-large and special handling items | T31: Large bulky | U31: 0 to 1.0 lb | V31: $3.12 | X31: Large bulky | Y31: 3 | Z31: 59 | AA31: 33 | AB31: 33 | AC31: 50
L32: Weight(oz) | M32: =H11*16 -> 464 | T32: Extra-large 0 to 50 lb | U32: 1.0+ to 2.0 lb | V32: $4.30 | X32: Extra-large 0 to 50 lb | Y32: 4 | Z32: 59 | AA32: 33 | AB32: 33 | AC32: 50
T33: Extra-large 50+ to 70 lb | U33: 2.0+ to 4.0 lb | V33: $6.36 | X33: Extra-large 50+ to 70 lb | Y33: 5 | Z33: 59 | AA33: 33 | AB33: 33 | AC33: 70
T34: Extra-large 70+ to 150 lb | U34: 4.0+ to 10.0 lb | V34: $10.04 | X34: Extra-large 70+ to 150 lb | Y34: 6 | Z34: 59 | AA34: 33 | AB34: 33 | AC34: 150
J35: LARGE | T35: Extra-large 150+ lb | U35: More than 10.0 lb | V35: $14.32 + $1.06/lb above 10 lb | X35: Extra-large 150+ lb | Y35: 7 | Z35: 59 | AA35: 33 | AB35: 33 | AC35: 150.1
P41: Up to 130 inches | Q41: 50 | S41: Tier | T41: =[1]CALCULATOR!AA33 -> 0 | U41: =T41 -> 0
J42: Large bulky | K42: 3 | L42: Up to 50 lb | M42: 59 | N42: 33 | O42: 33 | Q42: 50.1 | S42: Weight | T42: =[1]CALCULATOR!AA34 -> 0 | U42: =IF(AND($F$17>0,$F$17<=0.5),0.5,ROUND($F$17,0)) -> 0
J43: Extra-large 0 to 50 lb | K43: 4 | L43: Up to 50 lb | M43: 59 | N43: 33 | O43: 33 | Q43: 70 | S43: Qty | T43: =[1]CALCULATOR!AA35 -> 0 | U43: =T43 -> 0
J44: Extra-large 50+ to 70 lb | K44: 5 | L44: 50+ to 70 lb | M44: 59 | N44: 33 | O44: 33 | Q44: 150
J45: Extra-large 70+ to 150 lb | K45: 6 | L45: 70+ to 150 lb | M45: 59 | N45: 33 | O45: 33 | Q45: 150.1 | S45: Tier | T45: =IF($F$16=1,$A$2,IF($F$16=2,$A$6)) -> FALSE
J46: Extra-large 150+ lb | K46: 7 | L46: Over 150 lb | M46: 59 | N46: 33 | O46: 33 | S46: Fees | T46: =IFERROR(IF($G$16=1,$G$24,IF($G$16=2,IF($G$17>10,(($G$17-10)*1.06)+$G$25,$G$25)))*$G$18,FALSE) -> 0
T48: =IF(AND(P73<=0.25,$S73="Small standard-size"),"Small standard: 4 oz or less") -> FALSE
A49: SIZE | F49: Tier | G49: Longest side | H49: Median side | I49: Shortest side | J49: Weight | Q49: =IF(COUNTIF(L50:O50,TRUE)=4,F50,"-") -> -
A50: Small standard-size | F50: 1 | G50: 15 | H50: 12 | I50: 0.75 | J50: 1 | L50: =$H$8<=G50 -> FALSE | M50: =$H$9<=H50 -> TRUE | N50: =$H$10<=I50 -> FALSE | O50: =$H$11<=J50 -> FALSE | Q50: =IF(COUNTIF(L51:O51,TRUE)=4,F51,"-") -> -
A51: Large standard-size | F51: 2 | G51: 18 | H51: 14 | I51: 8 | J51: 20 | L51: =$H$8<=G51 -> FALSE | M51: =$H$9<=H51 -> TRUE | N51: =$H$10<=I51 -> TRUE | O51: =AND($H$11<=J51,$H$11>J50) -> FALSE | Q51: =IF(COUNTIF(L52:O52,TRUE)=4,F52,"-") -> -
A52: Large bulky | F52: 3 | G52: 59 | H52: 33 | I52: 33 | J52: 50 | L52: =$H$8<=G52 -> FALSE | M52: =$H$9<=H52 -> TRUE | N52: =$H$10<=I52 -> TRUE | O52: =AND($H$11<=J52,$H$11>J51) -> TRUE | Q52: =IF(COUNTIF(L53:O53,TRUE)=4,F53,"-") -> -
A53: Extra-large 0 to 50 lb | F53: 4 | G53: 59 | H53: 33 | I53: 33 | J53: 50 | L53: =$H$8<=G53 -> FALSE | M53: =$H$9<=H53 -> TRUE | N53: =$H$10<=I53 -> TRUE | O53: =AND($H$11<=J53,$H$11>J52) -> FALSE | Q53: =IF(COUNTIF(L54:O54,TRUE)=4,F54,"-") -> -
A54: Extra-large 50+ to 70 lb | F54: 5 | G54: 59 | H54: 33 | I54: 33 | J54: 70 | L54: =$H$8<=G54 -> FALSE | M54: =$H$9<=H54 -> TRUE | N54: =$H$10<=I54 -> TRUE | O54: =AND($H$11<=J54,$H$11>J53) -> FALSE | Q54: =IF(COUNTIF(L55:O55,TRUE)=4,F55,"-") -> -
A55: Extra-large 70+ to 150 lb | F55: 6 | G55: 59 | H55: 33 | I55: 33 | J55: 150 | L55: =$H$8<=G55 -> FALSE | M55: =$H$9<=H55 -> TRUE | N55: =$H$10<=I55 -> TRUE | O55: =AND($H$11<=J55,$H$11>J54) -> FALSE | Q55: =IF(COUNTIF(L56:O56,TRUE)=4,F56,"-") -> -
A56: Extra-large 150+ lb | F56: 7 | G56: 59 | H56: 33 | I56: 33 | J56: 150.1 | L56: =$H$8<=G56 -> FALSE | M56: =$H$9<=H56 -> TRUE | N56: =$H$10<=I56 -> TRUE | O56: =AND($H$11<=J56,$H$11>J55) -> FALSE
A60: Large bulky
A61: Extra-large 0 to 50 lb
A62: Extra-large 50 to 70 lb
A63: Extra-large 70 to 150 lb
A64: Extra-large 150+++ lb
A66: Large bulky | F66: Extra-large 0 to 50 lb | G66: Extra-large 50+ to 70 lb | H66: Extra-large 70+ to 150 lb | I66: Extra-large 150+ lb
A67: Small standard-size | F67: Large standard-size
H70: get data from parasbhai | K70: =H70&"x"&I70&"x"&J70 -> get data from parasbhaixx | L70: =(H70*I70*J70)/139 -> #VALUE! | M70: =(H70*I70*J70)/139 -> #VALUE! | N70: =IF(AND(M70>0,M70<=0.25),0.25,IF(AND(M70>0.25,M70<=0.5),0.5,IF(AND(M70>0.5,M70<=0.75),0.75,ROUNDUP(M70,0)))) -> #VALUE! | O70: get data from parasbhai | P70: =ROUNDUP(MAX(L70,O70),0) -> #VALUE! | Q70: =P70*16 -> #VALUE! | R70: =IF(RIGHT(S70,13)="standard-size","Standard-size","Oversize") -> #VALUE! | S70: =IF(AND($P70<=$J$50,$H70<=$G$50,$I70<=$H$50,$J70<=$I$50),$A$50,IF(AND($P70<=$J$51,$H70<=$G$51,$I70<=$H$51,$J70<=$I$51),$A$51,IF(AND($H70<=$G$52,$I70<=$H$52,$J70<=$I$52,$P70<=$J$52),$A$52,IF(AND($P70<=$J$53,OR(H$8>$G$53,$I70>$H$53,$J70>$I$53)),$A$53,IF(AND($P70>$J$53,$P70<=$J$54),$A$54,IF(AND($P70>$J$54,$P70<=$J$55),$A$55,$A$56)))))) -> #VALUE! | T70: =IF(AND($P70<=#REF!,$S70=#REF!),#REF!,IF(AND($P70<=#REF!,$S70=#REF!),#REF!,IF(AND($P70<=#REF!,$S70=#REF!),#REF!,IF(AND($P70<=#REF!,$S70=#REF!),#REF!,IF(AND($S70=#REF!,$P70<=#REF!),#REF!,IF(AND($S70=#REF!,$P70<=#REF!),#REF!,IF(AND($S70=#REF!,$P70<=#REF!),#REF!,IF(AND($S70=#REF!,$P70<=#REF!),#REF!,IF(AND($S70=#REF!,$P70<=#REF!),#REF!,IF(AND($S70=#REF!,$P70<=#REF!),#REF!,IF(AND($S70=#REF!,$P70<=#REF!),#REF!,IF(AND($S70=#REF!,$P70<=#REF!),#REF!,IF(AND($S70=#REF!,$P70>=#REF!),#REF!,IF(AND($S70=#REF!,$P70<=#REF!),#REF!,IF(AND($S70=#REF!,$P70<=#REF!),#REF!,IF(AND($S70=#REF!,$P70<=#REF!),#REF!,IF(AND($S70=#REF!,$P70<=#REF!),#REF!))))))))))))))))) -> #VALUE! | U70: =(H70*I70*J70)/1728 -> #VALUE! | V70: =IFERROR(IFERROR(VLOOKUP(ROUNDUP($P70,0),'FBA FEES'!$L$2:$Q$203,MATCH($Q70,'FBA FEES'!$L$2:$Q$2,0),FALSE),VLOOKUP(ROUNDUP($P70,0),'FBA FEES'!$C$6:$F$123,MATCH($Q70,'FBA FEES'!$C$6:$F$6,0),FALSE)),0) -> 0 | X70: =IFERROR(IFERROR(VLOOKUP(ROUNDUP($P70,0),'FBA FEES'!$L$2:$Q$203,MATCH($Q70,'FBA FEES'!$L$2:$Q$2,0),FALSE),VLOOKUP(ROUNDUP($P70,0),'FBA FEES'!$C$6:$F$123,MATCH($Q70,'FBA FEES'!$C$6:$F$6,0),FALSE)),0) -> 0 | AB70: =IFERROR(IF($R70=1,INDEX('[1]REMOVAL FEES'!$A$1:$C$22,MATCH(CONCATENATE("Standard Size",$O70),'[1]REMOVAL FEES'!$A$1:$A$22,0),3),IF($R70=2,IF($O70>10,(($O70-10)*1.06)+INDEX('[1]REMOVAL FEES'!$E$1:$G$22,MATCH(CONCATENATE("Large bulky, extra-large and special handling items",IF($O70>=11,11,$O70)),'[1]REMOVAL FEES'!$E$1:$E$13,0),3),INDEX('[1]REMOVAL FEES'!$E$1:$G$22,MATCH(CONCATENATE("Large bulky, extra-large and special handling items",IF($O70>=11,11,$O70)),'[1]REMOVAL FEES'!$E$1:$E$13,0),3))))*$S70,FALSE) -> FALSE | AE70: =-AD70*0.15 -> 0 | AF70: =-IFERROR(IFERROR(VLOOKUP(ROUNDUP($Q70,0),'FBA FEES'!$L$2:$Q$203,MATCH($S70,'FBA FEES'!$L$2:$Q$2,0),FALSE),VLOOKUP(ROUNDUP($Q70,0),'FBA FEES'!$C$6:$F$123,MATCH($S70,'FBA FEES'!$C$6:$F$6,0),FALSE)),0) -> 0 | AI70: =-IFERROR(IF($Y70=1,INDEX('[1]REMOVAL FEES'!$A$1:$C$22,MATCH(CONCATENATE("Standard Size",$P70),'[1]REMOVAL FEES'!$A$1:$A$22,0),3),IF($Y70=2,IF($P70>10,(($P70-10)*1.06)+INDEX('[1]REMOVAL FEES'!$E$1:$G$22,MATCH(CONCATENATE("Large bulky, extra-large and special handling items",IF($P70>=11,11,$P70)),'[1]REMOVAL FEES'!$E$1:$E$13,0),3),INDEX('[1]REMOVAL FEES'!$E$1:$G$22,MATCH(CONCATENATE("Large bulky, extra-large and special handling items",IF($P70>=11,11,$P70)),'[1]REMOVAL FEES'!$E$1:$E$13,0),3))))*$AA70,FALSE) -> 0 | AJ70: =AH70+AI70 -> 0 | AM70: =AK70+AL70 -> 0 | AN70: =(-IF($V70="Yes", IF($X70="Yes", VLOOKUP($W70, '[1]Storage Fees'!A:M, 13, FALSE), VLOOKUP($W70, '[1]Storage Fees'!A:M, 10, FALSE)), IF($X70="Yes", VLOOKUP($W70, '[1]Storage Fees'!A:M, 7, FALSE), VLOOKUP($W70, '[1]Storage Fees'!A:M, 4, FALSE))) * U70)*1.5 -> #N/A
A71: SR NO. | B71: L.O. | C71: DLTD | D71: DC | E71: CAT | F71: SKU | G71: RETURNLESS REFUND | H71: L | I71: W | J71: H | K71: Dimension | L71: Volumetric | M71: Volumetric F | N71: MCF WEIGHT | O71: ACT(UNIT WEIGHT) | P71: MAX | Q71: ACT(oz) | R71: Size-Tier | S71: Product Classification Calculator | T71: Sub-Tier | U71: Vol. | V71: Peak Season | W71: week | X71: Oversize | Y71: TIER | Z71: MCF TIER | AA71: QTY (REMOVAL) | AB71: Weight into Consideration | AC71: Weight in Consideration | AD71: Sale Price | AE71: Sell Fees | AF71: FBA fees | AG71: Processing Fee | AH71: TOTAL CHARGES | AI71: AVG Removal/Disposal Fees | AJ71: Net Charge Loss | AK71: P. Cost | AL71: Freight | AM71: Freight + P.cost | AN71: Storage Fee
A73: 1 | B73: Tushar | E73: CFB | F73: B10 | G73: RETURNLESS REFUND | H73: 25 | I73: 19 | J73: 19 | K73: =H73&"x"&I73&"x"&J73 -> 25x19x19 | L73: =(H73*I73*J73)/139 -> 64.928058 | M73: =(H73*I73*J73)/139 -> 64.928058 | N73: =IF(AND(M73>0,M73<=0.25),0.25,IF(AND(M73>0.25,M73<=0.5),0.5,IF(AND(M73>0.5,M73<=0.75),0.75,ROUNDUP(M73,0)))) -> 65 | O73: 38 | P73: =ROUNDUP(MAX(L73,O73),0) -> 65 | Q73: =P73*16 -> 1040 | R73: =IF(RIGHT(S73,13)="standard-size","Standard-size","Oversize") -> Oversize | S73: =IF(AND($P73<=$J$50,$H73<=$G$50,$I73<=$H$50,$J73<=$I$50),$A$50,IF(AND($P73<=$J$51,$H73<=$G$51,$I73<=$H$51,$J73<=$I$51),$A$51,IF(AND($H73<=$G$52,$I73<=$H$52,$J73<=$I$52,$P73<=$J$52),$A$52,IF(AND($P73<=$J$53,OR(H$8>$G$53,$I73>$H$53,$J73>$I$53)),$A$53,IF(AND($P73>$J$53,$P73<=$J$54),$A$54,IF(AND($P73>$J$54,$P73<=$J$55),$A$55,$A$56)))))) -> Extra-large 50+ to 70 lb | T73: Extra-large: 50+ to 70 lb | U73: =(H73*I73*J73)/1728 -> 5.2228009 | V73: No | W73: 22 – 28 | X73: Yes | Y73: 2 | Z73: 5 | AA73: 1 | AD73: 134.9417 | AE73: =-AD73*0.15 -> -20.241254 | AF73: =-IFERROR(IFERROR(VLOOKUP(ROUNDUP($Q73,0),'FBA FEES'!$L$2:$Q$203,MATCH($S73,'FBA FEES'!$L$2:$Q$2,0),FALSE),VLOOKUP(ROUNDUP($Q73,0),'FBA FEES'!$C$6:$F$123,MATCH($S73,'FBA FEES'!$C$6:$F$6,0),FALSE)),0) -> -50.62 | AG73: -7 | AH73: =AE73+AF73 -> -70.861254 | AI73: =-IFERROR(IF($Y73=1,INDEX('[1]REMOVAL FEES'!$A$1:$C$22,MATCH(CONCATENATE("Standard Size",$P73),'[1]REMOVAL FEES'!$A$1:$A$22,0),3),IF($Y73=2,IF($P73>10,(($P73-10)*1.06)+INDEX('[1]REMOVAL FEES'!$E$1:$G$22,MATCH(CONCATENATE("Large bulky, extra-large and special handling items",IF($P73>=11,11,$P73)),'[1]REMOVAL FEES'!$E$1:$E$13,0),3),INDEX('[1]REMOVAL FEES'!$E$1:$G$22,MATCH(CONCATENATE("Large bulky, extra-large and special handling items",IF($P73>=11,11,$P73)),'[1]REMOVAL FEES'!$E$1:$E$13,0),3))))*$AA73,FALSE) -> -72.62 | AJ73: =AH73+AI73 -> -143.48125 | AK73: -46.262718 | AL73: -17.903849 | AM73: =AK73+AL73 -> -64.166568 | AN73: =(-IF($V73="Yes", IF($X73="Yes", VLOOKUP($W73, '[1]Storage Fees'!A:M, 13, FALSE), VLOOKUP($W73, '[1]Storage Fees'!A:M, 10, FALSE)), IF($X73="Yes", VLOOKUP($W73, '[1]Storage Fees'!A:M, 7, FALSE), VLOOKUP($W73, '[1]Storage Fees'!A:M, 4, FALSE))) * U73)*1.5 -> -6.1890191
A74: 2 | B74: Tushar | E74: CFB | F74: B10J | G74: RETURNLESS REFUND | H74: 25 | I74: 7 | J74: 7 | K74: =H74&"x"&I74&"x"&J74 -> 25x7x7 | L74: =(H74*I74*J74)/139 -> 8.8129496 | M74: =(H74*I74*J74)/139 -> 8.8129496 | N74: =IF(AND(M74>0,M74<=0.25),0.25,IF(AND(M74>0.25,M74<=0.5),0.5,IF(AND(M74>0.5,M74<=0.75),0.75,ROUNDUP(M74,0)))) -> 9 | O74: 5 | P74: =ROUNDUP(MAX(L74,O74),0) -> 9 | Q74: =P74*16 -> 144 | R74: =IF(RIGHT(S74,13)="standard-size","Standard-size","Oversize") -> Oversize | S74: =IF(AND($P74<=$J$50,$H74<=$G$50,$I74<=$H$50,$J74<=$I$50),$A$50,IF(AND($P74<=$J$51,$H74<=$G$51,$I74<=$H$51,$J74<=$I$51),$A$51,IF(AND($H74<=$G$52,$I74<=$H$52,$J74<=$I$52,$P74<=$J$52),$A$52,IF(AND($P74<=$J$53,OR(H$8>$G$53,$I74>$H$53,$J74>$I$53)),$A$53,IF(AND($P74>$J$53,$P74<=$J$54),$A$54,IF(AND($P74>$J$54,$P74<=$J$55),$A$55,$A$56)))))) -> Large bulky | T74: Large bulky: up to 30 lb | U74: =(H74*I74*J74)/1728 -> 0.70891204 | V74: No | W74: 22 – 28 | X74: Yes | Y74: 2 | Z74: 3 | AA74: 1 | AD74: 31.675063 | AE74: =-AD74*0.15 -> -4.7512594 | AF74: =-IFERROR(IFERROR(VLOOKUP(ROUNDUP($Q74,0),'FBA FEES'!$L$2:$Q$203,MATCH($S74,'FBA FEES'!$L$2:$Q$2,0),FALSE),VLOOKUP(ROUNDUP($Q74,0),'FBA FEES'!$C$6:$F$123,MATCH($S74,'FBA FEES'!$C$6:$F$6,0),FALSE)),0) -> -12.65 | AG74: -7 | AH74: =AE74+AF74 -> -17.401259 | AI74: =-IFERROR(IF($Y74=1,INDEX('[1]REMOVAL FEES'!$A$1:$C$22,MATCH(CONCATENATE("Standard Size",$P74),'[1]REMOVAL FEES'!$A$1:$A$22,0),3),IF($Y74=2,IF($P74>10,(($P74-10)*1.06)+INDEX('[1]REMOVAL FEES'!$E$1:$G$22,MATCH(CONCATENATE("Large bulky, extra-large and special handling items",IF($P74>=11,11,$P74)),'[1]REMOVAL FEES'!$E$1:$E$13,0),3),INDEX('[1]REMOVAL FEES'!$E$1:$G$22,MATCH(CONCATENATE("Large bulky, extra-large and special handling items",IF($P74>=11,11,$P74)),'[1]REMOVAL FEES'!$E$1:$E$13,0),3))))*$AA74,FALSE) -> -10.04 | AJ74: =AH74+AI74 -> -27.441259 | AK74: -6.078 | AL74: -6.2374985 | AM74: =AK74+AL74 -> -12.315499 | AN74: =(-IF($V74="Yes", IF($X74="Yes", VLOOKUP($W74, '[1]Storage Fees'!A:M, 13, FALSE), VLOOKUP($W74, '[1]Storage Fees'!A:M, 10, FALSE)), IF($X74="Yes", VLOOKUP($W74, '[1]Storage Fees'!A:M, 7, FALSE), VLOOKUP($W74, '[1]Storage Fees'!A:M, 4, FALSE))) * U74)*1.5 -> -0.84006076
A75: 3 | B75: Tushar | E75: CFB | F75: B10X | G75: RETURNLESS REFUND | H75: 26 | I75: 11 | J75: 11 | K75: =H75&"x"&I75&"x"&J75 -> 26x11x11 | L75: =(H75*I75*J75)/139 -> 22.633094 | M75: =(H75*I75*J75)/139 -> 22.633094 | N75: =IF(AND(M75>0,M75<=0.25),0.25,IF(AND(M75>0.25,M75<=0.5),0.5,IF(AND(M75>0.5,M75<=0.75),0.75,ROUNDUP(M75,0)))) -> 23 | O75: 11 | P75: =ROUNDUP(MAX(L75,O75),0) -> 23 | Q75: =P75*16 -> 368 | R75: =IF(RIGHT(S75,13)="standard-size","Standard-size","Oversize") -> Oversize | S75: =IF(AND($P75<=$J$50,$H75<=$G$50,$I75<=$H$50,$J75<=$I$50),$A$50,IF(AND($P75<=$J$51,$H75<=$G$51,$I75<=$H$51,$J75<=$I$51),$A$51,IF(AND($H75<=$G$52,$I75<=$H$52,$J75<=$I$52,$P75<=$J$52),$A$52,IF(AND($P75<=$J$53,OR(H$8>$G$53,$I75>$H$53,$J75>$I$53)),$A$53,IF(AND($P75>$J$53,$P75<=$J$54),$A$54,IF(AND($P75>$J$54,$P75<=$J$55),$A$55,$A$56)))))) -> Large bulky | T75: Large bulky: up to 30 lb | U75: =(H75*I75*J75)/1728 -> 1.8206019 | V75: No | W75: 22 – 28 | X75: Yes | Y75: 2 | Z75: 3 | AA75: 1 | AD75: 55.427925 | AE75: =-AD75*0.15 -> -8.3141887 | AF75: =-IFERROR(IFERROR(VLOOKUP(ROUNDUP($Q75,0),'FBA FEES'!$L$2:$Q$203,MATCH($S75,'FBA FEES'!$L$2:$Q$2,0),FALSE),VLOOKUP(ROUNDUP($Q75,0),'FBA FEES'!$C$6:$F$123,MATCH($S75,'FBA FEES'!$C$6:$F$6,0),FALSE)),0) -> -17.97 | AG75: -7 | AH75: =AE75+AF75 -> -26.284189 | AI75: =-IFERROR(IF($Y75=1,INDEX('[1]REMOVAL FEES'!$A$1:$C$22,MATCH(CONCATENATE("Standard Size",$P75),'[1]REMOVAL FEES'!$A$1:$A$22,0),3),IF($Y75=2,IF($P75>10,(($P75-10)*1.06)+INDEX('[1]REMOVAL FEES'!$E$1:$G$22,MATCH(CONCATENATE("Large bulky, extra-large and special handling items",IF($P75>=11,11,$P75)),'[1]REMOVAL FEES'!$E$1:$E$13,0),3),INDEX('[1]REMOVAL FEES'!$E$1:$G$22,MATCH(CONCATENATE("Large bulky, extra-large and special handling items",IF($P75>=11,11,$P75)),'[1]REMOVAL FEES'!$E$1:$E$13,0),3))))*$AA75,FALSE) -> -28.1 | AJ75: =AH75+AI75 -> -54.384189 | AK75: -12.975157 | AL75: -7.731238 | AM75: =AK75+AL75 -> -20.706395 | AN75: =(-IF($V75="Yes", IF($X75="Yes", VLOOKUP($W75, '[1]Storage Fees'!A:M, 13, FALSE), VLOOKUP($W75, '[1]Storage Fees'!A:M, 10, FALSE)), IF($X75="Yes", VLOOKUP($W75, '[1]Storage Fees'!A:M, 7, FALSE), VLOOKUP($W75, '[1]Storage Fees'!A:M, 4, FALSE))) * U75)*1.5 -> -2.1574132
A76: 4 | B76: Tushar | E76: CFB | F76: B11 | G76: RETURNLESS REFUND | H76: 25 | I76: 18 | J76: 18 | K76: =H76&"x"&I76&"x"&J76 -> 25x18x18 | L76: =(H76*I76*J76)/139 -> 58.273381 | M76: =(H76*I76*J76)/139 -> 58.273381 | N76: =IF(AND(M76>0,M76<=0.25),0.25,IF(AND(M76>0.25,M76<=0.5),0.5,IF(AND(M76>0.5,M76<=0.75),0.75,ROUNDUP(M76,0)))) -> 59 | O76: 30 | P76: =ROUNDUP(MAX(L76,O76),0) -> 59 | Q76: =P76*16 -> 944 | R76: =IF(RIGHT(S76,13)="standard-size","Standard-size","Oversize") -> Oversize | S76: =IF(AND($P76<=$J$50,$H76<=$G$50,$I76<=$H$50,$J76<=$I$50),$A$50,IF(AND($P76<=$J$51,$H76<=$G$51,$I76<=$H$51,$J76<=$I$51),$A$51,IF(AND($H76<=$G$52,$I76<=$H$52,$J76<=$I$52,$P76<=$J$52),$A$52,IF(AND($P76<=$J$53,OR(H$8>$G$53,$I76>$H$53,$J76>$I$53)),$A$53,IF(AND($P76>$J$53,$P76<=$J$54),$A$54,IF(AND($P76>$J$54,$P76<=$J$55),$A$55,$A$56)))))) -> Extra-large 50+ to 70 lb | T76: Extra-large: 50+ to 70 lb | U76: =(H76*I76*J76)/1728 -> 4.6875 | V76: No | W76: 22 – 28 | X76: Yes | Y76: 2 | Z76: 5 | AA76: 1 | AD76: 118.66163 | AE76: =-AD76*0.15 -> -17.799244 | AF76: =-IFERROR(IFERROR(VLOOKUP(ROUNDUP($Q76,0),'FBA FEES'!$L$2:$Q$203,MATCH($S76,'FBA FEES'!$L$2:$Q$2,0),FALSE),VLOOKUP(ROUNDUP($Q76,0),'FBA FEES'!$C$6:$F$123,MATCH($S76,'FBA FEES'!$C$6:$F$6,0),FALSE)),0) -> -46.12 | AG76: -7 | AH76: =AE76+AF76 -> -63.919244 | AI76: =-IFERROR(IF($Y76=1,INDEX('[1]REMOVAL FEES'!$A$1:$C$22,MATCH(CONCATENATE("Standard Size",$P76),'[1]REMOVAL FEES'!$A$1:$A$22,0),3),IF($Y76=2,IF($P76>10,(($P76-10)*1.06)+INDEX('[1]REMOVAL FEES'!$E$1:$G$22,MATCH(CONCATENATE("Large bulky, extra-large and special handling items",IF($P76>=11,11,$P76)),'[1]REMOVAL FEES'!$E$1:$E$13,0),3),INDEX('[1]REMOVAL FEES'!$E$1:$G$22,MATCH(CONCATENATE("Large bulky, extra-large and special handling items",IF($P76>=11,11,$P76)),'[1]REMOVAL FEES'!$E$1:$E$13,0),3))))*$AA76,FALSE) -> -66.26 | AJ76: =AH76+AI76 -> -130.17924 | AK76: -36.613953 | AL76: -14.377571 | AM76: =AK76+AL76 -> -50.991524 | AN76: =(-IF($V76="Yes", IF($X76="Yes", VLOOKUP($W76, '[1]Storage Fees'!A:M, 13, FALSE), VLOOKUP($W76, '[1]Storage Fees'!A:M, 10, FALSE)), IF($X76="Yes", VLOOKUP($W76, '[1]Storage Fees'!A:M, 7, FALSE), VLOOKUP($W76, '[1]Storage Fees'!A:M, 4, FALSE))) * U76)*1.5 -> -5.5546875
A77: 5 | B77: Tushar | E77: CFB | F77: B12 | G77: RETURNLESS REFUND | H77: 25 | I77: 19 | J77: 19 | K77: =H77&"x"&I77&"x"&J77 -> 25x19x19 | L77: =(H77*I77*J77)/139 -> 64.928058 | M77: =(H77*I77*J77)/139 -> 64.928058 | N77: =IF(AND(M77>0,M77<=0.25),0.25,IF(AND(M77>0.25,M77<=0.5),0.5,IF(AND(M77>0.5,M77<=0.75),0.75,ROUNDUP(M77,0)))) -> 65 | O77: 35 | P77: =ROUNDUP(MAX(L77,O77),0) -> 65 | Q77: =P77*16 -> 1040 | R77: =IF(RIGHT(S77,13)="standard-size","Standard-size","Oversize") -> Oversize | S77: =IF(AND($P77<=$J$50,$H77<=$G$50,$I77<=$H$50,$J77<=$I$50),$A$50,IF(AND($P77<=$J$51,$H77<=$G$51,$I77<=$H$51,$J77<=$I$51),$A$51,IF(AND($H77<=$G$52,$I77<=$H$52,$J77<=$I$52,$P77<=$J$52),$A$52,IF(AND($P77<=$J$53,OR(H$8>$G$53,$I77>$H$53,$J77>$I$53)),$A$53,IF(AND($P77>$J$53,$P77<=$J$54),$A$54,IF(AND($P77>$J$54,$P77<=$J$55),$A$55,$A$56)))))) -> Extra-large 50+ to 70 lb | T77: Extra-large: 50+ to 70 lb | U77: =(H77*I77*J77)/1728 -> 5.2228009 | V77: No | W77: 22 – 28 | X77: Yes | Y77: 2 | Z77: 5 | AA77: 1 | AD77: 150 | AE77: =-AD77*0.15 -> -22.5 | AF77: =-IFERROR(IFERROR(VLOOKUP(ROUNDUP($Q77,0),'FBA FEES'!$L$2:$Q$203,MATCH($S77,'FBA FEES'!$L$2:$Q$2,0),FALSE),VLOOKUP(ROUNDUP($Q77,0),'FBA FEES'!$C$6:$F$123,MATCH($S77,'FBA FEES'!$C$6:$F$6,0),FALSE)),0) -> -50.62 | AG77: -7 | AH77: =AE77+AF77 -> -73.12 | AI77: =-IFERROR(IF($Y77=1,INDEX('[1]REMOVAL FEES'!$A$1:$C$22,MATCH(CONCATENATE("Standard Size",$P77),'[1]REMOVAL FEES'!$A$1:$A$22,0),3),IF($Y77=2,IF($P77>10,(($P77-10)*1.06)+INDEX('[1]REMOVAL FEES'!$E$1:$G$22,MATCH(CONCATENATE("Large bulky, extra-large and special handling items",IF($P77>=11,11,$P77)),'[1]REMOVAL FEES'!$E$1:$E$13,0),3),INDEX('[1]REMOVAL FEES'!$E$1:$G$22,MATCH(CONCATENATE("Large bulky, extra-large and special handling items",IF($P77>=11,11,$P77)),'[1]REMOVAL FEES'!$E$1:$E$13,0),3))))*$AA77,FALSE) -> -72.62 | AJ77: =AH77+AI77 -> -145.74 | AK77: -44.811279 | AL77: -17.578662 | AM77: =AK77+AL77 -> -62.389942 | AN77: =(-IF($V77="Yes", IF($X77="Yes", VLOOKUP($W77, '[1]Storage Fees'!A:M, 13, FALSE), VLOOKUP($W77, '[1]Storage Fees'!A:M, 10, FALSE)), IF($X77="Yes", VLOOKUP($W77, '[1]Storage Fees'!A:M, 7, FALSE), VLOOKUP($W77, '[1]Storage Fees'!A:M, 4, FALSE))) * U77)*1.5 -> -6.1890191
A78: 6 | B78: Tushar | E78: CFB | F78: B12F | G78: RETURNLESS REFUND | H78: 12 | I78: 12 | J78: 5 | K78: =H78&"x"&I78&"x"&J78 -> 12x12x5 | L78: =(H78*I78*J78)/139 -> 5.1798561 | M78: =(H78*I78*J78)/139 -> 5.1798561 | N78: =IF(AND(M78>0,M78<=0.25),0.25,IF(AND(M78>0.25,M78<=0.5),0.5,IF(AND(M78>0.5,M78<=0.75),0.75,ROUNDUP(M78,0)))) -> 6 | O78: 3 | P78: =ROUNDUP(MAX(L78,O78),0) -> 6 | Q78: =P78*16 -> 96 | R78: =IF(RIGHT(S78,13)="standard-size","Standard-size","Oversize") -> Standard-size | S78: =IF(AND($P78<=$J$50,$H78<=$G$50,$I78<=$H$50,$J78<=$I$50),$A$50,IF(AND($P78<=$J$51,$H78<=$G$51,$I78<=$H$51,$J78<=$I$51),$A$51,IF(AND($H78<=$G$52,$I78<=$H$52,$J78<=$I$52,$P78<=$J$52),$A$52,IF(AND($P78<=$J$53,OR(H$8>$G$53,$I78>$H$53,$J78>$I$53)),$A$53,IF(AND($P78>$J$53,$P78<=$J$54),$A$54,IF(AND($P78>$J$54,$P78<=$J$55),$A$55,$A$56)))))) -> Large standard-size | T78: Large standard: 3+ to 20 lb | U78: =(H78*I78*J78)/1728 -> 0.41666667 | V78: No | W78: 22 – 28 | X78: No | Y78: 1 | Z78: 2 | AA78: 1 | AD78: 20.4825 | AE78: =-AD78*0.15 -> -3.072375 | AF78: =-IFERROR(IFERROR(VLOOKUP(ROUNDUP($Q78,0),'FBA FEES'!$L$2:$Q$203,MATCH($S78,'FBA FEES'!$L$2:$Q$2,0),FALSE),VLOOKUP(ROUNDUP($Q78,0),'FBA FEES'!$C$6:$F$123,MATCH($S78,'FBA FEES'!$C$6:$F$6,0),FALSE)),0) -> -7.88 | AG78: -2 | AH78: =AE78+AF78 -> -10.952375 | AI78: =-IFERROR(IF($Y78=1,INDEX('[1]REMOVAL FEES'!$A$1:$C$22,MATCH(CONCATENATE("Standard Size",$P78),'[1]REMOVAL FEES'!$A$1:$A$22,0),3),IF($Y78=2,IF($P78>10,(($P78-10)*1.06)+INDEX('[1]REMOVAL FEES'!$E$1:$G$22,MATCH(CONCATENATE("Large bulky, extra-large and special handling items",IF($P78>=11,11,$P78)),'[1]REMOVAL FEES'!$E$1:$E$13,0),3),INDEX('[1]REMOVAL FEES'!$E$1:$G$22,MATCH(CONCATENATE("Large bulky, extra-large and special handling items",IF($P78>=11,11,$P78)),'[1]REMOVAL FEES'!$E$1:$E$13,0),3))))*$AA78,FALSE) -> -7.13 | AJ78: =AH78+AI78 -> -18.082375 | AK78: -3.5727586 | AL78: -1.4491853 | AM78: =AK78+AL78 -> -5.021944 | AN78: =(-IF($V78="Yes", IF($X78="Yes", VLOOKUP($W78, '[1]Storage Fees'!A:M, 13, FALSE), VLOOKUP($W78, '[1]Storage Fees'!A:M, 10, FALSE)), IF($X78="Yes", VLOOKUP($W78, '[1]Storage Fees'!A:M, 7, FALSE), VLOOKUP($W78, '[1]Storage Fees'!A:M, 4, FALSE))) * U78)*1.5 -> -0.7625
A79: 7 | B79: Tushar | E79: CFB | F79: B12H | G79: RETURNLESS REFUND | H79: 25 | I79: 9 | J79: 9 | K79: =H79&"x"&I79&"x"&J79 -> 25x9x9 | L79: =(H79*I79*J79)/139 -> 14.568345 | M79: =(H79*I79*J79)/139 -> 14.568345 | N79: =IF(AND(M79>0,M79<=0.25),0.25,IF(AND(M79>0.25,M79<=0.5),0.5,IF(AND(M79>0.5,M79<=0.75),0.75,ROUNDUP(M79,0)))) -> 15 | O79: 7 | P79: =ROUNDUP(MAX(L79,O79),0) -> 15 | Q79: =P79*16 -> 240 | R79: =IF(RIGHT(S79,13)="standard-size","Standard-size","Oversize") -> Oversize | S79: =IF(AND($P79<=$J$50,$H79<=$G$50,$I79<=$H$50,$J79<=$I$50),$A$50,IF(AND($P79<=$J$51,$H79<=$G$51,$I79<=$H$51,$J79<=$I$51),$A$51,IF(AND($H79<=$G$52,$I79<=$H$52,$J79<=$I$52,$P79<=$J$52),$A$52,IF(AND($P79<=$J$53,OR(H$8>$G$53,$I79>$H$53,$J79>$I$53)),$A$53,IF(AND($P79>$J$53,$P79<=$J$54),$A$54,IF(AND($P79>$J$54,$P79<=$J$55),$A$55,$A$56)))))) -> Large bulky | T79: Large bulky: up to 30 lb | U79: =(H79*I79*J79)/1728 -> 1.171875 | V79: No | W79: 22 – 28 | X79: Yes | Y79: 2 | Z79: 3 | AA79: 1 | AD79: 39.741111 | AE79: =-AD79*0.15 -> -5.9611667 | AF79: =-IFERROR(IFERROR(VLOOKUP(ROUNDUP($Q79,0),'FBA FEES'!$L$2:$Q$203,MATCH($S79,'FBA FEES'!$L$2:$Q$2,0),FALSE),VLOOKUP(ROUNDUP($Q79,0),'FBA FEES'!$C$6:$F$123,MATCH($S79,'FBA FEES'!$C$6:$F$6,0),FALSE)),0) -> -14.93 | AG79: -7 | AH79: =AE79+AF79 -> -20.891167 | AI79: =-IFERROR(IF($Y79=1,INDEX('[1]REMOVAL FEES'!$A$1:$C$22,MATCH(CONCATENATE("Standard Size",$P79),'[1]REMOVAL FEES'!$A$1:$A$22,0),3),IF($Y79=2,IF($P79>10,(($P79-10)*1.06)+INDEX('[1]REMOVAL FEES'!$E$1:$G$22,MATCH(CONCATENATE("Large bulky, extra-large and special handling items",IF($P79>=11,11,$P79)),'[1]REMOVAL FEES'!$E$1:$E$13,0),3),INDEX('[1]REMOVAL FEES'!$E$1:$G$22,MATCH(CONCATENATE("Large bulky, extra-large and special handling items",IF($P79>=11,11,$P79)),'[1]REMOVAL FEES'!$E$1:$E$13,0),3))))*$AA79,FALSE) -> -19.62 | AJ79: =AH79+AI79 -> -40.511167 | AK79: -8.5095833 | AL79: -6.9585022 | AM79: =AK79+AL79 -> -15.468085 | AN79: =(-IF($V79="Yes", IF($X79="Yes", VLOOKUP($W79, '[1]Storage Fees'!A:M, 13, FALSE), VLOOKUP($W79, '[1]Storage Fees'!A:M, 10, FALSE)), IF($X79="Yes", VLOOKUP($W79, '[1]Storage Fees'!A:M, 7, FALSE), VLOOKUP($W79, '[1]Storage Fees'!A:M, 4, FALSE))) * U79)*1.5 -> -1.3886719
A80: 8 | B80: Tushar | E80: CFB | F80: B12J | G80: RETURNLESS REFUND | H80: 25 | I80: 10 | J80: 10 | K80: =H80&"x"&I80&"x"&J80 -> 25x10x10 | L80: =(H80*I80*J80)/139 -> 17.985612 | M80: =(H80*I80*J80)/139 -> 17.985612 | N80: =IF(AND(M80>0,M80<=0.25),0.25,IF(AND(M80>0.25,M80<=0.5),0.5,IF(AND(M80>0.5,M80<=0.75),0.75,ROUNDUP(M80,0)))) -> 18 | O80: 12 | P80: =ROUNDUP(MAX(L80,O80),0) -> 18 | Q80: =P80*16 -> 288 | R80: =IF(RIGHT(S80,13)="standard-size","Standard-size","Oversize") -> Oversize | S80: =IF(AND($P80<=$J$50,$H80<=$G$50,$I80<=$H$50,$J80<=$I$50),$A$50,IF(AND($P80<=$J$51,$H80<=$G$51,$I80<=$H$51,$J80<=$I$51),$A$51,IF(AND($H80<=$G$52,$I80<=$H$52,$J80<=$I$52,$P80<=$J$52),$A$52,IF(AND($P80<=$J$53,OR(H$8>$G$53,$I80>$H$53,$J80>$I$53)),$A$53,IF(AND($P80>$J$53,$P80<=$J$54),$A$54,IF(AND($P80>$J$54,$P80<=$J$55),$A$55,$A$56)))))) -> Large bulky | T80: Large bulky: up to 30 lb | U80: =(H80*I80*J80)/1728 -> 1.4467593 | V80: No | W80: 22 – 28 | X80: Yes | Y80: 2 | Z80: 3 | AA80: 1 | AD80: 0 | AE80: =-AD80*0.15 -> 0 | AF80: =-IFERROR(IFERROR(VLOOKUP(ROUNDUP($Q80,0),'FBA FEES'!$L$2:$Q$203,MATCH($S80,'FBA FEES'!$L$2:$Q$2,0),FALSE),VLOOKUP(ROUNDUP($Q80,0),'FBA FEES'!$C$6:$F$123,MATCH($S80,'FBA FEES'!$C$6:$F$6,0),FALSE)),0) -> -16.07 | AG80: -7 | AH80: =AE80+AF80 -> -16.07 | AI80: =-IFERROR(IF($Y80=1,INDEX('[1]REMOVAL FEES'!$A$1:$C$22,MATCH(CONCATENATE("Standard Size",$P80),'[1]REMOVAL FEES'!$A$1:$A$22,0),3),IF($Y80=2,IF($P80>10,(($P80-10)*1.06)+INDEX('[1]REMOVAL FEES'!$E$1:$G$22,MATCH(CONCATENATE("Large bulky, extra-large and special handling items",IF($P80>=11,11,$P80)),'[1]REMOVAL FEES'!$E$1:$E$13,0),3),INDEX('[1]REMOVAL FEES'!$E$1:$G$22,MATCH(CONCATENATE("Large bulky, extra-large and special handling items",IF($P80>=11,11,$P80)),'[1]REMOVAL FEES'!$E$1:$E$13,0),3))))*$AA80,FALSE) -> -22.8 | AJ80: =AH80+AI80 -> -38.87 | AK80: 0 | AL80: 0 | AM80: =AK80+AL80 -> 0 | AN80: =(-IF($V80="Yes", IF($X80="Yes", VLOOKUP($W80, '[1]Storage Fees'!A:M, 13, FALSE), VLOOKUP($W80, '[1]Storage Fees'!A:M, 10, FALSE)), IF($X80="Yes", VLOOKUP($W80, '[1]Storage Fees'!A:M, 7, FALSE), VLOOKUP($W80, '[1]Storage Fees'!A:M, 4, FALSE))) * U80)*1.5 -> -1.7144097
A81: 9 | B81: Tushar | E81: CFB | F81: B12X | G81: RETURNLESS REFUND | H81: 25 | I81: 14 | J81: 14 | K81: =H81&"x"&I81&"x"&J81 -> 25x14x14 | L81: =(H81*I81*J81)/139 -> 35.251799 | M81: =(H81*I81*J81)/139 -> 35.251799 | N81: =IF(AND(M81>0,M81<=0.25),0.25,IF(AND(M81>0.25,M81<=0.5),0.5,IF(AND(M81>0.5,M81<=0.75),0.75,ROUNDUP(M81,0)))) -> 36 | O81: 21.1875 | P81: =ROUNDUP(MAX(L81,O81),0) -> 36 | Q81: =P81*16 -> 576 | R81: =IF(RIGHT(S81,13)="standard-size","Standard-size","Oversize") -> Oversize | S81: =IF(AND($P81<=$J$50,$H81<=$G$50,$I81<=$H$50,$J81<=$I$50),$A$50,IF(AND($P81<=$J$51,$H81<=$G$51,$I81<=$H$51,$J81<=$I$51),$A$51,IF(AND($H81<=$G$52,$I81<=$H$52,$J81<=$I$52,$P81<=$J$52),$A$52,IF(AND($P81<=$J$53,OR(H$8>$G$53,$I81>$H$53,$J81>$I$53)),$A$53,IF(AND($P81>$J$53,$P81<=$J$54),$A$54,IF(AND($P81>$J$54,$P81<=$J$55),$A$55,$A$56)))))) -> Large bulky | T81: Large bulky: above 30 lb | U81: =(H81*I81*J81)/1728 -> 2.8356481 | V81: No | W81: 22 – 28 | X81: Yes | Y81: 2 | Z81: 3 | AA81: 1 | AD81: 84.864685 | AE81: =-AD81*0.15 -> -12.729703 | AF81: =-IFERROR(IFERROR(VLOOKUP(ROUNDUP($Q81,0),'FBA FEES'!$L$2:$Q$203,MATCH($S81,'FBA FEES'!$L$2:$Q$2,0),FALSE),VLOOKUP(ROUNDUP($Q81,0),'FBA FEES'!$C$6:$F$123,MATCH($S81,'FBA FEES'!$C$6:$F$6,0),FALSE)),0) -> -22.91 | AG81: -7 | AH81: =AE81+AF81 -> -35.639703 | AI81: =-IFERROR(IF($Y81=1,INDEX('[1]REMOVAL FEES'!$A$1:$C$22,MATCH(CONCATENATE("Standard Size",$P81),'[1]REMOVAL FEES'!$A$1:$A$22,0),3),IF($Y81=2,IF($P81>10,(($P81-10)*1.06)+INDEX('[1]REMOVAL FEES'!$E$1:$G$22,MATCH(CONCATENATE("Large bulky, extra-large and special handling items",IF($P81>=11,11,$P81)),'[1]REMOVAL FEES'!$E$1:$E$13,0),3),INDEX('[1]REMOVAL FEES'!$E$1:$G$22,MATCH(CONCATENATE("Large bulky, extra-large and special handling items",IF($P81>=11,11,$P81)),'[1]REMOVAL FEES'!$E$1:$E$13,0),3))))*$AA81,FALSE) -> -41.88 | AJ81: =AH81+AI81 -> -77.519703 | AK81: -24.410548 | AL81: -12.512238 | AM81: =AK81+AL81 -> -36.922786 | AN81: =(-IF($V81="Yes", IF($X81="Yes", VLOOKUP($W81, '[1]Storage Fees'!A:M, 13, FALSE), VLOOKUP($W81, '[1]Storage Fees'!A:M, 10, FALSE)), IF($X81="Yes", VLOOKUP($W81, '[1]Storage Fees'!A:M, 7, FALSE), VLOOKUP($W81, '[1]Storage Fees'!A:M, 4, FALSE))) * U81)*1.5 -> -3.3602431
A82: 10 | B82: Tushar | E82: CFB | F82: B9J | G82: RETURNLESS REFUND | H82: 25 | I82: 6 | J82: 6 | K82: =H82&"x"&I82&"x"&J82 -> 25x6x6 | L82: =(H82*I82*J82)/139 -> 6.4748201 | M82: =(H82*I82*J82)/139 -> 6.4748201 | N82: =IF(AND(M82>0,M82<=0.25),0.25,IF(AND(M82>0.25,M82<=0.5),0.5,IF(AND(M82>0.5,M82<=0.75),0.75,ROUNDUP(M82,0)))) -> 7 | O82: 3 | P82: =ROUNDUP(MAX(L82,O82),0) -> 7 | Q82: =P82*16 -> 112 | R82: =IF(RIGHT(S82,13)="standard-size","Standard-size","Oversize") -> Oversize | S82: =IF(AND($P82<=$J$50,$H82<=$G$50,$I82<=$H$50,$J82<=$I$50),$A$50,IF(AND($P82<=$J$51,$H82<=$G$51,$I82<=$H$51,$J82<=$I$51),$A$51,IF(AND($H82<=$G$52,$I82<=$H$52,$J82<=$I$52,$P82<=$J$52),$A$52,IF(AND($P82<=$J$53,OR(H$8>$G$53,$I82>$H$53,$J82>$I$53)),$A$53,IF(AND($P82>$J$53,$P82<=$J$54),$A$54,IF(AND($P82>$J$54,$P82<=$J$55),$A$55,$A$56)))))) -> Large bulky | T82: Large bulky: up to 30 lb | U82: =(H82*I82*J82)/1728 -> 0.52083333 | V82: No | W82: 22 – 28 | X82: Yes | Y82: 2 | Z82: 3 | AA82: 1 | AD82: 29.265098 | AE82: =-AD82*0.15 -> -4.3897647 | AF82: =-IFERROR(IFERROR(VLOOKUP(ROUNDUP($Q82,0),'FBA FEES'!$L$2:$Q$203,MATCH($S82,'FBA FEES'!$L$2:$Q$2,0),FALSE),VLOOKUP(ROUNDUP($Q82,0),'FBA FEES'!$C$6:$F$123,MATCH($S82,'FBA FEES'!$C$6:$F$6,0),FALSE)),0) -> -11.89 | AG82: -7 | AH82: =AE82+AF82 -> -16.279765 | AI82: =-IFERROR(IF($Y82=1,INDEX('[1]REMOVAL FEES'!$A$1:$C$22,MATCH(CONCATENATE("Standard Size",$P82),'[1]REMOVAL FEES'!$A$1:$A$22,0),3),IF($Y82=2,IF($P82>10,(($P82-10)*1.06)+INDEX('[1]REMOVAL FEES'!$E$1:$G$22,MATCH(CONCATENATE("Large bulky, extra-large and special handling items",IF($P82>=11,11,$P82)),'[1]REMOVAL FEES'!$E$1:$E$13,0),3),INDEX('[1]REMOVAL FEES'!$E$1:$G$22,MATCH(CONCATENATE("Large bulky, extra-large and special handling items",IF($P82>=11,11,$P82)),'[1]REMOVAL FEES'!$E$1:$E$13,0),3))))*$AA82,FALSE) -> -10.04 | AJ82: =AH82+AI82 -> -26.319765 | AK82: -3.6053559 | AL82: -5.6417007 | AM82: =AK82+AL82 -> -9.2470567 | AN82: =(-IF($V82="Yes", IF($X82="Yes", VLOOKUP($W82, '[1]Storage Fees'!A:M, 13, FALSE), VLOOKUP($W82, '[1]Storage Fees'!A:M, 10, FALSE)), IF($X82="Yes", VLOOKUP($W82, '[1]Storage Fees'!A:M, 7, FALSE), VLOOKUP($W82, '[1]Storage Fees'!A:M, 4, FALSE))) * U82)*1.5 -> -0.6171875
A83: 11 | B83: Tushar | E83: CFB | F83: BS10 | G83: RETURNLESS REFUND | H83: 25 | I83: 14 | J83: 14 | K83: =H83&"x"&I83&"x"&J83 -> 25x14x14 | L83: =(H83*I83*J83)/139 -> 35.251799 | M83: =(H83*I83*J83)/139 -> 35.251799 | N83: =IF(AND(M83>0,M83<=0.25),0.25,IF(AND(M83>0.25,M83<=0.5),0.5,IF(AND(M83>0.5,M83<=0.75),0.75,ROUNDUP(M83,0)))) -> 36 | O83: 19 | P83: =ROUNDUP(MAX(L83,O83),0) -> 36 | Q83: =P83*16 -> 576 | R83: =IF(RIGHT(S83,13)="standard-size","Standard-size","Oversize") -> Oversize | S83: =IF(AND($P83<=$J$50,$H83<=$G$50,$I83<=$H$50,$J83<=$I$50),$A$50,IF(AND($P83<=$J$51,$H83<=$G$51,$I83<=$H$51,$J83<=$I$51),$A$51,IF(AND($H83<=$G$52,$I83<=$H$52,$J83<=$I$52,$P83<=$J$52),$A$52,IF(AND($P83<=$J$53,OR(H$8>$G$53,$I83>$H$53,$J83>$I$53)),$A$53,IF(AND($P83>$J$53,$P83<=$J$54),$A$54,IF(AND($P83>$J$54,$P83<=$J$55),$A$55,$A$56)))))) -> Large bulky | T83: Large bulky: above 30 lb | U83: =(H83*I83*J83)/1728 -> 2.8356481 | V83: No | W83: 22 – 28 | X83: Yes | Y83: 2 | Z83: 3 | AA83: 1 | AD83: 83.830892 | AE83: =-AD83*0.15 -> -12.574634 | AF83: =-IFERROR(IFERROR(VLOOKUP(ROUNDUP($Q83,0),'FBA FEES'!$L$2:$Q$203,MATCH($S83,'FBA FEES'!$L$2:$Q$2,0),FALSE),VLOOKUP(ROUNDUP($Q83,0),'FBA FEES'!$C$6:$F$123,MATCH($S83,'FBA FEES'!$C$6:$F$6,0),FALSE)),0) -> -22.91 | AG83: -7 | AH83: =AE83+AF83 -> -35.484634 | AI83: =-IFERROR(IF($Y83=1,INDEX('[1]REMOVAL FEES'!$A$1:$C$22,MATCH(CONCATENATE("Standard Size",$P83),'[1]REMOVAL FEES'!$A$1:$A$22,0),3),IF($Y83=2,IF($P83>10,(($P83-10)*1.06)+INDEX('[1]REMOVAL FEES'!$E$1:$G$22,MATCH(CONCATENATE("Large bulky, extra-large and special handling items",IF($P83>=11,11,$P83)),'[1]REMOVAL FEES'!$E$1:$E$13,0),3),INDEX('[1]REMOVAL FEES'!$E$1:$G$22,MATCH(CONCATENATE("Large bulky, extra-large and special handling items",IF($P83>=11,11,$P83)),'[1]REMOVAL FEES'!$E$1:$E$13,0),3))))*$AA83,FALSE) -> -41.88 | AJ83: =AH83+AI83 -> -77.364634 | AK83: -23.79 | AL83: -12.438 | AM83: =AK83+AL83 -> -36.228 | AN83: =(-IF($V83="Yes", IF($X83="Yes", VLOOKUP($W83, '[1]Storage Fees'!A:M, 13, FALSE), VLOOKUP($W83, '[1]Storage Fees'!A:M, 10, FALSE)), IF($X83="Yes", VLOOKUP($W83, '[1]Storage Fees'!A:M, 7, FALSE), VLOOKUP($W83, '[1]Storage Fees'!A:M, 4, FALSE))) * U83)*1.5 -> -3.3602431
A84: 12 | C84: DLTD | E84: CFB | F84: BS13 | G84: - | H84: 0 | I84: 0 | J84: 0 | K84: =H84&"x"&I84&"x"&J84 -> 0x0x0 | L84: =(H84*I84*J84)/139 -> 0 | M84: =(H84*I84*J84)/139 -> 0 | N84: =IF(AND(M84>0,M84<=0.25),0.25,IF(AND(M84>0.25,M84<=0.5),0.5,IF(AND(M84>0.5,M84<=0.75),0.75,ROUNDUP(M84,0)))) -> 0 | O84: 0 | P84: =ROUNDUP(MAX(L84,O84),0) -> 0 | Q84: =P84*16 -> 0 | R84: =IF(RIGHT(S84,13)="standard-size","Standard-size","Oversize") -> Standard-size | S84: =IF(AND($P84<=$J$50,$H84<=$G$50,$I84<=$H$50,$J84<=$I$50),$A$50,IF(AND($P84<=$J$51,$H84<=$G$51,$I84<=$H$51,$J84<=$I$51),$A$51,IF(AND($H84<=$G$52,$I84<=$H$52,$J84<=$I$52,$P84<=$J$52),$A$52,IF(AND($P84<=$J$53,OR(H$8>$G$53,$I84>$H$53,$J84>$I$53)),$A$53,IF(AND($P84>$J$53,$P84<=$J$54),$A$54,IF(AND($P84>$J$54,$P84<=$J$55),$A$55,$A$56)))))) -> Small standard-size | T84: Small standard: 4 oz or less | U84: =(H84*I84*J84)/1728 -> 0 | V84: No | W84: 22 – 28 | X84: No | Y84: 1 | Z84: 1 | AA84: 1 | AD84: 0 | AE84: =-AD84*0.15 -> 0 | AF84: =-IFERROR(IFERROR(VLOOKUP(ROUNDUP($Q84,0),'FBA FEES'!$L$2:$Q$203,MATCH($S84,'FBA FEES'!$L$2:$Q$2,0),FALSE),VLOOKUP(ROUNDUP($Q84,0),'FBA FEES'!$C$6:$F$123,MATCH($S84,'FBA FEES'!$C$6:$F$6,0),FALSE)),0) -> 0 | AG84: -2 | AH84: =AE84+AF84 -> 0 | AI84: =-IFERROR(IF($Y84=1,INDEX('[1]REMOVAL FEES'!$A$1:$C$22,MATCH(CONCATENATE("Standard Size",$P84),'[1]REMOVAL FEES'!$A$1:$A$22,0),3),IF($Y84=2,IF($P84>10,(($P84-10)*1.06)+INDEX('[1]REMOVAL FEES'!$E$1:$G$22,MATCH(CONCATENATE("Large bulky, extra-large and special handling items",IF($P84>=11,11,$P84)),'[1]REMOVAL FEES'!$E$1:$E$13,0),3),INDEX('[1]REMOVAL FEES'!$E$1:$G$22,MATCH(CONCATENATE("Large bulky, extra-large and special handling items",IF($P84>=11,11,$P84)),'[1]REMOVAL FEES'!$E$1:$E$13,0),3))))*$AA84,FALSE) -> 0 | AJ84: =AH84+AI84 -> 0 | AK84: 0 | AL84: 0 | AM84: =AK84+AL84 -> 0 | AN84: =(-IF($V84="Yes", IF($X84="Yes", VLOOKUP($W84, '[1]Storage Fees'!A:M, 13, FALSE), VLOOKUP($W84, '[1]Storage Fees'!A:M, 10, FALSE)), IF($X84="Yes", VLOOKUP($W84, '[1]Storage Fees'!A:M, 7, FALSE), VLOOKUP($W84, '[1]Storage Fees'!A:M, 4, FALSE))) * U84)*1.5 -> 0
A85: 13 | B85: Tushar | E85: CFB | F85: BS9 | G85: RETURNLESS REFUND | H85: 25 | I85: 10 | J85: 10 | K85: =H85&"x"&I85&"x"&J85 -> 25x10x10 | L85: =(H85*I85*J85)/139 -> 17.985612 | M85: =(H85*I85*J85)/139 -> 17.985612 | N85: =IF(AND(M85>0,M85<=0.25),0.25,IF(AND(M85>0.25,M85<=0.5),0.5,IF(AND(M85>0.5,M85<=0.75),0.75,ROUNDUP(M85,0)))) -> 18 | O85: 10 | P85: =ROUNDUP(MAX(L85,O85),0) -> 18 | Q85: =P85*16 -> 288 | R85: =IF(RIGHT(S85,13)="standard-size","Standard-size","Oversize") -> Oversize | S85: =IF(AND($P85<=$J$50,$H85<=$G$50,$I85<=$H$50,$J85<=$I$50),$A$50,IF(AND($P85<=$J$51,$H85<=$G$51,$I85<=$H$51,$J85<=$I$51),$A$51,IF(AND($H85<=$G$52,$I85<=$H$52,$J85<=$I$52,$P85<=$J$52),$A$52,IF(AND($P85<=$J$53,OR(H$8>$G$53,$I85>$H$53,$J85>$I$53)),$A$53,IF(AND($P85>$J$53,$P85<=$J$54),$A$54,IF(AND($P85>$J$54,$P85<=$J$55),$A$55,$A$56)))))) -> Large bulky | T85: Large bulky: up to 30 lb | U85: =(H85*I85*J85)/1728 -> 1.4467593 | V85: No | W85: 22 – 28 | X85: Yes | Y85: 2 | Z85: 3 | AA85: 1 | AD85: 64.868709 | AE85: =-AD85*0.15 -> -9.7303063 | AF85: =-IFERROR(IFERROR(VLOOKUP(ROUNDUP($Q85,0),'FBA FEES'!$L$2:$Q$203,MATCH($S85,'FBA FEES'!$L$2:$Q$2,0),FALSE),VLOOKUP(ROUNDUP($Q85,0),'FBA FEES'!$C$6:$F$123,MATCH($S85,'FBA FEES'!$C$6:$F$6,0),FALSE)),0) -> -16.07 | AG85: -7 | AH85: =AE85+AF85 -> -25.800306 | AI85: =-IFERROR(IF($Y85=1,INDEX('[1]REMOVAL FEES'!$A$1:$C$22,MATCH(CONCATENATE("Standard Size",$P85),'[1]REMOVAL FEES'!$A$1:$A$22,0),3),IF($Y85=2,IF($P85>10,(($P85-10)*1.06)+INDEX('[1]REMOVAL FEES'!$E$1:$G$22,MATCH(CONCATENATE("Large bulky, extra-large and special handling items",IF($P85>=11,11,$P85)),'[1]REMOVAL FEES'!$E$1:$E$13,0),3),INDEX('[1]REMOVAL FEES'!$E$1:$G$22,MATCH(CONCATENATE("Large bulky, extra-large and special handling items",IF($P85>=11,11,$P85)),'[1]REMOVAL FEES'!$E$1:$E$13,0),3))))*$AA85,FALSE) -> -22.8 | AJ85: =AH85+AI85 -> -48.600306 | AK85: -17.21 | AL85: -8.643611 | AM85: =AK85+AL85 -> -25.853611 | AN85: =(-IF($V85="Yes", IF($X85="Yes", VLOOKUP($W85, '[1]Storage Fees'!A:M, 13, FALSE), VLOOKUP($W85, '[1]Storage Fees'!A:M, 10, FALSE)), IF($X85="Yes", VLOOKUP($W85, '[1]Storage Fees'!A:M, 7, FALSE), VLOOKUP($W85, '[1]Storage Fees'!A:M, 4, FALSE))) * U85)*1.5 -> -1.7144097
A86: 14 | C86: DLTD | E86: CSM | F86: CM-B209 | G86: - | H86: 0 | I86: 0 | J86: 0 | K86: =H86&"x"&I86&"x"&J86 -> 0x0x0 | L86: =(H86*I86*J86)/139 -> 0 | M86: =(H86*I86*J86)/139 -> 0 | N86: =IF(AND(M86>0,M86<=0.25),0.25,IF(AND(M86>0.25,M86<=0.5),0.5,IF(AND(M86>0.5,M86<=0.75),0.75,ROUNDUP(M86,0)))) -> 0 | O86: 0 | P86: =ROUNDUP(MAX(L86,O86),0) -> 0 | Q86: =P86*16 -> 0 | R86: =IF(RIGHT(S86,13)="standard-size","Standard-size","Oversize") -> Standard-size | S86: =IF(AND($P86<=$J$50,$H86<=$G$50,$I86<=$H$50,$J86<=$I$50),$A$50,IF(AND($P86<=$J$51,$H86<=$G$51,$I86<=$H$51,$J86<=$I$51),$A$51,IF(AND($H86<=$G$52,$I86<=$H$52,$J86<=$I$52,$P86<=$J$52),$A$52,IF(AND($P86<=$J$53,OR(H$8>$G$53,$I86>$H$53,$J86>$I$53)),$A$53,IF(AND($P86>$J$53,$P86<=$J$54),$A$54,IF(AND($P86>$J$54,$P86<=$J$55),$A$55,$A$56)))))) -> Small standard-size | T86: Small standard: 4 oz or less | U86: =(H86*I86*J86)/1728 -> 0 | V86: No | W86: 22 – 28 | X86: No | Y86: 1 | Z86: 1 | AA86: 1 | AD86: 0 | AE86: =-AD86*0.15 -> 0 | AF86: =-IFERROR(IFERROR(VLOOKUP(ROUNDUP($Q86,0),'FBA FEES'!$L$2:$Q$203,MATCH($S86,'FBA FEES'!$L$2:$Q$2,0),FALSE),VLOOKUP(ROUNDUP($Q86,0),'FBA FEES'!$C$6:$F$123,MATCH($S86,'FBA FEES'!$C$6:$F$6,0),FALSE)),0) -> 0 | AG86: -10 | AH86: =AE86+AF86 -> 0 | AI86: =-IFERROR(IF($Y86=1,INDEX('[1]REMOVAL FEES'!$A$1:$C$22,MATCH(CONCATENATE("Standard Size",$P86),'[1]REMOVAL FEES'!$A$1:$A$22,0),3),IF($Y86=2,IF($P86>10,(($P86-10)*1.06)+INDEX('[1]REMOVAL FEES'!$E$1:$G$22,MATCH(CONCATENATE("Large bulky, extra-large and special handling items",IF($P86>=11,11,$P86)),'[1]REMOVAL FEES'!$E$1:$E$13,0),3),INDEX('[1]REMOVAL FEES'!$E$1:$G$22,MATCH(CONCATENATE("Large bulky, extra-large and special handling items",IF($P86>=11,11,$P86)),'[1]REMOVAL FEES'!$E$1:$E$13,0),3))))*$AA86,FALSE) -> 0 | AJ86: =AH86+AI86 -> 0 | AK86: 0 | AL86: 0 | AM86: =AK86+AL86 -> 0 | AN86: =(-IF($V86="Yes", IF($X86="Yes", VLOOKUP($W86, '[1]Storage Fees'!A:M, 13, FALSE), VLOOKUP($W86, '[1]Storage Fees'!A:M, 10, FALSE)), IF($X86="Yes", VLOOKUP($W86, '[1]Storage Fees'!A:M, 7, FALSE), VLOOKUP($W86, '[1]Storage Fees'!A:M, 4, FALSE))) * U86)*1.5 -> 0
A87: 15 | B87: Tushar | E87: CP | F87: CP-1-2425F | G87: RETURNLESS REFUND | H87: 25 | I87: 5 | J87: 5 | K87: =H87&"x"&I87&"x"&J87 -> 25x5x5 | L87: =(H87*I87*J87)/139 -> 4.4964029 | M87: =(H87*I87*J87)/139 -> 4.4964029 | N87: =IF(AND(M87>0,M87<=0.25),0.25,IF(AND(M87>0.25,M87<=0.5),0.5,IF(AND(M87>0.5,M87<=0.75),0.75,ROUNDUP(M87,0)))) -> 5 | O87: 3 | P87: =ROUNDUP(MAX(L87,O87),0) -> 5 | Q87: =P87*16 -> 80 | R87: =IF(RIGHT(S87,13)="standard-size","Standard-size","Oversize") -> Oversize | S87: =IF(AND($P87<=$J$50,$H87<=$G$50,$I87<=$H$50,$J87<=$I$50),$A$50,IF(AND($P87<=$J$51,$H87<=$G$51,$I87<=$H$51,$J87<=$I$51),$A$51,IF(AND($H87<=$G$52,$I87<=$H$52,$J87<=$I$52,$P87<=$J$52),$A$52,IF(AND($P87<=$J$53,OR(H$8>$G$53,$I87>$H$53,$J87>$I$53)),$A$53,IF(AND($P87>$J$53,$P87<=$J$54),$A$54,IF(AND($P87>$J$54,$P87<=$J$55),$A$55,$A$56)))))) -> Large bulky | T87: Large bulky: up to 30 lb | U87: =(H87*I87*J87)/1728 -> 0.36168981 | V87: No | W87: 22 – 28 | X87: Yes | Y87: 2 | Z87: 3 | AA87: 1 | AD87: 67.868153 | AE87: =-AD87*0.15 -> -10.180223 | AF87: =-IFERROR(IFERROR(VLOOKUP(ROUNDUP($Q87,0),'FBA FEES'!$L$2:$Q$203,MATCH($S87,'FBA FEES'!$L$2:$Q$2,0),FALSE),VLOOKUP(ROUNDUP($Q87,0),'FBA FEES'!$C$6:$F$123,MATCH($S87,'FBA FEES'!$C$6:$F$6,0),FALSE)),0) -> -11.13 | AG87: -10 | AH87: =AE87+AF87 -> -21.310223 | AI87: =-IFERROR(IF($Y87=1,INDEX('[1]REMOVAL FEES'!$A$1:$C$22,MATCH(CONCATENATE("Standard Size",$P87),'[1]REMOVAL FEES'!$A$1:$A$22,0),3),IF($Y87=2,IF($P87>10,(($P87-10)*1.06)+INDEX('[1]REMOVAL FEES'!$E$1:$G$22,MATCH(CONCATENATE("Large bulky, extra-large and special handling items",IF($P87>=11,11,$P87)),'[1]REMOVAL FEES'!$E$1:$E$13,0),3),INDEX('[1]REMOVAL FEES'!$E$1:$G$22,MATCH(CONCATENATE("Large bulky, extra-large and special handling items",IF($P87>=11,11,$P87)),'[1]REMOVAL FEES'!$E$1:$E$13,0),3))))*$AA87,FALSE) -> -10.04 | AJ87: =AH87+AI87 -> -31.350223 | AK87: -17.076831 | AL87: -6.2690099 | AM87: =AK87+AL87 -> -23.34584 | AN87: =(-IF($V87="Yes", IF($X87="Yes", VLOOKUP($W87, '[1]Storage Fees'!A:M, 13, FALSE), VLOOKUP($W87, '[1]Storage Fees'!A:M, 10, FALSE)), IF($X87="Yes", VLOOKUP($W87, '[1]Storage Fees'!A:M, 7, FALSE), VLOOKUP($W87, '[1]Storage Fees'!A:M, 4, FALSE))) * U87)*1.5 -> -0.42860243
A88: 16 | B88: Tushar | E88: CP | F88: CP-2-2425F | G88: - | H88: 25 | I88: 6 | J88: 6 | K88: =H88&"x"&I88&"x"&J88 -> 25x6x6 | L88: =(H88*I88*J88)/139 -> 6.4748201 | M88: =(H88*I88*J88)/139 -> 6.4748201 | N88: =IF(AND(M88>0,M88<=0.25),0.25,IF(AND(M88>0.25,M88<=0.5),0.5,IF(AND(M88>0.5,M88<=0.75),0.75,ROUNDUP(M88,0)))) -> 7 | O88: 4 | P88: =ROUNDUP(MAX(L88,O88),0) -> 7 | Q88: =P88*16 -> 112 | R88: =IF(RIGHT(S88,13)="standard-size","Standard-size","Oversize") -> Oversize | S88: =IF(AND($P88<=$J$50,$H88<=$G$50,$I88<=$H$50,$J88<=$I$50),$A$50,IF(AND($P88<=$J$51,$H88<=$G$51,$I88<=$H$51,$J88<=$I$51),$A$51,IF(AND($H88<=$G$52,$I88<=$H$52,$J88<=$I$52,$P88<=$J$52),$A$52,IF(AND($P88<=$J$53,OR(H$8>$G$53,$I88>$H$53,$J88>$I$53)),$A$53,IF(AND($P88>$J$53,$P88<=$J$54),$A$54,IF(AND($P88>$J$54,$P88<=$J$55),$A$55,$A$56)))))) -> Large bulky | T88: Large bulky: up to 30 lb | U88: =(H88*I88*J88)/1728 -> 0.52083333 | V88: No | W88: 22 – 28 | X88: Yes | Y88: 2 | Z88: 3 | AA88: 1 | AD88: 95.362045 | AE88: =-AD88*0.15 -> -14.304307 | AF88: =-IFERROR(IFERROR(VLOOKUP(ROUNDUP($Q88,0),'FBA FEES'!$L$2:$Q$203,MATCH($S88,'FBA FEES'!$L$2:$Q$2,0),FALSE),VLOOKUP(ROUNDUP($Q88,0),'FBA FEES'!$C$6:$F$123,MATCH($S88,'FBA FEES'!$C$6:$F$6,0),FALSE)),0) -> -11.89 | AG88: -10 | AH88: =AE88+AF88 -> -26.194307 | AI88: =-IFERROR(IF($Y88=1,INDEX('[1]REMOVAL FEES'!$A$1:$C$22,MATCH(CONCATENATE("Standard Size",$P88),'[1]REMOVAL FEES'!$A$1:$A$22,0),3),IF($Y88=2,IF($P88>10,(($P88-10)*1.06)+INDEX('[1]REMOVAL FEES'!$E$1:$G$22,MATCH(CONCATENATE("Large bulky, extra-large and special handling items",IF($P88>=11,11,$P88)),'[1]REMOVAL FEES'!$E$1:$E$13,0),3),INDEX('[1]REMOVAL FEES'!$E$1:$G$22,MATCH(CONCATENATE("Large bulky, extra-large and special handling items",IF($P88>=11,11,$P88)),'[1]REMOVAL FEES'!$E$1:$E$13,0),3))))*$AA88,FALSE) -> -10.04 | AJ88: =AH88+AI88 -> -36.234307 | AK88: -33.75 | AL88: -6.5592702 | AM88: =AK88+AL88 -> -40.30927 | AN88: =(-IF($V88="Yes", IF($X88="Yes", VLOOKUP($W88, '[1]Storage Fees'!A:M, 13, FALSE), VLOOKUP($W88, '[1]Storage Fees'!A:M, 10, FALSE)), IF($X88="Yes", VLOOKUP($W88, '[1]Storage Fees'!A:M, 7, FALSE), VLOOKUP($W88, '[1]Storage Fees'!A:M, 4, FALSE))) * U88)*1.5 -> -0.6171875
A89: 17 | B89: Tushar | E89: CP | F89: CP-3-2425F | G89: - | H89: 26 | I89: 7 | J89: 7 | K89: =H89&"x"&I89&"x"&J89 -> 26x7x7 | L89: =(H89*I89*J89)/139 -> 9.1654676 | M89: =(H89*I89*J89)/139 -> 9.1654676 | N89: =IF(AND(M89>0,M89<=0.25),0.25,IF(AND(M89>0.25,M89<=0.5),0.5,IF(AND(M89>0.5,M89<=0.75),0.75,ROUNDUP(M89,0)))) -> 10 | O89: 7 | P89: =ROUNDUP(MAX(L89,O89),0) -> 10 | Q89: =P89*16 -> 160 | R89: =IF(RIGHT(S89,13)="standard-size","Standard-size","Oversize") -> Oversize | S89: =IF(AND($P89<=$J$50,$H89<=$G$50,$I89<=$H$50,$J89<=$I$50),$A$50,IF(AND($P89<=$J$51,$H89<=$G$51,$I89<=$H$51,$J89<=$I$51),$A$51,IF(AND($H89<=$G$52,$I89<=$H$52,$J89<=$I$52,$P89<=$J$52),$A$52,IF(AND($P89<=$J$53,OR(H$8>$G$53,$I89>$H$53,$J89>$I$53)),$A$53,IF(AND($P89>$J$53,$P89<=$J$54),$A$54,IF(AND($P89>$J$54,$P89<=$J$55),$A$55,$A$56)))))) -> Large bulky | T89: Large bulky: up to 30 lb | U89: =(H89*I89*J89)/1728 -> 0.73726852 | V89: No | W89: 22 – 28 | X89: Yes | Y89: 2 | Z89: 3 | AA89: 1 | AD89: 112.38871 | AE89: =-AD89*0.15 -> -16.858307 | AF89: =-IFERROR(IFERROR(VLOOKUP(ROUNDUP($Q89,0),'FBA FEES'!$L$2:$Q$203,MATCH($S89,'FBA FEES'!$L$2:$Q$2,0),FALSE),VLOOKUP(ROUNDUP($Q89,0),'FBA FEES'!$C$6:$F$123,MATCH($S89,'FBA FEES'!$C$6:$F$6,0),FALSE)),0) -> -13.03 | AG89: -10 | AH89: =AE89+AF89 -> -29.888307 | AI89: =-IFERROR(IF($Y89=1,INDEX('[1]REMOVAL FEES'!$A$1:$C$22,MATCH(CONCATENATE("Standard Size",$P89),'[1]REMOVAL FEES'!$A$1:$A$22,0),3),IF($Y89=2,IF($P89>10,(($P89-10)*1.06)+INDEX('[1]REMOVAL FEES'!$E$1:$G$22,MATCH(CONCATENATE("Large bulky, extra-large and special handling items",IF($P89>=11,11,$P89)),'[1]REMOVAL FEES'!$E$1:$E$13,0),3),INDEX('[1]REMOVAL FEES'!$E$1:$G$22,MATCH(CONCATENATE("Large bulky, extra-large and special handling items",IF($P89>=11,11,$P89)),'[1]REMOVAL FEES'!$E$1:$E$13,0),3))))*$AA89,FALSE) -> -10.04 | AJ89: =AH89+AI89 -> -39.928307 | AK89: -46.65 | AL89: -6.7047705 | AM89: =AK89+AL89 -> -53.354771 | AN89: =(-IF($V89="Yes", IF($X89="Yes", VLOOKUP($W89, '[1]Storage Fees'!A:M, 13, FALSE), VLOOKUP($W89, '[1]Storage Fees'!A:M, 10, FALSE)), IF($X89="Yes", VLOOKUP($W89, '[1]Storage Fees'!A:M, 7, FALSE), VLOOKUP($W89, '[1]Storage Fees'!A:M, 4, FALSE))) * U89)*1.5 -> -0.87366319
A90: 18 | B90: Tushar | E90: CT | F90: CT-AM04 | G90: RETURNLESS REFUND | H90: 6 | I90: 5 | J90: 5 | K90: =H90&"x"&I90&"x"&J90 -> 6x5x5 | L90: =(H90*I90*J90)/139 -> 1.0791367 | M90: =(H90*I90*J90)/139 -> 1.0791367 | N90: =IF(AND(M90>0,M90<=0.25),0.25,IF(AND(M90>0.25,M90<=0.5),0.5,IF(AND(M90>0.5,M90<=0.75),0.75,ROUNDUP(M90,0)))) -> 2 | O90: 4 | P90: =ROUNDUP(MAX(L90,O90),0) -> 4 | Q90: =P90*16 -> 64 | R90: =IF(RIGHT(S90,13)="standard-size","Standard-size","Oversize") -> Standard-size | S90: =IF(AND($P90<=$J$50,$H90<=$G$50,$I90<=$H$50,$J90<=$I$50),$A$50,IF(AND($P90<=$J$51,$H90<=$G$51,$I90<=$H$51,$J90<=$I$51),$A$51,IF(AND($H90<=$G$52,$I90<=$H$52,$J90<=$I$52,$P90<=$J$52),$A$52,IF(AND($P90<=$J$53,OR(H$8>$G$53,$I90>$H$53,$J90>$I$53)),$A$53,IF(AND($P90>$J$53,$P90<=$J$54),$A$54,IF(AND($P90>$J$54,$P90<=$J$55),$A$55,$A$56)))))) -> Large standard-size | T90: Large standard: 3+ to 20 lb | U90: =(H90*I90*J90)/1728 -> 0.086805556 | V90: No | W90: 22 – 28 | X90: No | Y90: 1 | Z90: 2 | AA90: 1 | AD90: 24.451437 | AE90: =-AD90*0.15 -> -3.6677156 | AF90: =-IFERROR(IFERROR(VLOOKUP(ROUNDUP($Q90,0),'FBA FEES'!$L$2:$Q$203,MATCH($S90,'FBA FEES'!$L$2:$Q$2,0),FALSE),VLOOKUP(ROUNDUP($Q90,0),'FBA FEES'!$C$6:$F$123,MATCH($S90,'FBA FEES'!$C$6:$F$6,0),FALSE)),0) -> -7.24 | AG90: -10 | AH90: =AE90+AF90 -> -10.907716 | AI90: =-IFERROR(IF($Y90=1,INDEX('[1]REMOVAL FEES'!$A$1:$C$22,MATCH(CONCATENATE("Standard Size",$P90),'[1]REMOVAL FEES'!$A$1:$A$22,0),3),IF($Y90=2,IF($P90>10,(($P90-10)*1.06)+INDEX('[1]REMOVAL FEES'!$E$1:$G$22,MATCH(CONCATENATE("Large bulky, extra-large and special handling items",IF($P90>=11,11,$P90)),'[1]REMOVAL FEES'!$E$1:$E$13,0),3),INDEX('[1]REMOVAL FEES'!$E$1:$G$22,MATCH(CONCATENATE("Large bulky, extra-large and special handling items",IF($P90>=11,11,$P90)),'[1]REMOVAL FEES'!$E$1:$E$13,0),3))))*$AA90,FALSE) -> -5.01 | AJ90: =AH90+AI90 -> -15.917716 | AK90: -5.3514372 | AL90: -1.3790597 | AM90: =AK90+AL90 -> -6.7304969 | AN90: =(-IF($V90="Yes", IF($X90="Yes", VLOOKUP($W90, '[1]Storage Fees'!A:M, 13, FALSE), VLOOKUP($W90, '[1]Storage Fees'!A:M, 10, FALSE)), IF($X90="Yes", VLOOKUP($W90, '[1]Storage Fees'!A:M, 7, FALSE), VLOOKUP($W90, '[1]Storage Fees'!A:M, 4, FALSE))) * U90)*1.5 -> -0.15885417
A91: 19 | B91: Tushar | E91: CT | F91: CT-AM125 | G91: RETURNLESS REFUND | H91: 9 | I91: 8 | J91: 8 | K91: =H91&"x"&I91&"x"&J91 -> 9x8x8 | L91: =(H91*I91*J91)/139 -> 4.1438849 | M91: =(H91*I91*J91)/139 -> 4.1438849 | N91: =IF(AND(M91>0,M91<=0.25),0.25,IF(AND(M91>0.25,M91<=0.5),0.5,IF(AND(M91>0.5,M91<=0.75),0.75,ROUNDUP(M91,0)))) -> 5 | O91: 14 | P91: =ROUNDUP(MAX(L91,O91),0) -> 14 | Q91: =P91*16 -> 224 | R91: =IF(RIGHT(S91,13)="standard-size","Standard-size","Oversize") -> Standard-size | S91: =IF(AND($P91<=$J$50,$H91<=$G$50,$I91<=$H$50,$J91<=$I$50),$A$50,IF(AND($P91<=$J$51,$H91<=$G$51,$I91<=$H$51,$J91<=$I$51),$A$51,IF(AND($H91<=$G$52,$I91<=$H$52,$J91<=$I$52,$P91<=$J$52),$A$52,IF(AND($P91<=$J$53,OR(H$8>$G$53,$I91>$H$53,$J91>$I$53)),$A$53,IF(AND($P91>$J$53,$P91<=$J$54),$A$54,IF(AND($P91>$J$54,$P91<=$J$55),$A$55,$A$56)))))) -> Large standard-size | T91: Large standard: 3+ to 20 lb | U91: =(H91*I91*J91)/1728 -> 0.33333333 | V91: No | W91: 22 – 28 | X91: No | Y91: 1 | Z91: 2 | AA91: 1 | AD91: 46.129063 | AE91: =-AD91*0.15 -> -6.9193594 | AF91: =-IFERROR(IFERROR(VLOOKUP(ROUNDUP($Q91,0),'FBA FEES'!$L$2:$Q$203,MATCH($S91,'FBA FEES'!$L$2:$Q$2,0),FALSE),VLOOKUP(ROUNDUP($Q91,0),'FBA FEES'!$C$6:$F$123,MATCH($S91,'FBA FEES'!$C$6:$F$6,0),FALSE)),0) -> -10.44 | AG91: -10 | AH91: =AE91+AF91 -> -17.359359 | AI91: =-IFERROR(IF($Y91=1,INDEX('[1]REMOVAL FEES'!$A$1:$C$22,MATCH(CONCATENATE("Standard Size",$P91),'[1]REMOVAL FEES'!$A$1:$A$22,0),3),IF($Y91=2,IF($P91>10,(($P91-10)*1.06)+INDEX('[1]REMOVAL FEES'!$E$1:$G$22,MATCH(CONCATENATE("Large bulky, extra-large and special handling items",IF($P91>=11,11,$P91)),'[1]REMOVAL FEES'!$E$1:$E$13,0),3),INDEX('[1]REMOVAL FEES'!$E$1:$G$22,MATCH(CONCATENATE("Large bulky, extra-large and special handling items",IF($P91>=11,11,$P91)),'[1]REMOVAL FEES'!$E$1:$E$13,0),3))))*$AA91,FALSE) -> -15.61 | AJ91: =AH91+AI91 -> -32.969359 | AK91: -15.044687 | AL91: -5.2170764 | AM91: =AK91+AL91 -> -20.261764 | AN91: =(-IF($V91="Yes", IF($X91="Yes", VLOOKUP($W91, '[1]Storage Fees'!A:M, 13, FALSE), VLOOKUP($W91, '[1]Storage Fees'!A:M, 10, FALSE)), IF($X91="Yes", VLOOKUP($W91, '[1]Storage Fees'!A:M, 7, FALSE), VLOOKUP($W91, '[1]Storage Fees'!A:M, 4, FALSE))) * U91)*1.5 -> -0.61
A92: 20 | B92: Tushar | E92: CT | F92: CT-AS10 | G92: RETURNLESS REFUND | H92: 10 | I92: 9 | J92: 10 | K92: =H92&"x"&I92&"x"&J92 -> 10x9x10 | L92: =(H92*I92*J92)/139 -> 6.4748201 | M92: =(H92*I92*J92)/139 -> 6.4748201 | N92: =IF(AND(M92>0,M92<=0.25),0.25,IF(AND(M92>0.25,M92<=0.5),0.5,IF(AND(M92>0.5,M92<=0.75),0.75,ROUNDUP(M92,0)))) -> 7 | O92: 11.3125 | P92: =ROUNDUP(MAX(L92,O92),0) -> 12 | Q92: =P92*16 -> 192 | R92: =IF(RIGHT(S92,13)="standard-size","Standard-size","Oversize") -> Oversize | S92: =IF(AND($P92<=$J$50,$H92<=$G$50,$I92<=$H$50,$J92<=$I$50),$A$50,IF(AND($P92<=$J$51,$H92<=$G$51,$I92<=$H$51,$J92<=$I$51),$A$51,IF(AND($H92<=$G$52,$I92<=$H$52,$J92<=$I$52,$P92<=$J$52),$A$52,IF(AND($P92<=$J$53,OR(H$8>$G$53,$I92>$H$53,$J92>$I$53)),$A$53,IF(AND($P92>$J$53,$P92<=$J$54),$A$54,IF(AND($P92>$J$54,$P92<=$J$55),$A$55,$A$56)))))) -> Large bulky | T92: Large bulky: up to 30 lb | U92: =(H92*I92*J92)/1728 -> 0.52083333 | V92: No | W92: 22 – 28 | X92: Yes | Y92: 2 | Z92: 3 | AA92: 1 | AD92: 0 | AE92: =-AD92*0.15 -> 0 | AF92: =-IFERROR(IFERROR(VLOOKUP(ROUNDUP($Q92,0),'FBA FEES'!$L$2:$Q$203,MATCH($S92,'FBA FEES'!$L$2:$Q$2,0),FALSE),VLOOKUP(ROUNDUP($Q92,0),'FBA FEES'!$C$6:$F$123,MATCH($S92,'FBA FEES'!$C$6:$F$6,0),FALSE)),0) -> -13.79 | AG92: -10 | AH92: =AE92+AF92 -> -13.79 | AI92: =-IFERROR(IF($Y92=1,INDEX('[1]REMOVAL FEES'!$A$1:$C$22,MATCH(CONCATENATE("Standard Size",$P92),'[1]REMOVAL FEES'!$A$1:$A$22,0),3),IF($Y92=2,IF($P92>10,(($P92-10)*1.06)+INDEX('[1]REMOVAL FEES'!$E$1:$G$22,MATCH(CONCATENATE("Large bulky, extra-large and special handling items",IF($P92>=11,11,$P92)),'[1]REMOVAL FEES'!$E$1:$E$13,0),3),INDEX('[1]REMOVAL FEES'!$E$1:$G$22,MATCH(CONCATENATE("Large bulky, extra-large and special handling items",IF($P92>=11,11,$P92)),'[1]REMOVAL FEES'!$E$1:$E$13,0),3))))*$AA92,FALSE) -> -16.44 | AJ92: =AH92+AI92 -> -30.23 | AK92: 0 | AL92: 0 | AM92: =AK92+AL92 -> 0 | AN92: =(-IF($V92="Yes", IF($X92="Yes", VLOOKUP($W92, '[1]Storage Fees'!A:M, 13, FALSE), VLOOKUP($W92, '[1]Storage Fees'!A:M, 10, FALSE)), IF($X92="Yes", VLOOKUP($W92, '[1]Storage Fees'!A:M, 7, FALSE), VLOOKUP($W92, '[1]Storage Fees'!A:M, 4, FALSE))) * U92)*1.5 -> -0.6171875
A93: 21 | B93: Tushar | E93: CT | F93: CT-TC22 | G93: - | H93: 10 | I93: 8 | J93: 8 | K93: =H93&"x"&I93&"x"&J93 -> 10x8x8 | L93: =(H93*I93*J93)/139 -> 4.6043165 | M93: =(H93*I93*J93)/139 -> 4.6043165 | N93: =IF(AND(M93>0,M93<=0.25),0.25,IF(AND(M93>0.25,M93<=0.5),0.5,IF(AND(M93>0.5,M93<=0.75),0.75,ROUNDUP(M93,0)))) -> 5 | O93: 23 | P93: =ROUNDUP(MAX(L93,O93),0) -> 23 | Q93: =P93*16 -> 368 | R93: =IF(RIGHT(S93,13)="standard-size","Standard-size","Oversize") -> Oversize | S93: =IF(AND($P93<=$J$50,$H93<=$G$50,$I93<=$H$50,$J93<=$I$50),$A$50,IF(AND($P93<=$J$51,$H93<=$G$51,$I93<=$H$51,$J93<=$I$51),$A$51,IF(AND($H93<=$G$52,$I93<=$H$52,$J93<=$I$52,$P93<=$J$52),$A$52,IF(AND($P93<=$J$53,OR(H$8>$G$53,$I93>$H$53,$J93>$I$53)),$A$53,IF(AND($P93>$J$53,$P93<=$J$54),$A$54,IF(AND($P93>$J$54,$P93<=$J$55),$A$55,$A$56)))))) -> Large bulky | T93: Large bulky: up to 30 lb | U93: =(H93*I93*J93)/1728 -> 0.37037037 | V93: No | W93: 22 – 28 | X93: Yes | Y93: 2 | Z93: 3 | AA93: 1 | AD93: 111.9317 | AE93: =-AD93*0.15 -> -16.789755 | AF93: =-IFERROR(IFERROR(VLOOKUP(ROUNDUP($Q93,0),'FBA FEES'!$L$2:$Q$203,MATCH($S93,'FBA FEES'!$L$2:$Q$2,0),FALSE),VLOOKUP(ROUNDUP($Q93,0),'FBA FEES'!$C$6:$F$123,MATCH($S93,'FBA FEES'!$C$6:$F$6,0),FALSE)),0) -> -17.97 | AG93: -10 | AH93: =AE93+AF93 -> -34.759755 | AI93: =-IFERROR(IF($Y93=1,INDEX('[1]REMOVAL FEES'!$A$1:$C$22,MATCH(CONCATENATE("Standard Size",$P93),'[1]REMOVAL FEES'!$A$1:$A$22,0),3),IF($Y93=2,IF($P93>10,(($P93-10)*1.06)+INDEX('[1]REMOVAL FEES'!$E$1:$G$22,MATCH(CONCATENATE("Large bulky, extra-large and special handling items",IF($P93>=11,11,$P93)),'[1]REMOVAL FEES'!$E$1:$E$13,0),3),INDEX('[1]REMOVAL FEES'!$E$1:$G$22,MATCH(CONCATENATE("Large bulky, extra-large and special handling items",IF($P93>=11,11,$P93)),'[1]REMOVAL FEES'!$E$1:$E$13,0),3))))*$AA93,FALSE) -> -28.1 | AJ93: =AH93+AI93 -> -62.859755 | AK93: -46.8673 | AL93: -10.858541 | AM93: =AK93+AL93 -> -57.725841 | AN93: =(-IF($V93="Yes", IF($X93="Yes", VLOOKUP($W93, '[1]Storage Fees'!A:M, 13, FALSE), VLOOKUP($W93, '[1]Storage Fees'!A:M, 10, FALSE)), IF($X93="Yes", VLOOKUP($W93, '[1]Storage Fees'!A:M, 7, FALSE), VLOOKUP($W93, '[1]Storage Fees'!A:M, 4, FALSE))) * U93)*1.5 -> -0.43888889
A94: 22 | B94: Tushar | E94: CT | F94: CT-WK22 | G94: - | H94: 9 | I94: 9 | J94: 9 | K94: =H94&"x"&I94&"x"&J94 -> 9x9x9 | L94: =(H94*I94*J94)/139 -> 5.2446043 | M94: =(H94*I94*J94)/139 -> 5.2446043 | N94: =IF(AND(M94>0,M94<=0.25),0.25,IF(AND(M94>0.25,M94<=0.5),0.5,IF(AND(M94>0.5,M94<=0.75),0.75,ROUNDUP(M94,0)))) -> 6 | O94: 23 | P94: =ROUNDUP(MAX(L94,O94),0) -> 23 | Q94: =P94*16 -> 368 | R94: =IF(RIGHT(S94,13)="standard-size","Standard-size","Oversize") -> Oversize | S94: =IF(AND($P94<=$J$50,$H94<=$G$50,$I94<=$H$50,$J94<=$I$50),$A$50,IF(AND($P94<=$J$51,$H94<=$G$51,$I94<=$H$51,$J94<=$I$51),$A$51,IF(AND($H94<=$G$52,$I94<=$H$52,$J94<=$I$52,$P94<=$J$52),$A$52,IF(AND($P94<=$J$53,OR(H$8>$G$53,$I94>$H$53,$J94>$I$53)),$A$53,IF(AND($P94>$J$53,$P94<=$J$54),$A$54,IF(AND($P94>$J$54,$P94<=$J$55),$A$55,$A$56)))))) -> Large bulky | T94: Large bulky: up to 30 lb | U94: =(H94*I94*J94)/1728 -> 0.421875 | V94: No | W94: 22 – 28 | X94: Yes | Y94: 2 | Z94: 3 | AA94: 1 | AD94: 76.598409 | AE94: =-AD94*0.15 -> -11.489761 | AF94: =-IFERROR(IFERROR(VLOOKUP(ROUNDUP($Q94,0),'FBA FEES'!$L$2:$Q$203,MATCH($S94,'FBA FEES'!$L$2:$Q$2,0),FALSE),VLOOKUP(ROUNDUP($Q94,0),'FBA FEES'!$C$6:$F$123,MATCH($S94,'FBA FEES'!$C$6:$F$6,0),FALSE)),0) -> -17.97 | AG94: -10 | AH94: =AE94+AF94 -> -29.459761 | AI94: =-IFERROR(IF($Y94=1,INDEX('[1]REMOVAL FEES'!$A$1:$C$22,MATCH(CONCATENATE("Standard Size",$P94),'[1]REMOVAL FEES'!$A$1:$A$22,0),3),IF($Y94=2,IF($P94>10,(($P94-10)*1.06)+INDEX('[1]REMOVAL FEES'!$E$1:$G$22,MATCH(CONCATENATE("Large bulky, extra-large and special handling items",IF($P94>=11,11,$P94)),'[1]REMOVAL FEES'!$E$1:$E$13,0),3),INDEX('[1]REMOVAL FEES'!$E$1:$G$22,MATCH(CONCATENATE("Large bulky, extra-large and special handling items",IF($P94>=11,11,$P94)),'[1]REMOVAL FEES'!$E$1:$E$13,0),3))))*$AA94,FALSE) -> -28.1 | AJ94: =AH94+AI94 -> -57.559761 | AK94: -27.002273 | AL94: -11.744733 | AM94: =AK94+AL94 -> -38.747006 | AN94: =(-IF($V94="Yes", IF($X94="Yes", VLOOKUP($W94, '[1]Storage Fees'!A:M, 13, FALSE), VLOOKUP($W94, '[1]Storage Fees'!A:M, 10, FALSE)), IF($X94="Yes", VLOOKUP($W94, '[1]Storage Fees'!A:M, 7, FALSE), VLOOKUP($W94, '[1]Storage Fees'!A:M, 4, FALSE))) * U94)*1.5 -> -0.49992188
A95: 23 | B95: Janvi | E95: EH | F95: EH-03 | G95: RETURNLESS REFUND | H95: 11 | I95: 4 | J95: 3 | K95: =H95&"x"&I95&"x"&J95 -> 11x4x3 | L95: =(H95*I95*J95)/139 -> 0.94964029 | M95: =(H95*I95*J95)/139 -> 0.94964029 | N95: =IF(AND(M95>0,M95<=0.25),0.25,IF(AND(M95>0.25,M95<=0.5),0.5,IF(AND(M95>0.5,M95<=0.75),0.75,ROUNDUP(M95,0)))) -> 1 | O95: 1.5 | P95: =ROUNDUP(MAX(L95,O95),0) -> 2 | Q95: =P95*16 -> 32 | R95: =IF(RIGHT(S95,13)="standard-size","Standard-size","Oversize") -> Standard-size | S95: =IF(AND($P95<=$J$50,$H95<=$G$50,$I95<=$H$50,$J95<=$I$50),$A$50,IF(AND($P95<=$J$51,$H95<=$G$51,$I95<=$H$51,$J95<=$I$51),$A$51,IF(AND($H95<=$G$52,$I95<=$H$52,$J95<=$I$52,$P95<=$J$52),$A$52,IF(AND($P95<=$J$53,OR(H$8>$G$53,$I95>$H$53,$J95>$I$53)),$A$53,IF(AND($P95>$J$53,$P95<=$J$54),$A$54,IF(AND($P95>$J$54,$P95<=$J$55),$A$55,$A$56)))))) -> Large standard-size | T95: Large standard: 1+ to 2 lb | U95: =(H95*I95*J95)/1728 -> 0.076388889 | V95: No | W95: 22 – 28 | X95: No | Y95: 1 | Z95: 2 | AA95: 1 | AD95: 26.964016 | AE95: =-AD95*0.15 -> -4.0446025 | AF95: =-IFERROR(IFERROR(VLOOKUP(ROUNDUP($Q95,0),'FBA FEES'!$L$2:$Q$203,MATCH($S95,'FBA FEES'!$L$2:$Q$2,0),FALSE),VLOOKUP(ROUNDUP($Q95,0),'FBA FEES'!$C$6:$F$123,MATCH($S95,'FBA FEES'!$C$6:$F$6,0),FALSE)),0) -> -5.77 | AG95: -10 | AH95: =AE95+AF95 -> -9.8146025 | AI95: =-IFERROR(IF($Y95=1,INDEX('[1]REMOVAL FEES'!$A$1:$C$22,MATCH(CONCATENATE("Standard Size",$P95),'[1]REMOVAL FEES'!$A$1:$A$22,0),3),IF($Y95=2,IF($P95>10,(($P95-10)*1.06)+INDEX('[1]REMOVAL FEES'!$E$1:$G$22,MATCH(CONCATENATE("Large bulky, extra-large and special handling items",IF($P95>=11,11,$P95)),'[1]REMOVAL FEES'!$E$1:$E$13,0),3),INDEX('[1]REMOVAL FEES'!$E$1:$G$22,MATCH(CONCATENATE("Large bulky, extra-large and special handling items",IF($P95>=11,11,$P95)),'[1]REMOVAL FEES'!$E$1:$E$13,0),3))))*$AA95,FALSE) -> -2.27 | AJ95: =AH95+AI95 -> -12.084602 | AK95: -8.7161475 | AL95: -0.59483472 | AM95: =AK95+AL95 -> -9.3109823 | AN95: =(-IF($V95="Yes", IF($X95="Yes", VLOOKUP($W95, '[1]Storage Fees'!A:M, 13, FALSE), VLOOKUP($W95, '[1]Storage Fees'!A:M, 10, FALSE)), IF($X95="Yes", VLOOKUP($W95, '[1]Storage Fees'!A:M, 7, FALSE), VLOOKUP($W95, '[1]Storage Fees'!A:M, 4, FALSE))) * U95)*1.5 -> -0.13979167
A96: 24 | C96: DLTD | E96: FB | F96: FB-0303 | G96: - | H96: 0 | I96: 0 | J96: 0 | K96: =H96&"x"&I96&"x"&J96 -> 0x0x0 | L96: =(H96*I96*J96)/139 -> 0 | M96: =(H96*I96*J96)/139 -> 0 | N96: =IF(AND(M96>0,M96<=0.25),0.25,IF(AND(M96>0.25,M96<=0.5),0.5,IF(AND(M96>0.5,M96<=0.75),0.75,ROUNDUP(M96,0)))) -> 0 | O96: 0 | P96: =ROUNDUP(MAX(L96,O96),0) -> 0 | Q96: =P96*16 -> 0 | R96: =IF(RIGHT(S96,13)="standard-size","Standard-size","Oversize") -> Standard-size | S96: =IF(AND($P96<=$J$50,$H96<=$G$50,$I96<=$H$50,$J96<=$I$50),$A$50,IF(AND($P96<=$J$51,$H96<=$G$51,$I96<=$H$51,$J96<=$I$51),$A$51,IF(AND($H96<=$G$52,$I96<=$H$52,$J96<=$I$52,$P96<=$J$52),$A$52,IF(AND($P96<=$J$53,OR(H$8>$G$53,$I96>$H$53,$J96>$I$53)),$A$53,IF(AND($P96>$J$53,$P96<=$J$54),$A$54,IF(AND($P96>$J$54,$P96<=$J$55),$A$55,$A$56)))))) -> Small standard-size | T96: Small standard: 4 oz or less | U96: =(H96*I96*J96)/1728 -> 0 | V96: No | W96: 22 – 28 | X96: No | Y96: 1 | Z96: 1 | AA96: 1 | AD96: 0 | AE96: =-AD96*0.15 -> 0 | AF96: =-IFERROR(IFERROR(VLOOKUP(ROUNDUP($Q96,0),'FBA FEES'!$L$2:$Q$203,MATCH($S96,'FBA FEES'!$L$2:$Q$2,0),FALSE),VLOOKUP(ROUNDUP($Q96,0),'FBA FEES'!$C$6:$F$123,MATCH($S96,'FBA FEES'!$C$6:$F$6,0),FALSE)),0) -> 0 | AG96: -10 | AH96: =AE96+AF96 -> 0 | AI96: =-IFERROR(IF($Y96=1,INDEX('[1]REMOVAL FEES'!$A$1:$C$22,MATCH(CONCATENATE("Standard Size",$P96),'[1]REMOVAL FEES'!$A$1:$A$22,0),3),IF($Y96=2,IF($P96>10,(($P96-10)*1.06)+INDEX('[1]REMOVAL FEES'!$E$1:$G$22,MATCH(CONCATENATE("Large bulky, extra-large and special handling items",IF($P96>=11,11,$P96)),'[1]REMOVAL FEES'!$E$1:$E$13,0),3),INDEX('[1]REMOVAL FEES'!$E$1:$G$22,MATCH(CONCATENATE("Large bulky, extra-large and special handling items",IF($P96>=11,11,$P96)),'[1]REMOVAL FEES'!$E$1:$E$13,0),3))))*$AA96,FALSE) -> 0 | AJ96: =AH96+AI96 -> 0 | AK96: 0 | AL96: 0 | AM96: =AK96+AL96 -> 0 | AN96: =(-IF($V96="Yes", IF($X96="Yes", VLOOKUP($W96, '[1]Storage Fees'!A:M, 13, FALSE), VLOOKUP($W96, '[1]Storage Fees'!A:M, 10, FALSE)), IF($X96="Yes", VLOOKUP($W96, '[1]Storage Fees'!A:M, 7, FALSE), VLOOKUP($W96, '[1]Storage Fees'!A:M, 4, FALSE))) * U96)*1.5 -> 0
A97: 25 | B97: Tushar | E97: FP | F97: FP-61 | G97: RETURNLESS REFUND | H97: 5 | I97: 4 | J97: 2 | K97: =H97&"x"&I97&"x"&J97 -> 5x4x2 | L97: =(H97*I97*J97)/139 -> 0.28776978 | M97: =(H97*I97*J97)/139 -> 0.28776978 | N97: =IF(AND(M97>0,M97<=0.25),0.25,IF(AND(M97>0.25,M97<=0.5),0.5,IF(AND(M97>0.5,M97<=0.75),0.75,ROUNDUP(M97,0)))) -> 0.5 | O97: 0.9375 | P97: =ROUNDUP(MAX(L97,O97),0) -> 1 | Q97: =P97*16 -> 16 | R97: =IF(RIGHT(S97,13)="standard-size","Standard-size","Oversize") -> Standard-size | S97: =IF(AND($P97<=$J$50,$H97<=$G$50,$I97<=$H$50,$J97<=$I$50),$A$50,IF(AND($P97<=$J$51,$H97<=$G$51,$I97<=$H$51,$J97<=$I$51),$A$51,IF(AND($H97<=$G$52,$I97<=$H$52,$J97<=$I$52,$P97<=$J$52),$A$52,IF(AND($P97<=$J$53,OR(H$8>$G$53,$I97>$H$53,$J97>$I$53)),$A$53,IF(AND($P97>$J$53,$P97<=$J$54),$A$54,IF(AND($P97>$J$54,$P97<=$J$55),$A$55,$A$56)))))) -> Large standard-size | T97: Large standard: 12+ to 16 oz | U97: =(H97*I97*J97)/1728 -> 0.023148148 | V97: No | W97: 22 – 28 | X97: No | Y97: 1 | Z97: 2 | AA97: 1 | AD97: 14.586886 | AE97: =-AD97*0.15 -> -2.1880329 | AF97: =-IFERROR(IFERROR(VLOOKUP(ROUNDUP($Q97,0),'FBA FEES'!$L$2:$Q$203,MATCH($S97,'FBA FEES'!$L$2:$Q$2,0),FALSE),VLOOKUP(ROUNDUP($Q97,0),'FBA FEES'!$C$6:$F$123,MATCH($S97,'FBA FEES'!$C$6:$F$6,0),FALSE)),0) -> -4.55 | AG97: -10 | AH97: =AE97+AF97 -> -6.7380329 | AI97: =-IFERROR(IF($Y97=1,INDEX('[1]REMOVAL FEES'!$A$1:$C$22,MATCH(CONCATENATE("Standard Size",$P97),'[1]REMOVAL FEES'!$A$1:$A$22,0),3),IF($Y97=2,IF($P97>10,(($P97-10)*1.06)+INDEX('[1]REMOVAL FEES'!$E$1:$G$22,MATCH(CONCATENATE("Large bulky, extra-large and special handling items",IF($P97>=11,11,$P97)),'[1]REMOVAL FEES'!$E$1:$E$13,0),3),INDEX('[1]REMOVAL FEES'!$E$1:$G$22,MATCH(CONCATENATE("Large bulky, extra-large and special handling items",IF($P97>=11,11,$P97)),'[1]REMOVAL FEES'!$E$1:$E$13,0),3))))*$AA97,FALSE) -> -1.53 | AJ97: =AH97+AI97 -> -8.2680329 | AK97: -2.356325 | AL97: -0.5836022 | AM97: =AK97+AL97 -> -2.9399272 | AN97: =(-IF($V97="Yes", IF($X97="Yes", VLOOKUP($W97, '[1]Storage Fees'!A:M, 13, FALSE), VLOOKUP($W97, '[1]Storage Fees'!A:M, 10, FALSE)), IF($X97="Yes", VLOOKUP($W97, '[1]Storage Fees'!A:M, 7, FALSE), VLOOKUP($W97, '[1]Storage Fees'!A:M, 4, FALSE))) * U97)*1.5 -> -0.042361111
A98: 26 | B98: Tushar | E98: FP | F98: FP-64 | G98: RETURNLESS REFUND | H98: 7 | I98: 5 | J98: 1 | K98: =H98&"x"&I98&"x"&J98 -> 7x5x1 | L98: =(H98*I98*J98)/139 -> 0.25179856 | M98: =(H98*I98*J98)/139 -> 0.25179856 | N98: =IF(AND(M98>0,M98<=0.25),0.25,IF(AND(M98>0.25,M98<=0.5),0.5,IF(AND(M98>0.5,M98<=0.75),0.75,ROUNDUP(M98,0)))) -> 0.5 | O98: 0.9375 | P98: =ROUNDUP(MAX(L98,O98),0) -> 1 | Q98: =P98*16 -> 16 | R98: =IF(RIGHT(S98,13)="standard-size","Standard-size","Oversize") -> Standard-size | S98: =IF(AND($P98<=$J$50,$H98<=$G$50,$I98<=$H$50,$J98<=$I$50),$A$50,IF(AND($P98<=$J$51,$H98<=$G$51,$I98<=$H$51,$J98<=$I$51),$A$51,IF(AND($H98<=$G$52,$I98<=$H$52,$J98<=$I$52,$P98<=$J$52),$A$52,IF(AND($P98<=$J$53,OR(H$8>$G$53,$I98>$H$53,$J98>$I$53)),$A$53,IF(AND($P98>$J$53,$P98<=$J$54),$A$54,IF(AND($P98>$J$54,$P98<=$J$55),$A$55,$A$56)))))) -> Large standard-size | T98: Large standard: 12+ to 16 oz | U98: =(H98*I98*J98)/1728 -> 0.02025463 | V98: No | W98: 22 – 28 | X98: No | Y98: 1 | Z98: 2 | AA98: 1 | AD98: 17.740562 | AE98: =-AD98*0.15 -> -2.6610843 | AF98: =-IFERROR(IFERROR(VLOOKUP(ROUNDUP($Q98,0),'FBA FEES'!$L$2:$Q$203,MATCH($S98,'FBA FEES'!$L$2:$Q$2,0),FALSE),VLOOKUP(ROUNDUP($Q98,0),'FBA FEES'!$C$6:$F$123,MATCH($S98,'FBA FEES'!$C$6:$F$6,0),FALSE)),0) -> -4.55 | AG98: -10 | AH98: =AE98+AF98 -> -7.2110843 | AI98: =-IFERROR(IF($Y98=1,INDEX('[1]REMOVAL FEES'!$A$1:$C$22,MATCH(CONCATENATE("Standard Size",$P98),'[1]REMOVAL FEES'!$A$1:$A$22,0),3),IF($Y98=2,IF($P98>10,(($P98-10)*1.06)+INDEX('[1]REMOVAL FEES'!$E$1:$G$22,MATCH(CONCATENATE("Large bulky, extra-large and special handling items",IF($P98>=11,11,$P98)),'[1]REMOVAL FEES'!$E$1:$E$13,0),3),INDEX('[1]REMOVAL FEES'!$E$1:$G$22,MATCH(CONCATENATE("Large bulky, extra-large and special handling items",IF($P98>=11,11,$P98)),'[1]REMOVAL FEES'!$E$1:$E$13,0),3))))*$AA98,FALSE) -> -1.53 | AJ98: =AH98+AI98 -> -8.7410843 | AK98: -2.32 | AL98: -0.586331 | AM98: =AK98+AL98 -> -2.906331 | AN98: =(-IF($V98="Yes", IF($X98="Yes", VLOOKUP($W98, '[1]Storage Fees'!A:M, 13, FALSE), VLOOKUP($W98, '[1]Storage Fees'!A:M, 10, FALSE)), IF($X98="Yes", VLOOKUP($W98, '[1]Storage Fees'!A:M, 7, FALSE), VLOOKUP($W98, '[1]Storage Fees'!A:M, 4, FALSE))) * U98)*1.5 -> -0.037065972
A99: 27 | C99: DLTD | E99: FP | F99: FP-66 | G99: - | H99: 0 | I99: 0 | J99: 0 | K99: =H99&"x"&I99&"x"&J99 -> 0x0x0 | L99: =(H99*I99*J99)/139 -> 0 | M99: =(H99*I99*J99)/139 -> 0 | N99: =IF(AND(M99>0,M99<=0.25),0.25,IF(AND(M99>0.25,M99<=0.5),0.5,IF(AND(M99>0.5,M99<=0.75),0.75,ROUNDUP(M99,0)))) -> 0 | O99: 0 | P99: =ROUNDUP(MAX(L99,O99),0) -> 0 | Q99: =P99*16 -> 0 | R99: =IF(RIGHT(S99,13)="standard-size","Standard-size","Oversize") -> Standard-size | S99: =IF(AND($P99<=$J$50,$H99<=$G$50,$I99<=$H$50,$J99<=$I$50),$A$50,IF(AND($P99<=$J$51,$H99<=$G$51,$I99<=$H$51,$J99<=$I$51),$A$51,IF(AND($H99<=$G$52,$I99<=$H$52,$J99<=$I$52,$P99<=$J$52),$A$52,IF(AND($P99<=$J$53,OR(H$8>$G$53,$I99>$H$53,$J99>$I$53)),$A$53,IF(AND($P99>$J$53,$P99<=$J$54),$A$54,IF(AND($P99>$J$54,$P99<=$J$55),$A$55,$A$56)))))) -> Small standard-size | T99: Small standard: 4 oz or less | U99: =(H99*I99*J99)/1728 -> 0 | V99: No | W99: 22 – 28 | X99: No | Y99: 1 | Z99: 1 | AA99: 1 | AD99: 0 | AE99: =-AD99*0.15 -> 0 | AF99: =-IFERROR(IFERROR(VLOOKUP(ROUNDUP($Q99,0),'FBA FEES'!$L$2:$Q$203,MATCH($S99,'FBA FEES'!$L$2:$Q$2,0),FALSE),VLOOKUP(ROUNDUP($Q99,0),'FBA FEES'!$C$6:$F$123,MATCH($S99,'FBA FEES'!$C$6:$F$6,0),FALSE)),0) -> 0 | AG99: -10 | AH99: =AE99+AF99 -> 0 | AI99: =-IFERROR(IF($Y99=1,INDEX('[1]REMOVAL FEES'!$A$1:$C$22,MATCH(CONCATENATE("Standard Size",$P99),'[1]REMOVAL FEES'!$A$1:$A$22,0),3),IF($Y99=2,IF($P99>10,(($P99-10)*1.06)+INDEX('[1]REMOVAL FEES'!$E$1:$G$22,MATCH(CONCATENATE("Large bulky, extra-large and special handling items",IF($P99>=11,11,$P99)),'[1]REMOVAL FEES'!$E$1:$E$13,0),3),INDEX('[1]REMOVAL FEES'!$E$1:$G$22,MATCH(CONCATENATE("Large bulky, extra-large and special handling items",IF($P99>=11,11,$P99)),'[1]REMOVAL FEES'!$E$1:$E$13,0),3))))*$AA99,FALSE) -> 0 | AJ99: =AH99+AI99 -> 0 | AK99: 0 | AL99: 0 | AM99: =AK99+AL99 -> 0 | AN99: =(-IF($V99="Yes", IF($X99="Yes", VLOOKUP($W99, '[1]Storage Fees'!A:M, 13, FALSE), VLOOKUP($W99, '[1]Storage Fees'!A:M, 10, FALSE)), IF($X99="Yes", VLOOKUP($W99, '[1]Storage Fees'!A:M, 7, FALSE), VLOOKUP($W99, '[1]Storage Fees'!A:M, 4, FALSE))) * U99)*1.5 -> 0
A100: 28 | B100: Tushar | E100: FP | F100: FP-68 | G100: RETURNLESS REFUND | H100: 8 | I100: 5 | J100: 1 | K100: =H100&"x"&I100&"x"&J100 -> 8x5x1 | L100: =(H100*I100*J100)/139 -> 0.28776978 | M100: =(H100*I100*J100)/139 -> 0.28776978 | N100: =IF(AND(M100>0,M100<=0.25),0.25,IF(AND(M100>0.25,M100<=0.5),0.5,IF(AND(M100>0.5,M100<=0.75),0.75,ROUNDUP(M100,0)))) -> 0.5 | O100: 0.9375 | P100: =ROUNDUP(MAX(L100,O100),0) -> 1 | Q100: =P100*16 -> 16 | R100: =IF(RIGHT(S100,13)="standard-size","Standard-size","Oversize") -> Standard-size | S100: =IF(AND($P100<=$J$50,$H100<=$G$50,$I100<=$H$50,$J100<=$I$50),$A$50,IF(AND($P100<=$J$51,$H100<=$G$51,$I100<=$H$51,$J100<=$I$51),$A$51,IF(AND($H100<=$G$52,$I100<=$H$52,$J100<=$I$52,$P100<=$J$52),$A$52,IF(AND($P100<=$J$53,OR(H$8>$G$53,$I100>$H$53,$J100>$I$53)),$A$53,IF(AND($P100>$J$53,$P100<=$J$54),$A$54,IF(AND($P100>$J$54,$P100<=$J$55),$A$55,$A$56)))))) -> Large standard-size | T100: Large standard: 12+ to 16 oz | U100: =(H100*I100*J100)/1728 -> 0.023148148 | V100: No | W100: 22 – 28 | X100: No | Y100: 1 | Z100: 2 | AA100: 1 | AD100: 14.638949 | AE100: =-AD100*0.15 -> -2.1958424 | AF100: =-IFERROR(IFERROR(VLOOKUP(ROUNDUP($Q100,0),'FBA FEES'!$L$2:$Q$203,MATCH($S100,'FBA FEES'!$L$2:$Q$2,0),FALSE),VLOOKUP(ROUNDUP($Q100,0),'FBA FEES'!$C$6:$F$123,MATCH($S100,'FBA FEES'!$C$6:$F$6,0),FALSE)),0) -> -4.55 | AG100: -10 | AH100: =AE100+AF100 -> -6.7458424 | AI100: =-IFERROR(IF($Y100=1,INDEX('[1]REMOVAL FEES'!$A$1:$C$22,MATCH(CONCATENATE("Standard Size",$P100),'[1]REMOVAL FEES'!$A$1:$A$22,0),3),IF($Y100=2,IF($P100>10,(($P100-10)*1.06)+INDEX('[1]REMOVAL FEES'!$E$1:$G$22,MATCH(CONCATENATE("Large bulky, extra-large and special handling items",IF($P100>=11,11,$P100)),'[1]REMOVAL FEES'!$E$1:$E$13,0),3),INDEX('[1]REMOVAL FEES'!$E$1:$G$22,MATCH(CONCATENATE("Large bulky, extra-large and special handling items",IF($P100>=11,11,$P100)),'[1]REMOVAL FEES'!$E$1:$E$13,0),3))))*$AA100,FALSE) -> -1.53 | AJ100: =AH100+AI100 -> -8.2758424 | AK100: -2.1261356 | AL100: -0.55438933 | AM100: =AK100+AL100 -> -2.6805249 | AN100: =(-IF($V100="Yes", IF($X100="Yes", VLOOKUP($W100, '[1]Storage Fees'!A:M, 13, FALSE), VLOOKUP($W100, '[1]Storage Fees'!A:M, 10, FALSE)), IF($X100="Yes", VLOOKUP($W100, '[1]Storage Fees'!A:M, 7, FALSE), VLOOKUP($W100, '[1]Storage Fees'!A:M, 4, FALSE))) * U100)*1.5 -> -0.042361111
A101: 29 | B101: Tushar | C101: DLTD | D101: LNP | E101: FP | F101: FP-69 | G101: - | H101: 8 | I101: 7 | J101: 1 | K101: =H101&"x"&I101&"x"&J101 -> 8x7x1 | L101: =(H101*I101*J101)/139 -> 0.4028777 | M101: =(H101*I101*J101)/139 -> 0.4028777 | N101: =IF(AND(M101>0,M101<=0.25),0.25,IF(AND(M101>0.25,M101<=0.5),0.5,IF(AND(M101>0.5,M101<=0.75),0.75,ROUNDUP(M101,0)))) -> 0.5 | O101: 1.5 | P101: =ROUNDUP(MAX(L101,O101),0) -> 2 | Q101: =P101*16 -> 32 | R101: =IF(RIGHT(S101,13)="standard-size","Standard-size","Oversize") -> Standard-size | S101: =IF(AND($P101<=$J$50,$H101<=$G$50,$I101<=$H$50,$J101<=$I$50),$A$50,IF(AND($P101<=$J$51,$H101<=$G$51,$I101<=$H$51,$J101<=$I$51),$A$51,IF(AND($H101<=$G$52,$I101<=$H$52,$J101<=$I$52,$P101<=$J$52),$A$52,IF(AND($P101<=$J$53,OR(H$8>$G$53,$I101>$H$53,$J101>$I$53)),$A$53,IF(AND($P101>$J$53,$P101<=$J$54),$A$54,IF(AND($P101>$J$54,$P101<=$J$55),$A$55,$A$56)))))) -> Large standard-size | T101: Large standard: 1+ to 2 lb | U101: =(H101*I101*J101)/1728 -> 0.032407407 | V101: No | W101: 22 – 28 | X101: No | Y101: 1 | Z101: 2 | AA101: 1 | AD101: 0 | AE101: =-AD101*0.15 -> 0 | AF101: =-IFERROR(IFERROR(VLOOKUP(ROUNDUP($Q101,0),'FBA FEES'!$L$2:$Q$203,MATCH($S101,'FBA FEES'!$L$2:$Q$2,0),FALSE),VLOOKUP(ROUNDUP($Q101,0),'FBA FEES'!$C$6:$F$123,MATCH($S101,'FBA FEES'!$C$6:$F$6,0),FALSE)),0) -> -5.77 | AG101: -10 | AH101: =AE101+AF101 -> -5.77 | AI101: =-IFERROR(IF($Y101=1,INDEX('[1]REMOVAL FEES'!$A$1:$C$22,MATCH(CONCATENATE("Standard Size",$P101),'[1]REMOVAL FEES'!$A$1:$A$22,0),3),IF($Y101=2,IF($P101>10,(($P101-10)*1.06)+INDEX('[1]REMOVAL FEES'!$E$1:$G$22,MATCH(CONCATENATE("Large bulky, extra-large and special handling items",IF($P101>=11,11,$P101)),'[1]REMOVAL FEES'!$E$1:$E$13,0),3),INDEX('[1]REMOVAL FEES'!$E$1:$G$22,MATCH(CONCATENATE("Large bulky, extra-large and special handling items",IF($P101>=11,11,$P101)),'[1]REMOVAL FEES'!$E$1:$E$13,0),3))))*$AA101,FALSE) -> -2.27 | AJ101: =AH101+AI101 -> -8.04 | AK101: 0 | AL101: 0 | AM101: =AK101+AL101 -> 0 | AN101: =(-IF($V101="Yes", IF($X101="Yes", VLOOKUP($W101, '[1]Storage Fees'!A:M, 13, FALSE), VLOOKUP($W101, '[1]Storage Fees'!A:M, 10, FALSE)), IF($X101="Yes", VLOOKUP($W101, '[1]Storage Fees'!A:M, 7, FALSE), VLOOKUP($W101, '[1]Storage Fees'!A:M, 4, FALSE))) * U101)*1.5 -> -0.059305556
A102: 30 | B102: Tushar | C102: DLTD | D102: LSF | E102: FP | F102: FP-70 | G102: RETURNLESS REFUND | H102: 12 | I102: 8 | J102: 3 | K102: =H102&"x"&I102&"x"&J102 -> 12x8x3 | L102: =(H102*I102*J102)/139 -> 2.0719424 | M102: =(H102*I102*J102)/139 -> 2.0719424 | N102: =IF(AND(M102>0,M102<=0.25),0.25,IF(AND(M102>0.25,M102<=0.5),0.5,IF(AND(M102>0.5,M102<=0.75),0.75,ROUNDUP(M102,0)))) -> 3 | O102: 7 | P102: =ROUNDUP(MAX(L102,O102),0) -> 7 | Q102: =P102*16 -> 112 | R102: =IF(RIGHT(S102,13)="standard-size","Standard-size","Oversize") -> Standard-size | S102: =IF(AND($P102<=$J$50,$H102<=$G$50,$I102<=$H$50,$J102<=$I$50),$A$50,IF(AND($P102<=$J$51,$H102<=$G$51,$I102<=$H$51,$J102<=$I$51),$A$51,IF(AND($H102<=$G$52,$I102<=$H$52,$J102<=$I$52,$P102<=$J$52),$A$52,IF(AND($P102<=$J$53,OR(H$8>$G$53,$I102>$H$53,$J102>$I$53)),$A$53,IF(AND($P102>$J$53,$P102<=$J$54),$A$54,IF(AND($P102>$J$54,$P102<=$J$55),$A$55,$A$56)))))) -> Large standard-size | T102: Large standard: 3+ to 20 lb | U102: =(H102*I102*J102)/1728 -> 0.16666667 | V102: No | W102: 22 – 28 | X102: No | Y102: 1 | Z102: 2 | AA102: 1 | AD102: 27.341429 | AE102: =-AD102*0.15 -> -4.1012143 | AF102: =-IFERROR(IFERROR(VLOOKUP(ROUNDUP($Q102,0),'FBA FEES'!$L$2:$Q$203,MATCH($S102,'FBA FEES'!$L$2:$Q$2,0),FALSE),VLOOKUP(ROUNDUP($Q102,0),'FBA FEES'!$C$6:$F$123,MATCH($S102,'FBA FEES'!$C$6:$F$6,0),FALSE)),0) -> -8.2 | AG102: -10 | AH102: =AE102+AF102 -> -12.301214 | AI102: =-IFERROR(IF($Y102=1,INDEX('[1]REMOVAL FEES'!$A$1:$C$22,MATCH(CONCATENATE("Standard Size",$P102),'[1]REMOVAL FEES'!$A$1:$A$22,0),3),IF($Y102=2,IF($P102>10,(($P102-10)*1.06)+INDEX('[1]REMOVAL FEES'!$E$1:$G$22,MATCH(CONCATENATE("Large bulky, extra-large and special handling items",IF($P102>=11,11,$P102)),'[1]REMOVAL FEES'!$E$1:$E$13,0),3),INDEX('[1]REMOVAL FEES'!$E$1:$G$22,MATCH(CONCATENATE("Large bulky, extra-large and special handling items",IF($P102>=11,11,$P102)),'[1]REMOVAL FEES'!$E$1:$E$13,0),3))))*$AA102,FALSE) -> -8.19 | AJ102: =AH102+AI102 -> -20.491214 | AK102: -12.97 | AL102: -1.9657143 | AM102: =AK102+AL102 -> -14.935714 | AN102: =(-IF($V102="Yes", IF($X102="Yes", VLOOKUP($W102, '[1]Storage Fees'!A:M, 13, FALSE), VLOOKUP($W102, '[1]Storage Fees'!A:M, 10, FALSE)), IF($X102="Yes", VLOOKUP($W102, '[1]Storage Fees'!A:M, 7, FALSE), VLOOKUP($W102, '[1]Storage Fees'!A:M, 4, FALSE))) * U102)*1.5 -> -0.305
A103: 31 | B103: Tushar | E103: FP | F103: FP-71 | G103: RETURNLESS REFUND | H103: 10 | I103: 9 | J103: 2 | K103: =H103&"x"&I103&"x"&J103 -> 10x9x2 | L103: =(H103*I103*J103)/139 -> 1.294964 | M103: =(H103*I103*J103)/139 -> 1.294964 | N103: =IF(AND(M103>0,M103<=0.25),0.25,IF(AND(M103>0.25,M103<=0.5),0.5,IF(AND(M103>0.5,M103<=0.75),0.75,ROUNDUP(M103,0)))) -> 2 | O103: 4 | P103: =ROUNDUP(MAX(L103,O103),0) -> 4 | Q103: =P103*16 -> 64 | R103: =IF(RIGHT(S103,13)="standard-size","Standard-size","Oversize") -> Standard-size | S103: =IF(AND($P103<=$J$50,$H103<=$G$50,$I103<=$H$50,$J103<=$I$50),$A$50,IF(AND($P103<=$J$51,$H103<=$G$51,$I103<=$H$51,$J103<=$I$51),$A$51,IF(AND($H103<=$G$52,$I103<=$H$52,$J103<=$I$52,$P103<=$J$52),$A$52,IF(AND($P103<=$J$53,OR(H$8>$G$53,$I103>$H$53,$J103>$I$53)),$A$53,IF(AND($P103>$J$53,$P103<=$J$54),$A$54,IF(AND($P103>$J$54,$P103<=$J$55),$A$55,$A$56)))))) -> Large standard-size | T103: Large standard: 3+ to 20 lb | U103: =(H103*I103*J103)/1728 -> 0.10416667 | V103: No | W103: 22 – 28 | X103: No | Y103: 1 | Z103: 2 | AA103: 1 | AD103: 27.080914 | AE103: =-AD103*0.15 -> -4.0621371 | AF103: =-IFERROR(IFERROR(VLOOKUP(ROUNDUP($Q103,0),'FBA FEES'!$L$2:$Q$203,MATCH($S103,'FBA FEES'!$L$2:$Q$2,0),FALSE),VLOOKUP(ROUNDUP($Q103,0),'FBA FEES'!$C$6:$F$123,MATCH($S103,'FBA FEES'!$C$6:$F$6,0),FALSE)),0) -> -7.24 | AG103: -10 | AH103: =AE103+AF103 -> -11.302137 | AI103: =-IFERROR(IF($Y103=1,INDEX('[1]REMOVAL FEES'!$A$1:$C$22,MATCH(CONCATENATE("Standard Size",$P103),'[1]REMOVAL FEES'!$A$1:$A$22,0),3),IF($Y103=2,IF($P103>10,(($P103-10)*1.06)+INDEX('[1]REMOVAL FEES'!$E$1:$G$22,MATCH(CONCATENATE("Large bulky, extra-large and special handling items",IF($P103>=11,11,$P103)),'[1]REMOVAL FEES'!$E$1:$E$13,0),3),INDEX('[1]REMOVAL FEES'!$E$1:$G$22,MATCH(CONCATENATE("Large bulky, extra-large and special handling items",IF($P103>=11,11,$P103)),'[1]REMOVAL FEES'!$E$1:$E$13,0),3))))*$AA103,FALSE) -> -5.01 | AJ103: =AH103+AI103 -> -16.312137 | AK103: -7.8694571 | AL103: -1.3501875 | AM103: =AK103+AL103 -> -9.2196447 | AN103: =(-IF($V103="Yes", IF($X103="Yes", VLOOKUP($W103, '[1]Storage Fees'!A:M, 13, FALSE), VLOOKUP($W103, '[1]Storage Fees'!A:M, 10, FALSE)), IF($X103="Yes", VLOOKUP($W103, '[1]Storage Fees'!A:M, 7, FALSE), VLOOKUP($W103, '[1]Storage Fees'!A:M, 4, FALSE))) * U103)*1.5 -> -0.190625
A104: 32 | B104: Tushar | C104: DLTD | D104: LSF | E104: FP | F104: FP-72 | G104: RETURNLESS REFUND | H104: 14 | I104: 10 | J104: 3 | K104: =H104&"x"&I104&"x"&J104 -> 14x10x3 | L104: =(H104*I104*J104)/139 -> 3.0215827 | M104: =(H104*I104*J104)/139 -> 3.0215827 | N104: =IF(AND(M104>0,M104<=0.25),0.25,IF(AND(M104>0.25,M104<=0.5),0.5,IF(AND(M104>0.5,M104<=0.75),0.75,ROUNDUP(M104,0)))) -> 4 | O104: 11 | P104: =ROUNDUP(MAX(L104,O104),0) -> 11 | Q104: =P104*16 -> 176 | R104: =IF(RIGHT(S104,13)="standard-size","Standard-size","Oversize") -> Standard-size | S104: =IF(AND($P104<=$J$50,$H104<=$G$50,$I104<=$H$50,$J104<=$I$50),$A$50,IF(AND($P104<=$J$51,$H104<=$G$51,$I104<=$H$51,$J104<=$I$51),$A$51,IF(AND($H104<=$G$52,$I104<=$H$52,$J104<=$I$52,$P104<=$J$52),$A$52,IF(AND($P104<=$J$53,OR(H$8>$G$53,$I104>$H$53,$J104>$I$53)),$A$53,IF(AND($P104>$J$53,$P104<=$J$54),$A$54,IF(AND($P104>$J$54,$P104<=$J$55),$A$55,$A$56)))))) -> Large standard-size | T104: Large standard: 3+ to 20 lb | U104: =(H104*I104*J104)/1728 -> 0.24305556 | V104: No | W104: 22 – 28 | X104: No | Y104: 1 | Z104: 2 | AA104: 1 | AD104: 48.765 | AE104: =-AD104*0.15 -> -7.31475 | AF104: =-IFERROR(IFERROR(VLOOKUP(ROUNDUP($Q104,0),'FBA FEES'!$L$2:$Q$203,MATCH($S104,'FBA FEES'!$L$2:$Q$2,0),FALSE),VLOOKUP(ROUNDUP($Q104,0),'FBA FEES'!$C$6:$F$123,MATCH($S104,'FBA FEES'!$C$6:$F$6,0),FALSE)),0) -> -9.48 | AG104: -10 | AH104: =AE104+AF104 -> -16.79475 | AI104: =-IFERROR(IF($Y104=1,INDEX('[1]REMOVAL FEES'!$A$1:$C$22,MATCH(CONCATENATE("Standard Size",$P104),'[1]REMOVAL FEES'!$A$1:$A$22,0),3),IF($Y104=2,IF($P104>10,(($P104-10)*1.06)+INDEX('[1]REMOVAL FEES'!$E$1:$G$22,MATCH(CONCATENATE("Large bulky, extra-large and special handling items",IF($P104>=11,11,$P104)),'[1]REMOVAL FEES'!$E$1:$E$13,0),3),INDEX('[1]REMOVAL FEES'!$E$1:$G$22,MATCH(CONCATENATE("Large bulky, extra-large and special handling items",IF($P104>=11,11,$P104)),'[1]REMOVAL FEES'!$E$1:$E$13,0),3))))*$AA104,FALSE) -> -12.43 | AJ104: =AH104+AI104 -> -29.22475 | AK104: -19.5525 | AL104: -3.06375 | AM104: =AK104+AL104 -> -22.61625 | AN104: =(-IF($V104="Yes", IF($X104="Yes", VLOOKUP($W104, '[1]Storage Fees'!A:M, 13, FALSE), VLOOKUP($W104, '[1]Storage Fees'!A:M, 10, FALSE)), IF($X104="Yes", VLOOKUP($W104, '[1]Storage Fees'!A:M, 7, FALSE), VLOOKUP($W104, '[1]Storage Fees'!A:M, 4, FALSE))) * U104)*1.5 -> -0.44479167
A105: 33 | C105: DLTD | E105: FP | F105: FP-73 | G105: - | H105: 0 | I105: 0 | J105: 0 | K105: =H105&"x"&I105&"x"&J105 -> 0x0x0 | L105: =(H105*I105*J105)/139 -> 0 | M105: =(H105*I105*J105)/139 -> 0 | N105: =IF(AND(M105>0,M105<=0.25),0.25,IF(AND(M105>0.25,M105<=0.5),0.5,IF(AND(M105>0.5,M105<=0.75),0.75,ROUNDUP(M105,0)))) -> 0 | O105: 0 | P105: =ROUNDUP(MAX(L105,O105),0) -> 0 | Q105: =P105*16 -> 0 | R105: =IF(RIGHT(S105,13)="standard-size","Standard-size","Oversize") -> Standard-size | S105: =IF(AND($P105<=$J$50,$H105<=$G$50,$I105<=$H$50,$J105<=$I$50),$A$50,IF(AND($P105<=$J$51,$H105<=$G$51,$I105<=$H$51,$J105<=$I$51),$A$51,IF(AND($H105<=$G$52,$I105<=$H$52,$J105<=$I$52,$P105<=$J$52),$A$52,IF(AND($P105<=$J$53,OR(H$8>$G$53,$I105>$H$53,$J105>$I$53)),$A$53,IF(AND($P105>$J$53,$P105<=$J$54),$A$54,IF(AND($P105>$J$54,$P105<=$J$55),$A$55,$A$56)))))) -> Small standard-size | T105: Small standard: 4 oz or less | U105: =(H105*I105*J105)/1728 -> 0 | V105: No | W105: 22 – 28 | X105: No | Y105: 1 | Z105: 1 | AA105: 1 | AD105: 105.83448 | AE105: =-AD105*0.15 -> -15.875172 | AF105: =-IFERROR(IFERROR(VLOOKUP(ROUNDUP($Q105,0),'FBA FEES'!$L$2:$Q$203,MATCH($S105,'FBA FEES'!$L$2:$Q$2,0),FALSE),VLOOKUP(ROUNDUP($Q105,0),'FBA FEES'!$C$6:$F$123,MATCH($S105,'FBA FEES'!$C$6:$F$6,0),FALSE)),0) -> 0 | AG105: -10 | AH105: =AE105+AF105 -> -15.875172 | AI105: =-IFERROR(IF($Y105=1,INDEX('[1]REMOVAL FEES'!$A$1:$C$22,MATCH(CONCATENATE("Standard Size",$P105),'[1]REMOVAL FEES'!$A$1:$A$22,0),3),IF($Y105=2,IF($P105>10,(($P105-10)*1.06)+INDEX('[1]REMOVAL FEES'!$E$1:$G$22,MATCH(CONCATENATE("Large bulky, extra-large and special handling items",IF($P105>=11,11,$P105)),'[1]REMOVAL FEES'!$E$1:$E$13,0),3),INDEX('[1]REMOVAL FEES'!$E$1:$G$22,MATCH(CONCATENATE("Large bulky, extra-large and special handling items",IF($P105>=11,11,$P105)),'[1]REMOVAL FEES'!$E$1:$E$13,0),3))))*$AA105,FALSE) -> 0 | AJ105: =AH105+AI105 -> -15.875172 | AK105: -48.23 | AL105: -11.827374 | AM105: =AK105+AL105 -> -60.057374 | AN105: =(-IF($V105="Yes", IF($X105="Yes", VLOOKUP($W105, '[1]Storage Fees'!A:M, 13, FALSE), VLOOKUP($W105, '[1]Storage Fees'!A:M, 10, FALSE)), IF($X105="Yes", VLOOKUP($W105, '[1]Storage Fees'!A:M, 7, FALSE), VLOOKUP($W105, '[1]Storage Fees'!A:M, 4, FALSE))) * U105)*1.5 -> 0
A106: 34 | C106: DLTD | E106: FPB | F106: FPB-01 | G106: - | H106: 0 | I106: 0 | J106: 0 | K106: =H106&"x"&I106&"x"&J106 -> 0x0x0 | L106: =(H106*I106*J106)/139 -> 0 | M106: =(H106*I106*J106)/139 -> 0 | N106: =IF(AND(M106>0,M106<=0.25),0.25,IF(AND(M106>0.25,M106<=0.5),0.5,IF(AND(M106>0.5,M106<=0.75),0.75,ROUNDUP(M106,0)))) -> 0 | O106: 0 | P106: =ROUNDUP(MAX(L106,O106),0) -> 0 | Q106: =P106*16 -> 0 | R106: =IF(RIGHT(S106,13)="standard-size","Standard-size","Oversize") -> Standard-size | S106: =IF(AND($P106<=$J$50,$H106<=$G$50,$I106<=$H$50,$J106<=$I$50),$A$50,IF(AND($P106<=$J$51,$H106<=$G$51,$I106<=$H$51,$J106<=$I$51),$A$51,IF(AND($H106<=$G$52,$I106<=$H$52,$J106<=$I$52,$P106<=$J$52),$A$52,IF(AND($P106<=$J$53,OR(H$8>$G$53,$I106>$H$53,$J106>$I$53)),$A$53,IF(AND($P106>$J$53,$P106<=$J$54),$A$54,IF(AND($P106>$J$54,$P106<=$J$55),$A$55,$A$56)))))) -> Small standard-size | T106: Small standard: 4 oz or less | U106: =(H106*I106*J106)/1728 -> 0 | V106: No | W106: 22 – 28 | X106: No | Y106: 1 | Z106: 1 | AA106: 1 | AD106: 131.61915 | AE106: =-AD106*0.15 -> -19.742873 | AF106: =-IFERROR(IFERROR(VLOOKUP(ROUNDUP($Q106,0),'FBA FEES'!$L$2:$Q$203,MATCH($S106,'FBA FEES'!$L$2:$Q$2,0),FALSE),VLOOKUP(ROUNDUP($Q106,0),'FBA FEES'!$C$6:$F$123,MATCH($S106,'FBA FEES'!$C$6:$F$6,0),FALSE)),0) -> 0 | AG106: -10 | AH106: =AE106+AF106 -> -19.742873 | AI106: =-IFERROR(IF($Y106=1,INDEX('[1]REMOVAL FEES'!$A$1:$C$22,MATCH(CONCATENATE("Standard Size",$P106),'[1]REMOVAL FEES'!$A$1:$A$22,0),3),IF($Y106=2,IF($P106>10,(($P106-10)*1.06)+INDEX('[1]REMOVAL FEES'!$E$1:$G$22,MATCH(CONCATENATE("Large bulky, extra-large and special handling items",IF($P106>=11,11,$P106)),'[1]REMOVAL FEES'!$E$1:$E$13,0),3),INDEX('[1]REMOVAL FEES'!$E$1:$G$22,MATCH(CONCATENATE("Large bulky, extra-large and special handling items",IF($P106>=11,11,$P106)),'[1]REMOVAL FEES'!$E$1:$E$13,0),3))))*$AA106,FALSE) -> 0 | AJ106: =AH106+AI106 -> -19.742873 | AK106: -45.750847 | AL106: -11.838952 | AM106: =AK106+AL106 -> -57.5898 | AN106: =(-IF($V106="Yes", IF($X106="Yes", VLOOKUP($W106, '[1]Storage Fees'!A:M, 13, FALSE), VLOOKUP($W106, '[1]Storage Fees'!A:M, 10, FALSE)), IF($X106="Yes", VLOOKUP($W106, '[1]Storage Fees'!A:M, 7, FALSE), VLOOKUP($W106, '[1]Storage Fees'!A:M, 4, FALSE))) * U106)*1.5 -> 0
A107: 35 | B107: Paresh | D107: SEA | E107: FPB | F107: FPB-02 | G107: RETURNLESS REFUND | H107: 9.5 | I107: 6.5 | J107: 5.5 | K107: =H107&"x"&I107&"x"&J107 -> 9.5x6.5x5.5 | L107: =(H107*I107*J107)/139 -> 2.4433453 | M107: =(H107*I107*J107)/139 -> 2.4433453 | N107: =IF(AND(M107>0,M107<=0.25),0.25,IF(AND(M107>0.25,M107<=0.5),0.5,IF(AND(M107>0.5,M107<=0.75),0.75,ROUNDUP(M107,0)))) -> 3 | O107: 7.4375 | P107: =ROUNDUP(MAX(L107,O107),0) -> 8 | Q107: =P107*16 -> 128 | R107: =IF(RIGHT(S107,13)="standard-size","Standard-size","Oversize") -> Standard-size | S107: =IF(AND($P107<=$J$50,$H107<=$G$50,$I107<=$H$50,$J107<=$I$50),$A$50,IF(AND($P107<=$J$51,$H107<=$G$51,$I107<=$H$51,$J107<=$I$51),$A$51,IF(AND($H107<=$G$52,$I107<=$H$52,$J107<=$I$52,$P107<=$J$52),$A$52,IF(AND($P107<=$J$53,OR(H$8>$G$53,$I107>$H$53,$J107>$I$53)),$A$53,IF(AND($P107>$J$53,$P107<=$J$54),$A$54,IF(AND($P107>$J$54,$P107<=$J$55),$A$55,$A$56)))))) -> Large standard-size | T107: Large standard: 3+ to 20 lb | U107: =(H107*I107*J107)/1728 -> 0.19654225 | V107: No | W107: 22 – 28 | X107: No | Y107: 1 | Z107: 2 | AA107: 1 | AD107: 46.101111 | AE107: =-AD107*0.15 -> -6.9151667 | AF107: =-IFERROR(IFERROR(VLOOKUP(ROUNDUP($Q107,0),'FBA FEES'!$L$2:$Q$203,MATCH($S107,'FBA FEES'!$L$2:$Q$2,0),FALSE),VLOOKUP(ROUNDUP($Q107,0),'FBA FEES'!$C$6:$F$123,MATCH($S107,'FBA FEES'!$C$6:$F$6,0),FALSE)),0) -> -8.52 | AG107: -10 | AH107: =AE107+AF107 -> -15.435167 | AI107: =-IFERROR(IF($Y107=1,INDEX('[1]REMOVAL FEES'!$A$1:$C$22,MATCH(CONCATENATE("Standard Size",$P107),'[1]REMOVAL FEES'!$A$1:$A$22,0),3),IF($Y107=2,IF($P107>10,(($P107-10)*1.06)+INDEX('[1]REMOVAL FEES'!$E$1:$G$22,MATCH(CONCATENATE("Large bulky, extra-large and special handling items",IF($P107>=11,11,$P107)),'[1]REMOVAL FEES'!$E$1:$E$13,0),3),INDEX('[1]REMOVAL FEES'!$E$1:$G$22,MATCH(CONCATENATE("Large bulky, extra-large and special handling items",IF($P107>=11,11,$P107)),'[1]REMOVAL FEES'!$E$1:$E$13,0),3))))*$AA107,FALSE) -> -9.25 | AJ107: =AH107+AI107 -> -24.685167 | AK107: -19.58 | AL107: -3.3530864 | AM107: =AK107+AL107 -> -22.933086 | AN107: =(-IF($V107="Yes", IF($X107="Yes", VLOOKUP($W107, '[1]Storage Fees'!A:M, 13, FALSE), VLOOKUP($W107, '[1]Storage Fees'!A:M, 10, FALSE)), IF($X107="Yes", VLOOKUP($W107, '[1]Storage Fees'!A:M, 7, FALSE), VLOOKUP($W107, '[1]Storage Fees'!A:M, 4, FALSE))) * U107)*1.5 -> -0.35967231
A108: 36 | B108: Paresh | C108: DLTD | D108: IMP FPB-11 | E108: FPB | F108: FPB-03 | G108: - | H108: 24 | I108: 19 | J108: 4 | K108: =H108&"x"&I108&"x"&J108 -> 24x19x4 | L108: =(H108*I108*J108)/139 -> 13.122302 | M108: =(H108*I108*J108)/139 -> 13.122302 | N108: =IF(AND(M108>0,M108<=0.25),0.25,IF(AND(M108>0.25,M108<=0.5),0.5,IF(AND(M108>0.5,M108<=0.75),0.75,ROUNDUP(M108,0)))) -> 14 | O108: 28 | P108: =ROUNDUP(MAX(L108,O108),0) -> 28 | Q108: =P108*16 -> 448 | R108: =IF(RIGHT(S108,13)="standard-size","Standard-size","Oversize") -> Oversize | S108: =IF(AND($P108<=$J$50,$H108<=$G$50,$I108<=$H$50,$J108<=$I$50),$A$50,IF(AND($P108<=$J$51,$H108<=$G$51,$I108<=$H$51,$J108<=$I$51),$A$51,IF(AND($H108<=$G$52,$I108<=$H$52,$J108<=$I$52,$P108<=$J$52),$A$52,IF(AND($P108<=$J$53,OR(H$8>$G$53,$I108>$H$53,$J108>$I$53)),$A$53,IF(AND($P108>$J$53,$P108<=$J$54),$A$54,IF(AND($P108>$J$54,$P108<=$J$55),$A$55,$A$56)))))) -> Large bulky | T108: Large bulky: up to 30 lb | U108: =(H108*I108*J108)/1728 -> 1.0555556 | V108: No | W108: 22 – 28 | X108: Yes | Y108: 2 | Z108: 3 | AA108: 1 | AD108: 158.94409 | AE108: =-AD108*0.15 -> -23.841614 | AF108: =-IFERROR(IFERROR(VLOOKUP(ROUNDUP($Q108,0),'FBA FEES'!$L$2:$Q$203,MATCH($S108,'FBA FEES'!$L$2:$Q$2,0),FALSE),VLOOKUP(ROUNDUP($Q108,0),'FBA FEES'!$C$6:$F$123,MATCH($S108,'FBA FEES'!$C$6:$F$6,0),FALSE)),0) -> -19.87 | AG108: -10 | AH108: =AE108+AF108 -> -43.711614 | AI108: =-IFERROR(IF($Y108=1,INDEX('[1]REMOVAL FEES'!$A$1:$C$22,MATCH(CONCATENATE("Standard Size",$P108),'[1]REMOVAL FEES'!$A$1:$A$22,0),3),IF($Y108=2,IF($P108>10,(($P108-10)*1.06)+INDEX('[1]REMOVAL FEES'!$E$1:$G$22,MATCH(CONCATENATE("Large bulky, extra-large and special handling items",IF($P108>=11,11,$P108)),'[1]REMOVAL FEES'!$E$1:$E$13,0),3),INDEX('[1]REMOVAL FEES'!$E$1:$G$22,MATCH(CONCATENATE("Large bulky, extra-large and special handling items",IF($P108>=11,11,$P108)),'[1]REMOVAL FEES'!$E$1:$E$13,0),3))))*$AA108,FALSE) -> -33.4 | AJ108: =AH108+AI108 -> -77.111614 | AK108: -56.058864 | AL108: -11.944664 | AM108: =AK108+AL108 -> -68.003528 | AN108: =(-IF($V108="Yes", IF($X108="Yes", VLOOKUP($W108, '[1]Storage Fees'!A:M, 13, FALSE), VLOOKUP($W108, '[1]Storage Fees'!A:M, 10, FALSE)), IF($X108="Yes", VLOOKUP($W108, '[1]Storage Fees'!A:M, 7, FALSE), VLOOKUP($W108, '[1]Storage Fees'!A:M, 4, FALSE))) * U108)*1.5 -> -1.2508333
A109: 37 | C109: DLTD | E109: GT | F109: GT-12 | G109: - | H109: 0 | I109: 0 | J109: 0 | K109: =H109&"x"&I109&"x"&J109 -> 0x0x0 | L109: =(H109*I109*J109)/139 -> 0 | M109: =(H109*I109*J109)/139 -> 0 | N109: =IF(AND(M109>0,M109<=0.25),0.25,IF(AND(M109>0.25,M109<=0.5),0.5,IF(AND(M109>0.5,M109<=0.75),0.75,ROUNDUP(M109,0)))) -> 0 | O109: 0 | P109: =ROUNDUP(MAX(L109,O109),0) -> 0 | Q109: =P109*16 -> 0 | R109: =IF(RIGHT(S109,13)="standard-size","Standard-size","Oversize") -> Standard-size | S109: =IF(AND($P109<=$J$50,$H109<=$G$50,$I109<=$H$50,$J109<=$I$50),$A$50,IF(AND($P109<=$J$51,$H109<=$G$51,$I109<=$H$51,$J109<=$I$51),$A$51,IF(AND($H109<=$G$52,$I109<=$H$52,$J109<=$I$52,$P109<=$J$52),$A$52,IF(AND($P109<=$J$53,OR(H$8>$G$53,$I109>$H$53,$J109>$I$53)),$A$53,IF(AND($P109>$J$53,$P109<=$J$54),$A$54,IF(AND($P109>$J$54,$P109<=$J$55),$A$55,$A$56)))))) -> Small standard-size | T109: Small standard: 4 oz or less | U109: =(H109*I109*J109)/1728 -> 0 | V109: No | W109: 22 – 28 | X109: No | Y109: 1 | Z109: 1 | AA109: 1 | AD109: 0 | AE109: =-AD109*0.15 -> 0 | AF109: =-IFERROR(IFERROR(VLOOKUP(ROUNDUP($Q109,0),'FBA FEES'!$L$2:$Q$203,MATCH($S109,'FBA FEES'!$L$2:$Q$2,0),FALSE),VLOOKUP(ROUNDUP($Q109,0),'FBA FEES'!$C$6:$F$123,MATCH($S109,'FBA FEES'!$C$6:$F$6,0),FALSE)),0) -> 0 | AG109: -10 | AH109: =AE109+AF109 -> 0 | AI109: =-IFERROR(IF($Y109=1,INDEX('[1]REMOVAL FEES'!$A$1:$C$22,MATCH(CONCATENATE("Standard Size",$P109),'[1]REMOVAL FEES'!$A$1:$A$22,0),3),IF($Y109=2,IF($P109>10,(($P109-10)*1.06)+INDEX('[1]REMOVAL FEES'!$E$1:$G$22,MATCH(CONCATENATE("Large bulky, extra-large and special handling items",IF($P109>=11,11,$P109)),'[1]REMOVAL FEES'!$E$1:$E$13,0),3),INDEX('[1]REMOVAL FEES'!$E$1:$G$22,MATCH(CONCATENATE("Large bulky, extra-large and special handling items",IF($P109>=11,11,$P109)),'[1]REMOVAL FEES'!$E$1:$E$13,0),3))))*$AA109,FALSE) -> 0 | AJ109: =AH109+AI109 -> 0 | AK109: 0 | AL109: 0 | AM109: =AK109+AL109 -> 0 | AN109: =(-IF($V109="Yes", IF($X109="Yes", VLOOKUP($W109, '[1]Storage Fees'!A:M, 13, FALSE), VLOOKUP($W109, '[1]Storage Fees'!A:M, 10, FALSE)), IF($X109="Yes", VLOOKUP($W109, '[1]Storage Fees'!A:M, 7, FALSE), VLOOKUP($W109, '[1]Storage Fees'!A:M, 4, FALSE))) * U109)*1.5 -> 0
A110: 38 | B110: Prem | E110: HB | F110: HB-10P | G110: - | H110: 12 | I110: 12 | J110: 10 | K110: =H110&"x"&I110&"x"&J110 -> 12x12x10 | L110: =(H110*I110*J110)/139 -> 10.359712 | M110: =(H110*I110*J110)/139 -> 10.359712 | N110: =IF(AND(M110>0,M110<=0.25),0.25,IF(AND(M110>0.25,M110<=0.5),0.5,IF(AND(M110>0.5,M110<=0.75),0.75,ROUNDUP(M110,0)))) -> 11 | O110: 13 | P110: =ROUNDUP(MAX(L110,O110),0) -> 13 | Q110: =P110*16 -> 208 | R110: =IF(RIGHT(S110,13)="standard-size","Standard-size","Oversize") -> Oversize | S110: =IF(AND($P110<=$J$50,$H110<=$G$50,$I110<=$H$50,$J110<=$I$50),$A$50,IF(AND($P110<=$J$51,$H110<=$G$51,$I110<=$H$51,$J110<=$I$51),$A$51,IF(AND($H110<=$G$52,$I110<=$H$52,$J110<=$I$52,$P110<=$J$52),$A$52,IF(AND($P110<=$J$53,OR(H$8>$G$53,$I110>$H$53,$J110>$I$53)),$A$53,IF(AND($P110>$J$53,$P110<=$J$54),$A$54,IF(AND($P110>$J$54,$P110<=$J$55),$A$55,$A$56)))))) -> Large bulky | T110: Large bulky: up to 30 lb | U110: =(H110*I110*J110)/1728 -> 0.83333333 | V110: No | W110: 22 – 28 | X110: Yes | Y110: 2 | Z110: 3 | AA110: 1 | AD110: 108.26811 | AE110: =-AD110*0.15 -> -16.240216 | AF110: =-IFERROR(IFERROR(VLOOKUP(ROUNDUP($Q110,0),'FBA FEES'!$L$2:$Q$203,MATCH($S110,'FBA FEES'!$L$2:$Q$2,0),FALSE),VLOOKUP(ROUNDUP($Q110,0),'FBA FEES'!$C$6:$F$123,MATCH($S110,'FBA FEES'!$C$6:$F$6,0),FALSE)),0) -> -14.17 | AG110: -10 | AH110: =AE110+AF110 -> -30.410216 | AI110: =-IFERROR(IF($Y110=1,INDEX('[1]REMOVAL FEES'!$A$1:$C$22,MATCH(CONCATENATE("Standard Size",$P110),'[1]REMOVAL FEES'!$A$1:$A$22,0),3),IF($Y110=2,IF($P110>10,(($P110-10)*1.06)+INDEX('[1]REMOVAL FEES'!$E$1:$G$22,MATCH(CONCATENATE("Large bulky, extra-large and special handling items",IF($P110>=11,11,$P110)),'[1]REMOVAL FEES'!$E$1:$E$13,0),3),INDEX('[1]REMOVAL FEES'!$E$1:$G$22,MATCH(CONCATENATE("Large bulky, extra-large and special handling items",IF($P110>=11,11,$P110)),'[1]REMOVAL FEES'!$E$1:$E$13,0),3))))*$AA110,FALSE) -> -17.5 | AJ110: =AH110+AI110 -> -47.910216 | AK110: -33.968564 | AL110: -6.4403009 | AM110: =AK110+AL110 -> -40.408865 | AN110: =(-IF($V110="Yes", IF($X110="Yes", VLOOKUP($W110, '[1]Storage Fees'!A:M, 13, FALSE), VLOOKUP($W110, '[1]Storage Fees'!A:M, 10, FALSE)), IF($X110="Yes", VLOOKUP($W110, '[1]Storage Fees'!A:M, 7, FALSE), VLOOKUP($W110, '[1]Storage Fees'!A:M, 4, FALSE))) * U110)*1.5 -> -0.9875
A111: 39 | B111: Prem | E111: HB | F111: HB-18 | G111: RETURNLESS REFUND | H111: 10 | I111: 10 | J111: 10 | K111: =H111&"x"&I111&"x"&J111 -> 10x10x10 | L111: =(H111*I111*J111)/139 -> 7.1942446 | M111: =(H111*I111*J111)/139 -> 7.1942446 | N111: =IF(AND(M111>0,M111<=0.25),0.25,IF(AND(M111>0.25,M111<=0.5),0.5,IF(AND(M111>0.5,M111<=0.75),0.75,ROUNDUP(M111,0)))) -> 8 | O111: 11 | P111: =ROUNDUP(MAX(L111,O111),0) -> 11 | Q111: =P111*16 -> 176 | R111: =IF(RIGHT(S111,13)="standard-size","Standard-size","Oversize") -> Oversize | S111: =IF(AND($P111<=$J$50,$H111<=$G$50,$I111<=$H$50,$J111<=$I$50),$A$50,IF(AND($P111<=$J$51,$H111<=$G$51,$I111<=$H$51,$J111<=$I$51),$A$51,IF(AND($H111<=$G$52,$I111<=$H$52,$J111<=$I$52,$P111<=$J$52),$A$52,IF(AND($P111<=$J$53,OR(H$8>$G$53,$I111>$H$53,$J111>$I$53)),$A$53,IF(AND($P111>$J$53,$P111<=$J$54),$A$54,IF(AND($P111>$J$54,$P111<=$J$55),$A$55,$A$56)))))) -> Large bulky | T111: Large bulky: up to 30 lb | U111: =(H111*I111*J111)/1728 -> 0.5787037 | V111: No | W111: 22 – 28 | X111: Yes | Y111: 2 | Z111: 3 | AA111: 1 | AD111: 85.430968 | AE111: =-AD111*0.15 -> -12.814645 | AF111: =-IFERROR(IFERROR(VLOOKUP(ROUNDUP($Q111,0),'FBA FEES'!$L$2:$Q$203,MATCH($S111,'FBA FEES'!$L$2:$Q$2,0),FALSE),VLOOKUP(ROUNDUP($Q111,0),'FBA FEES'!$C$6:$F$123,MATCH($S111,'FBA FEES'!$C$6:$F$6,0),FALSE)),0) -> -13.41 | AG111: -10 | AH111: =AE111+AF111 -> -26.224645 | AI111: =-IFERROR(IF($Y111=1,INDEX('[1]REMOVAL FEES'!$A$1:$C$22,MATCH(CONCATENATE("Standard Size",$P111),'[1]REMOVAL FEES'!$A$1:$A$22,0),3),IF($Y111=2,IF($P111>10,(($P111-10)*1.06)+INDEX('[1]REMOVAL FEES'!$E$1:$G$22,MATCH(CONCATENATE("Large bulky, extra-large and special handling items",IF($P111>=11,11,$P111)),'[1]REMOVAL FEES'!$E$1:$E$13,0),3),INDEX('[1]REMOVAL FEES'!$E$1:$G$22,MATCH(CONCATENATE("Large bulky, extra-large and special handling items",IF($P111>=11,11,$P111)),'[1]REMOVAL FEES'!$E$1:$E$13,0),3))))*$AA111,FALSE) -> -15.38 | AJ111: =AH111+AI111 -> -41.604645 | AK111: -26.18 | AL111: -4.1424144 | AM111: =AK111+AL111 -> -30.322414 | AN111: =(-IF($V111="Yes", IF($X111="Yes", VLOOKUP($W111, '[1]Storage Fees'!A:M, 13, FALSE), VLOOKUP($W111, '[1]Storage Fees'!A:M, 10, FALSE)), IF($X111="Yes", VLOOKUP($W111, '[1]Storage Fees'!A:M, 7, FALSE), VLOOKUP($W111, '[1]Storage Fees'!A:M, 4, FALSE))) * U111)*1.5 -> -0.68576389
A112: 40 | B112: Prem | E112: HB | F112: HB-25 | G112: RETURNLESS REFUND | H112: 12 | I112: 12 | J112: 10 | K112: =H112&"x"&I112&"x"&J112 -> 12x12x10 | L112: =(H112*I112*J112)/139 -> 10.359712 | M112: =(H112*I112*J112)/139 -> 10.359712 | N112: =IF(AND(M112>0,M112<=0.25),0.25,IF(AND(M112>0.25,M112<=0.5),0.5,IF(AND(M112>0.5,M112<=0.75),0.75,ROUNDUP(M112,0)))) -> 11 | O112: 12 | P112: =ROUNDUP(MAX(L112,O112),0) -> 12 | Q112: =P112*16 -> 192 | R112: =IF(RIGHT(S112,13)="standard-size","Standard-size","Oversize") -> Oversize | S112: =IF(AND($P112<=$J$50,$H112<=$G$50,$I112<=$H$50,$J112<=$I$50),$A$50,IF(AND($P112<=$J$51,$H112<=$G$51,$I112<=$H$51,$J112<=$I$51),$A$51,IF(AND($H112<=$G$52,$I112<=$H$52,$J112<=$I$52,$P112<=$J$52),$A$52,IF(AND($P112<=$J$53,OR(H$8>$G$53,$I112>$H$53,$J112>$I$53)),$A$53,IF(AND($P112>$J$53,$P112<=$J$54),$A$54,IF(AND($P112>$J$54,$P112<=$J$55),$A$55,$A$56)))))) -> Large bulky | T112: Large bulky: up to 30 lb | U112: =(H112*I112*J112)/1728 -> 0.83333333 | V112: No | W112: 22 – 28 | X112: Yes | Y112: 2 | Z112: 3 | AA112: 1 | AD112: 93.044167 | AE112: =-AD112*0.15 -> -13.956625 | AF112: =-IFERROR(IFERROR(VLOOKUP(ROUNDUP($Q112,0),'FBA FEES'!$L$2:$Q$203,MATCH($S112,'FBA FEES'!$L$2:$Q$2,0),FALSE),VLOOKUP(ROUNDUP($Q112,0),'FBA FEES'!$C$6:$F$123,MATCH($S112,'FBA FEES'!$C$6:$F$6,0),FALSE)),0) -> -13.79 | AG112: -10 | AH112: =AE112+AF112 -> -27.746625 | AI112: =-IFERROR(IF($Y112=1,INDEX('[1]REMOVAL FEES'!$A$1:$C$22,MATCH(CONCATENATE("Standard Size",$P112),'[1]REMOVAL FEES'!$A$1:$A$22,0),3),IF($Y112=2,IF($P112>10,(($P112-10)*1.06)+INDEX('[1]REMOVAL FEES'!$E$1:$G$22,MATCH(CONCATENATE("Large bulky, extra-large and special handling items",IF($P112>=11,11,$P112)),'[1]REMOVAL FEES'!$E$1:$E$13,0),3),INDEX('[1]REMOVAL FEES'!$E$1:$G$22,MATCH(CONCATENATE("Large bulky, extra-large and special handling items",IF($P112>=11,11,$P112)),'[1]REMOVAL FEES'!$E$1:$E$13,0),3))))*$AA112,FALSE) -> -16.44 | AJ112: =AH112+AI112 -> -44.186625 | AK112: -29.2325 | AL112: -5.9740675 | AM112: =AK112+AL112 -> -35.206567 | AN112: =(-IF($V112="Yes", IF($X112="Yes", VLOOKUP($W112, '[1]Storage Fees'!A:M, 13, FALSE), VLOOKUP($W112, '[1]Storage Fees'!A:M, 10, FALSE)), IF($X112="Yes", VLOOKUP($W112, '[1]Storage Fees'!A:M, 7, FALSE), VLOOKUP($W112, '[1]Storage Fees'!A:M, 4, FALSE))) * U112)*1.5 -> -0.9875
A113: 41 | B113: Prem | E113: HB | F113: HB-35 | G113: - | H113: 12 | I113: 12 | J113: 10 | K113: =H113&"x"&I113&"x"&J113 -> 12x12x10 | L113: =(H113*I113*J113)/139 -> 10.359712 | M113: =(H113*I113*J113)/139 -> 10.359712 | N113: =IF(AND(M113>0,M113<=0.25),0.25,IF(AND(M113>0.25,M113<=0.5),0.5,IF(AND(M113>0.5,M113<=0.75),0.75,ROUNDUP(M113,0)))) -> 11 | O113: 17 | P113: =ROUNDUP(MAX(L113,O113),0) -> 17 | Q113: =P113*16 -> 272 | R113: =IF(RIGHT(S113,13)="standard-size","Standard-size","Oversize") -> Oversize | S113: =IF(AND($P113<=$J$50,$H113<=$G$50,$I113<=$H$50,$J113<=$I$50),$A$50,IF(AND($P113<=$J$51,$H113<=$G$51,$I113<=$H$51,$J113<=$I$51),$A$51,IF(AND($H113<=$G$52,$I113<=$H$52,$J113<=$I$52,$P113<=$J$52),$A$52,IF(AND($P113<=$J$53,OR(H$8>$G$53,$I113>$H$53,$J113>$I$53)),$A$53,IF(AND($P113>$J$53,$P113<=$J$54),$A$54,IF(AND($P113>$J$54,$P113<=$J$55),$A$55,$A$56)))))) -> Large bulky | T113: Large bulky: up to 30 lb | U113: =(H113*I113*J113)/1728 -> 0.83333333 | V113: No | W113: 22 – 28 | X113: Yes | Y113: 2 | Z113: 3 | AA113: 1 | AD113: 105.52716 | AE113: =-AD113*0.15 -> -15.829073 | AF113: =-IFERROR(IFERROR(VLOOKUP(ROUNDUP($Q113,0),'FBA FEES'!$L$2:$Q$203,MATCH($S113,'FBA FEES'!$L$2:$Q$2,0),FALSE),VLOOKUP(ROUNDUP($Q113,0),'FBA FEES'!$C$6:$F$123,MATCH($S113,'FBA FEES'!$C$6:$F$6,0),FALSE)),0) -> -15.69 | AG113: -10 | AH113: =AE113+AF113 -> -31.519073 | AI113: =-IFERROR(IF($Y113=1,INDEX('[1]REMOVAL FEES'!$A$1:$C$22,MATCH(CONCATENATE("Standard Size",$P113),'[1]REMOVAL FEES'!$A$1:$A$22,0),3),IF($Y113=2,IF($P113>10,(($P113-10)*1.06)+INDEX('[1]REMOVAL FEES'!$E$1:$G$22,MATCH(CONCATENATE("Large bulky, extra-large and special handling items",IF($P113>=11,11,$P113)),'[1]REMOVAL FEES'!$E$1:$E$13,0),3),INDEX('[1]REMOVAL FEES'!$E$1:$G$22,MATCH(CONCATENATE("Large bulky, extra-large and special handling items",IF($P113>=11,11,$P113)),'[1]REMOVAL FEES'!$E$1:$E$13,0),3))))*$AA113,FALSE) -> -21.74 | AJ113: =AH113+AI113 -> -53.259073 | AK113: -40.48069 | AL113: -8.4406273 | AM113: =AK113+AL113 -> -48.921317 | AN113: =(-IF($V113="Yes", IF($X113="Yes", VLOOKUP($W113, '[1]Storage Fees'!A:M, 13, FALSE), VLOOKUP($W113, '[1]Storage Fees'!A:M, 10, FALSE)), IF($X113="Yes", VLOOKUP($W113, '[1]Storage Fees'!A:M, 7, FALSE), VLOOKUP($W113, '[1]Storage Fees'!A:M, 4, FALSE))) * U113)*1.5 -> -0.9875
A114: 42 | B114: Tushar | E114: IB | F114: IB-A06 | G114: RETURNLESS REFUND | H114: 15 | I114: 11 | J114: 9 | K114: =H114&"x"&I114&"x"&J114 -> 15x11x9 | L114: =(H114*I114*J114)/139 -> 10.683453 | M114: =(H114*I114*J114)/139 -> 10.683453 | N114: =IF(AND(M114>0,M114<=0.25),0.25,IF(AND(M114>0.25,M114<=0.5),0.5,IF(AND(M114>0.5,M114<=0.75),0.75,ROUNDUP(M114,0)))) -> 11 | O114: 10 | P114: =ROUNDUP(MAX(L114,O114),0) -> 11 | Q114: =P114*16 -> 176 | R114: =IF(RIGHT(S114,13)="standard-size","Standard-size","Oversize") -> Oversize | S114: =IF(AND($P114<=$J$50,$H114<=$G$50,$I114<=$H$50,$J114<=$I$50),$A$50,IF(AND($P114<=$J$51,$H114<=$G$51,$I114<=$H$51,$J114<=$I$51),$A$51,IF(AND($H114<=$G$52,$I114<=$H$52,$J114<=$I$52,$P114<=$J$52),$A$52,IF(AND($P114<=$J$53,OR(H$8>$G$53,$I114>$H$53,$J114>$I$53)),$A$53,IF(AND($P114>$J$53,$P114<=$J$54),$A$54,IF(AND($P114>$J$54,$P114<=$J$55),$A$55,$A$56)))))) -> Large bulky | T114: Large bulky: up to 30 lb | U114: =(H114*I114*J114)/1728 -> 0.859375 | V114: No | W114: 22 – 28 | X114: Yes | Y114: 2 | Z114: 3 | AA114: 1 | AD114: 47.917671 | AE114: =-AD114*0.15 -> -7.1876506 | AF114: =-IFERROR(IFERROR(VLOOKUP(ROUNDUP($Q114,0),'FBA FEES'!$L$2:$Q$203,MATCH($S114,'FBA FEES'!$L$2:$Q$2,0),FALSE),VLOOKUP(ROUNDUP($Q114,0),'FBA FEES'!$C$6:$F$123,MATCH($S114,'FBA FEES'!$C$6:$F$6,0),FALSE)),0) -> -13.41 | AG114: -10 | AH114: =AE114+AF114 -> -20.597651 | AI114: =-IFERROR(IF($Y114=1,INDEX('[1]REMOVAL FEES'!$A$1:$C$22,MATCH(CONCATENATE("Standard Size",$P114),'[1]REMOVAL FEES'!$A$1:$A$22,0),3),IF($Y114=2,IF($P114>10,(($P114-10)*1.06)+INDEX('[1]REMOVAL FEES'!$E$1:$G$22,MATCH(CONCATENATE("Large bulky, extra-large and special handling items",IF($P114>=11,11,$P114)),'[1]REMOVAL FEES'!$E$1:$E$13,0),3),INDEX('[1]REMOVAL FEES'!$E$1:$G$22,MATCH(CONCATENATE("Large bulky, extra-large and special handling items",IF($P114>=11,11,$P114)),'[1]REMOVAL FEES'!$E$1:$E$13,0),3))))*$AA114,FALSE) -> -15.38 | AJ114: =AH114+AI114 -> -35.977651 | AK114: -11.887106 | AL114: -5.4760957 | AM114: =AK114+AL114 -> -17.363202 | AN114: =(-IF($V114="Yes", IF($X114="Yes", VLOOKUP($W114, '[1]Storage Fees'!A:M, 13, FALSE), VLOOKUP($W114, '[1]Storage Fees'!A:M, 10, FALSE)), IF($X114="Yes", VLOOKUP($W114, '[1]Storage Fees'!A:M, 7, FALSE), VLOOKUP($W114, '[1]Storage Fees'!A:M, 4, FALSE))) * U114)*1.5 -> -1.0183594
A115: 43 | B115: Tushar | E115: IB | F115: IB-A16 | G115: RETURNLESS REFUND | H115: 16 | I115: 13 | J115: 13 | K115: =H115&"x"&I115&"x"&J115 -> 16x13x13 | L115: =(H115*I115*J115)/139 -> 19.453237 | M115: =(H115*I115*J115)/139 -> 19.453237 | N115: =IF(AND(M115>0,M115<=0.25),0.25,IF(AND(M115>0.25,M115<=0.5),0.5,IF(AND(M115>0.5,M115<=0.75),0.75,ROUNDUP(M115,0)))) -> 20 | O115: 22 | P115: =ROUNDUP(MAX(L115,O115),0) -> 22 | Q115: =P115*16 -> 352 | R115: =IF(RIGHT(S115,13)="standard-size","Standard-size","Oversize") -> Oversize | S115: =IF(AND($P115<=$J$50,$H115<=$G$50,$I115<=$H$50,$J115<=$I$50),$A$50,IF(AND($P115<=$J$51,$H115<=$G$51,$I115<=$H$51,$J115<=$I$51),$A$51,IF(AND($H115<=$G$52,$I115<=$H$52,$J115<=$I$52,$P115<=$J$52),$A$52,IF(AND($P115<=$J$53,OR(H$8>$G$53,$I115>$H$53,$J115>$I$53)),$A$53,IF(AND($P115>$J$53,$P115<=$J$54),$A$54,IF(AND($P115>$J$54,$P115<=$J$55),$A$55,$A$56)))))) -> Large bulky | T115: Large bulky: up to 30 lb | U115: =(H115*I115*J115)/1728 -> 1.5648148 | V115: No | W115: 22 – 28 | X115: Yes | Y115: 2 | Z115: 3 | AA115: 1 | AD115: 83.615877 | AE115: =-AD115*0.15 -> -12.542382 | AF115: =-IFERROR(IFERROR(VLOOKUP(ROUNDUP($Q115,0),'FBA FEES'!$L$2:$Q$203,MATCH($S115,'FBA FEES'!$L$2:$Q$2,0),FALSE),VLOOKUP(ROUNDUP($Q115,0),'FBA FEES'!$C$6:$F$123,MATCH($S115,'FBA FEES'!$C$6:$F$6,0),FALSE)),0) -> -17.59 | AG115: -10 | AH115: =AE115+AF115 -> -30.132382 | AI115: =-IFERROR(IF($Y115=1,INDEX('[1]REMOVAL FEES'!$A$1:$C$22,MATCH(CONCATENATE("Standard Size",$P115),'[1]REMOVAL FEES'!$A$1:$A$22,0),3),IF($Y115=2,IF($P115>10,(($P115-10)*1.06)+INDEX('[1]REMOVAL FEES'!$E$1:$G$22,MATCH(CONCATENATE("Large bulky, extra-large and special handling items",IF($P115>=11,11,$P115)),'[1]REMOVAL FEES'!$E$1:$E$13,0),3),INDEX('[1]REMOVAL FEES'!$E$1:$G$22,MATCH(CONCATENATE("Large bulky, extra-large and special handling items",IF($P115>=11,11,$P115)),'[1]REMOVAL FEES'!$E$1:$E$13,0),3))))*$AA115,FALSE) -> -27.04 | AJ115: =AH115+AI115 -> -57.172382 | AK115: -26.194652 | AL115: -8.0723531 | AM115: =AK115+AL115 -> -34.267005 | AN115: =(-IF($V115="Yes", IF($X115="Yes", VLOOKUP($W115, '[1]Storage Fees'!A:M, 13, FALSE), VLOOKUP($W115, '[1]Storage Fees'!A:M, 10, FALSE)), IF($X115="Yes", VLOOKUP($W115, '[1]Storage Fees'!A:M, 7, FALSE), VLOOKUP($W115, '[1]Storage Fees'!A:M, 4, FALSE))) * U115)*1.5 -> -1.8543056
A116: 44 | B116: Tushar | E116: IB | F116: IB-C05 | G116: RETURNLESS REFUND | H116: 15 | I116: 10 | J116: 10 | K116: =H116&"x"&I116&"x"&J116 -> 15x10x10 | L116: =(H116*I116*J116)/139 -> 10.791367 | M116: =(H116*I116*J116)/139 -> 10.791367 | N116: =IF(AND(M116>0,M116<=0.25),0.25,IF(AND(M116>0.25,M116<=0.5),0.5,IF(AND(M116>0.5,M116<=0.75),0.75,ROUNDUP(M116,0)))) -> 11 | O116: 12 | P116: =ROUNDUP(MAX(L116,O116),0) -> 12 | Q116: =P116*16 -> 192 | R116: =IF(RIGHT(S116,13)="standard-size","Standard-size","Oversize") -> Oversize | S116: =IF(AND($P116<=$J$50,$H116<=$G$50,$I116<=$H$50,$J116<=$I$50),$A$50,IF(AND($P116<=$J$51,$H116<=$G$51,$I116<=$H$51,$J116<=$I$51),$A$51,IF(AND($H116<=$G$52,$I116<=$H$52,$J116<=$I$52,$P116<=$J$52),$A$52,IF(AND($P116<=$J$53,OR(H$8>$G$53,$I116>$H$53,$J116>$I$53)),$A$53,IF(AND($P116>$J$53,$P116<=$J$54),$A$54,IF(AND($P116>$J$54,$P116<=$J$55),$A$55,$A$56)))))) -> Large bulky | T116: Large bulky: up to 30 lb | U116: =(H116*I116*J116)/1728 -> 0.86805556 | V116: No | W116: 22 – 28 | X116: Yes | Y116: 2 | Z116: 3 | AA116: 1 | AD116: 43.149167 | AE116: =-AD116*0.15 -> -6.472375 | AF116: =-IFERROR(IFERROR(VLOOKUP(ROUNDUP($Q116,0),'FBA FEES'!$L$2:$Q$203,MATCH($S116,'FBA FEES'!$L$2:$Q$2,0),FALSE),VLOOKUP(ROUNDUP($Q116,0),'FBA FEES'!$C$6:$F$123,MATCH($S116,'FBA FEES'!$C$6:$F$6,0),FALSE)),0) -> -13.79 | AG116: -10 | AH116: =AE116+AF116 -> -20.262375 | AI116: =-IFERROR(IF($Y116=1,INDEX('[1]REMOVAL FEES'!$A$1:$C$22,MATCH(CONCATENATE("Standard Size",$P116),'[1]REMOVAL FEES'!$A$1:$A$22,0),3),IF($Y116=2,IF($P116>10,(($P116-10)*1.06)+INDEX('[1]REMOVAL FEES'!$E$1:$G$22,MATCH(CONCATENATE("Large bulky, extra-large and special handling items",IF($P116>=11,11,$P116)),'[1]REMOVAL FEES'!$E$1:$E$13,0),3),INDEX('[1]REMOVAL FEES'!$E$1:$G$22,MATCH(CONCATENATE("Large bulky, extra-large and special handling items",IF($P116>=11,11,$P116)),'[1]REMOVAL FEES'!$E$1:$E$13,0),3))))*$AA116,FALSE) -> -16.44 | AJ116: =AH116+AI116 -> -36.702375 | AK116: -13.536429 | AL116: -5.7237644 | AM116: =AK116+AL116 -> -19.260193 | AN116: =(-IF($V116="Yes", IF($X116="Yes", VLOOKUP($W116, '[1]Storage Fees'!A:M, 13, FALSE), VLOOKUP($W116, '[1]Storage Fees'!A:M, 10, FALSE)), IF($X116="Yes", VLOOKUP($W116, '[1]Storage Fees'!A:M, 7, FALSE), VLOOKUP($W116, '[1]Storage Fees'!A:M, 4, FALSE))) * U116)*1.5 -> -1.0286458
A117: 45 | C117: DLTD | E117: IB | F117: IB-C11M | G117: - | H117: 0 | I117: 0 | J117: 0 | K117: =H117&"x"&I117&"x"&J117 -> 0x0x0 | L117: =(H117*I117*J117)/139 -> 0 | M117: =(H117*I117*J117)/139 -> 0 | N117: =IF(AND(M117>0,M117<=0.25),0.25,IF(AND(M117>0.25,M117<=0.5),0.5,IF(AND(M117>0.5,M117<=0.75),0.75,ROUNDUP(M117,0)))) -> 0 | O117: 0 | P117: =ROUNDUP(MAX(L117,O117),0) -> 0 | Q117: =P117*16 -> 0 | R117: =IF(RIGHT(S117,13)="standard-size","Standard-size","Oversize") -> Standard-size | S117: =IF(AND($P117<=$J$50,$H117<=$G$50,$I117<=$H$50,$J117<=$I$50),$A$50,IF(AND($P117<=$J$51,$H117<=$G$51,$I117<=$H$51,$J117<=$I$51),$A$51,IF(AND($H117<=$G$52,$I117<=$H$52,$J117<=$I$52,$P117<=$J$52),$A$52,IF(AND($P117<=$J$53,OR(H$8>$G$53,$I117>$H$53,$J117>$I$53)),$A$53,IF(AND($P117>$J$53,$P117<=$J$54),$A$54,IF(AND($P117>$J$54,$P117<=$J$55),$A$55,$A$56)))))) -> Small standard-size | T117: Small standard: 4 oz or less | U117: =(H117*I117*J117)/1728 -> 0 | V117: No | W117: 22 – 28 | X117: No | Y117: 1 | Z117: 1 | AA117: 1 | AD117: 65.413529 | AE117: =-AD117*0.15 -> -9.8120294 | AF117: =-IFERROR(IFERROR(VLOOKUP(ROUNDUP($Q117,0),'FBA FEES'!$L$2:$Q$203,MATCH($S117,'FBA FEES'!$L$2:$Q$2,0),FALSE),VLOOKUP(ROUNDUP($Q117,0),'FBA FEES'!$C$6:$F$123,MATCH($S117,'FBA FEES'!$C$6:$F$6,0),FALSE)),0) -> 0 | AG117: -10 | AH117: =AE117+AF117 -> -9.8120294 | AI117: =-IFERROR(IF($Y117=1,INDEX('[1]REMOVAL FEES'!$A$1:$C$22,MATCH(CONCATENATE("Standard Size",$P117),'[1]REMOVAL FEES'!$A$1:$A$22,0),3),IF($Y117=2,IF($P117>10,(($P117-10)*1.06)+INDEX('[1]REMOVAL FEES'!$E$1:$G$22,MATCH(CONCATENATE("Large bulky, extra-large and special handling items",IF($P117>=11,11,$P117)),'[1]REMOVAL FEES'!$E$1:$E$13,0),3),INDEX('[1]REMOVAL FEES'!$E$1:$G$22,MATCH(CONCATENATE("Large bulky, extra-large and special handling items",IF($P117>=11,11,$P117)),'[1]REMOVAL FEES'!$E$1:$E$13,0),3))))*$AA117,FALSE) -> 0 | AJ117: =AH117+AI117 -> -9.8120294 | AK117: -24.808824 | AL117: -10.802778 | AM117: =AK117+AL117 -> -35.611601 | AN117: =(-IF($V117="Yes", IF($X117="Yes", VLOOKUP($W117, '[1]Storage Fees'!A:M, 13, FALSE), VLOOKUP($W117, '[1]Storage Fees'!A:M, 10, FALSE)), IF($X117="Yes", VLOOKUP($W117, '[1]Storage Fees'!A:M, 7, FALSE), VLOOKUP($W117, '[1]Storage Fees'!A:M, 4, FALSE))) * U117)*1.5 -> 0
A118: 46 | B118: Tushar | E118: IB | F118: IB-C12 | G118: RETURNLESS REFUND | H118: 16 | I118: 13 | J118: 13 | K118: =H118&"x"&I118&"x"&J118 -> 16x13x13 | L118: =(H118*I118*J118)/139 -> 19.453237 | M118: =(H118*I118*J118)/139 -> 19.453237 | N118: =IF(AND(M118>0,M118<=0.25),0.25,IF(AND(M118>0.25,M118<=0.5),0.5,IF(AND(M118>0.5,M118<=0.75),0.75,ROUNDUP(M118,0)))) -> 20 | O118: 25 | P118: =ROUNDUP(MAX(L118,O118),0) -> 25 | Q118: =P118*16 -> 400 | R118: =IF(RIGHT(S118,13)="standard-size","Standard-size","Oversize") -> Oversize | S118: =IF(AND($P118<=$J$50,$H118<=$G$50,$I118<=$H$50,$J118<=$I$50),$A$50,IF(AND($P118<=$J$51,$H118<=$G$51,$I118<=$H$51,$J118<=$I$51),$A$51,IF(AND($H118<=$G$52,$I118<=$H$52,$J118<=$I$52,$P118<=$J$52),$A$52,IF(AND($P118<=$J$53,OR(H$8>$G$53,$I118>$H$53,$J118>$I$53)),$A$53,IF(AND($P118>$J$53,$P118<=$J$54),$A$54,IF(AND($P118>$J$54,$P118<=$J$55),$A$55,$A$56)))))) -> Large bulky | T118: Large bulky: up to 30 lb | U118: =(H118*I118*J118)/1728 -> 1.5648148 | V118: No | W118: 22 – 28 | X118: Yes | Y118: 2 | Z118: 3 | AA118: 1 | AD118: 75.500643 | AE118: =-AD118*0.15 -> -11.325096 | AF118: =-IFERROR(IFERROR(VLOOKUP(ROUNDUP($Q118,0),'FBA FEES'!$L$2:$Q$203,MATCH($S118,'FBA FEES'!$L$2:$Q$2,0),FALSE),VLOOKUP(ROUNDUP($Q118,0),'FBA FEES'!$C$6:$F$123,MATCH($S118,'FBA FEES'!$C$6:$F$6,0),FALSE)),0) -> -18.73 | AG118: -10 | AH118: =AE118+AF118 -> -30.055096 | AI118: =-IFERROR(IF($Y118=1,INDEX('[1]REMOVAL FEES'!$A$1:$C$22,MATCH(CONCATENATE("Standard Size",$P118),'[1]REMOVAL FEES'!$A$1:$A$22,0),3),IF($Y118=2,IF($P118>10,(($P118-10)*1.06)+INDEX('[1]REMOVAL FEES'!$E$1:$G$22,MATCH(CONCATENATE("Large bulky, extra-large and special handling items",IF($P118>=11,11,$P118)),'[1]REMOVAL FEES'!$E$1:$E$13,0),3),INDEX('[1]REMOVAL FEES'!$E$1:$G$22,MATCH(CONCATENATE("Large bulky, extra-large and special handling items",IF($P118>=11,11,$P118)),'[1]REMOVAL FEES'!$E$1:$E$13,0),3))))*$AA118,FALSE) -> -30.22 | AJ118: =AH118+AI118 -> -60.275096 | AK118: -28.375432 | AL118: -8.9492337 | AM118: =AK118+AL118 -> -37.324666 | AN118: =(-IF($V118="Yes", IF($X118="Yes", VLOOKUP($W118, '[1]Storage Fees'!A:M, 13, FALSE), VLOOKUP($W118, '[1]Storage Fees'!A:M, 10, FALSE)), IF($X118="Yes", VLOOKUP($W118, '[1]Storage Fees'!A:M, 7, FALSE), VLOOKUP($W118, '[1]Storage Fees'!A:M, 4, FALSE))) * U118)*1.5 -> -1.8543056
A119: 47 | B119: Tushar | E119: IB | F119: IB-D10 | G119: RETURNLESS REFUND | H119: 16 | I119: 16 | J119: 13 | K119: =H119&"x"&I119&"x"&J119 -> 16x16x13 | L119: =(H119*I119*J119)/139 -> 23.942446 | M119: =(H119*I119*J119)/139 -> 23.942446 | N119: =IF(AND(M119>0,M119<=0.25),0.25,IF(AND(M119>0.25,M119<=0.5),0.5,IF(AND(M119>0.5,M119<=0.75),0.75,ROUNDUP(M119,0)))) -> 24 | O119: 28 | P119: =ROUNDUP(MAX(L119,O119),0) -> 28 | Q119: =P119*16 -> 448 | R119: =IF(RIGHT(S119,13)="standard-size","Standard-size","Oversize") -> Oversize | S119: =IF(AND($P119<=$J$50,$H119<=$G$50,$I119<=$H$50,$J119<=$I$50),$A$50,IF(AND($P119<=$J$51,$H119<=$G$51,$I119<=$H$51,$J119<=$I$51),$A$51,IF(AND($H119<=$G$52,$I119<=$H$52,$J119<=$I$52,$P119<=$J$52),$A$52,IF(AND($P119<=$J$53,OR(H$8>$G$53,$I119>$H$53,$J119>$I$53)),$A$53,IF(AND($P119>$J$53,$P119<=$J$54),$A$54,IF(AND($P119>$J$54,$P119<=$J$55),$A$55,$A$56)))))) -> Large bulky | T119: Large bulky: up to 30 lb | U119: =(H119*I119*J119)/1728 -> 1.9259259 | V119: No | W119: 22 – 28 | X119: Yes | Y119: 2 | Z119: 3 | AA119: 1 | AD119: 90.96303 | AE119: =-AD119*0.15 -> -13.644455 | AF119: =-IFERROR(IFERROR(VLOOKUP(ROUNDUP($Q119,0),'FBA FEES'!$L$2:$Q$203,MATCH($S119,'FBA FEES'!$L$2:$Q$2,0),FALSE),VLOOKUP(ROUNDUP($Q119,0),'FBA FEES'!$C$6:$F$123,MATCH($S119,'FBA FEES'!$C$6:$F$6,0),FALSE)),0) -> -19.87 | AG119: -10 | AH119: =AE119+AF119 -> -33.514455 | AI119: =-IFERROR(IF($Y119=1,INDEX('[1]REMOVAL FEES'!$A$1:$C$22,MATCH(CONCATENATE("Standard Size",$P119),'[1]REMOVAL FEES'!$A$1:$A$22,0),3),IF($Y119=2,IF($P119>10,(($P119-10)*1.06)+INDEX('[1]REMOVAL FEES'!$E$1:$G$22,MATCH(CONCATENATE("Large bulky, extra-large and special handling items",IF($P119>=11,11,$P119)),'[1]REMOVAL FEES'!$E$1:$E$13,0),3),INDEX('[1]REMOVAL FEES'!$E$1:$G$22,MATCH(CONCATENATE("Large bulky, extra-large and special handling items",IF($P119>=11,11,$P119)),'[1]REMOVAL FEES'!$E$1:$E$13,0),3))))*$AA119,FALSE) -> -33.4 | AJ119: =AH119+AI119 -> -66.914455 | AK119: -30.386667 | AL119: -11.585503 | AM119: =AK119+AL119 -> -41.972169 | AN119: =(-IF($V119="Yes", IF($X119="Yes", VLOOKUP($W119, '[1]Storage Fees'!A:M, 13, FALSE), VLOOKUP($W119, '[1]Storage Fees'!A:M, 10, FALSE)), IF($X119="Yes", VLOOKUP($W119, '[1]Storage Fees'!A:M, 7, FALSE), VLOOKUP($W119, '[1]Storage Fees'!A:M, 4, FALSE))) * U119)*1.5 -> -2.2822222
A120: 48 | C120: DLTD | E120: IB | F120: IB-E03 | G120: - | H120: 0 | I120: 0 | J120: 0 | K120: =H120&"x"&I120&"x"&J120 -> 0x0x0 | L120: =(H120*I120*J120)/139 -> 0 | M120: =(H120*I120*J120)/139 -> 0 | N120: =IF(AND(M120>0,M120<=0.25),0.25,IF(AND(M120>0.25,M120<=0.5),0.5,IF(AND(M120>0.5,M120<=0.75),0.75,ROUNDUP(M120,0)))) -> 0 | O120: 0 | P120: =ROUNDUP(MAX(L120,O120),0) -> 0 | Q120: =P120*16 -> 0 | R120: =IF(RIGHT(S120,13)="standard-size","Standard-size","Oversize") -> Standard-size | S120: =IF(AND($P120<=$J$50,$H120<=$G$50,$I120<=$H$50,$J120<=$I$50),$A$50,IF(AND($P120<=$J$51,$H120<=$G$51,$I120<=$H$51,$J120<=$I$51),$A$51,IF(AND($H120<=$G$52,$I120<=$H$52,$J120<=$I$52,$P120<=$J$52),$A$52,IF(AND($P120<=$J$53,OR(H$8>$G$53,$I120>$H$53,$J120>$I$53)),$A$53,IF(AND($P120>$J$53,$P120<=$J$54),$A$54,IF(AND($P120>$J$54,$P120<=$J$55),$A$55,$A$56)))))) -> Small standard-size | T120: Small standard: 4 oz or less | U120: =(H120*I120*J120)/1728 -> 0 | V120: No | W120: 22 – 28 | X120: No | Y120: 1 | Z120: 1 | AA120: 1 | AD120: 0 | AE120: =-AD120*0.15 -> 0 | AF120: =-IFERROR(IFERROR(VLOOKUP(ROUNDUP($Q120,0),'FBA FEES'!$L$2:$Q$203,MATCH($S120,'FBA FEES'!$L$2:$Q$2,0),FALSE),VLOOKUP(ROUNDUP($Q120,0),'FBA FEES'!$C$6:$F$123,MATCH($S120,'FBA FEES'!$C$6:$F$6,0),FALSE)),0) -> 0 | AG120: -10 | AH120: =AE120+AF120 -> 0 | AI120: =-IFERROR(IF($Y120=1,INDEX('[1]REMOVAL FEES'!$A$1:$C$22,MATCH(CONCATENATE("Standard Size",$P120),'[1]REMOVAL FEES'!$A$1:$A$22,0),3),IF($Y120=2,IF($P120>10,(($P120-10)*1.06)+INDEX('[1]REMOVAL FEES'!$E$1:$G$22,MATCH(CONCATENATE("Large bulky, extra-large and special handling items",IF($P120>=11,11,$P120)),'[1]REMOVAL FEES'!$E$1:$E$13,0),3),INDEX('[1]REMOVAL FEES'!$E$1:$G$22,MATCH(CONCATENATE("Large bulky, extra-large and special handling items",IF($P120>=11,11,$P120)),'[1]REMOVAL FEES'!$E$1:$E$13,0),3))))*$AA120,FALSE) -> 0 | AJ120: =AH120+AI120 -> 0 | AK120: 0 | AL120: 0 | AM120: =AK120+AL120 -> 0 | AN120: =(-IF($V120="Yes", IF($X120="Yes", VLOOKUP($W120, '[1]Storage Fees'!A:M, 13, FALSE), VLOOKUP($W120, '[1]Storage Fees'!A:M, 10, FALSE)), IF($X120="Yes", VLOOKUP($W120, '[1]Storage Fees'!A:M, 7, FALSE), VLOOKUP($W120, '[1]Storage Fees'!A:M, 4, FALSE))) * U120)*1.5 -> 0
A121: 49 | B121: Tushar | C121: DLTD | E121: IB | F121: IB-E08 | G121: - | H121: 15 | I121: 12 | J121: 12 | K121: =H121&"x"&I121&"x"&J121 -> 15x12x12 | L121: =(H121*I121*J121)/139 -> 15.539568 | M121: =(H121*I121*J121)/139 -> 15.539568 | N121: =IF(AND(M121>0,M121<=0.25),0.25,IF(AND(M121>0.25,M121<=0.5),0.5,IF(AND(M121>0.5,M121<=0.75),0.75,ROUNDUP(M121,0)))) -> 16 | O121: 24 | P121: =ROUNDUP(MAX(L121,O121),0) -> 24 | Q121: =P121*16 -> 384 | R121: =IF(RIGHT(S121,13)="standard-size","Standard-size","Oversize") -> Oversize | S121: =IF(AND($P121<=$J$50,$H121<=$G$50,$I121<=$H$50,$J121<=$I$50),$A$50,IF(AND($P121<=$J$51,$H121<=$G$51,$I121<=$H$51,$J121<=$I$51),$A$51,IF(AND($H121<=$G$52,$I121<=$H$52,$J121<=$I$52,$P121<=$J$52),$A$52,IF(AND($P121<=$J$53,OR(H$8>$G$53,$I121>$H$53,$J121>$I$53)),$A$53,IF(AND($P121>$J$53,$P121<=$J$54),$A$54,IF(AND($P121>$J$54,$P121<=$J$55),$A$55,$A$56)))))) -> Large bulky | T121: Large bulky: up to 30 lb | U121: =(H121*I121*J121)/1728 -> 1.25 | V121: No | W121: 22 – 28 | X121: Yes | Y121: 2 | Z121: 3 | AA121: 1 | AD121: 79.233333 | AE121: =-AD121*0.15 -> -11.885 | AF121: =-IFERROR(IFERROR(VLOOKUP(ROUNDUP($Q121,0),'FBA FEES'!$L$2:$Q$203,MATCH($S121,'FBA FEES'!$L$2:$Q$2,0),FALSE),VLOOKUP(ROUNDUP($Q121,0),'FBA FEES'!$C$6:$F$123,MATCH($S121,'FBA FEES'!$C$6:$F$6,0),FALSE)),0) -> -18.35 | AG121: -10 | AH121: =AE121+AF121 -> -30.235 | AI121: =-IFERROR(IF($Y121=1,INDEX('[1]REMOVAL FEES'!$A$1:$C$22,MATCH(CONCATENATE("Standard Size",$P121),'[1]REMOVAL FEES'!$A$1:$A$22,0),3),IF($Y121=2,IF($P121>10,(($P121-10)*1.06)+INDEX('[1]REMOVAL FEES'!$E$1:$G$22,MATCH(CONCATENATE("Large bulky, extra-large and special handling items",IF($P121>=11,11,$P121)),'[1]REMOVAL FEES'!$E$1:$E$13,0),3),INDEX('[1]REMOVAL FEES'!$E$1:$G$22,MATCH(CONCATENATE("Large bulky, extra-large and special handling items",IF($P121>=11,11,$P121)),'[1]REMOVAL FEES'!$E$1:$E$13,0),3))))*$AA121,FALSE) -> -29.16 | AJ121: =AH121+AI121 -> -59.395 | AK121: -26.64 | AL121: -13.139167 | AM121: =AK121+AL121 -> -39.779167 | AN121: =(-IF($V121="Yes", IF($X121="Yes", VLOOKUP($W121, '[1]Storage Fees'!A:M, 13, FALSE), VLOOKUP($W121, '[1]Storage Fees'!A:M, 10, FALSE)), IF($X121="Yes", VLOOKUP($W121, '[1]Storage Fees'!A:M, 7, FALSE), VLOOKUP($W121, '[1]Storage Fees'!A:M, 4, FALSE))) * U121)*1.5 -> -1.48125
...

Sheet Stores
A1: STORE | B1: SHORT
A2: Amazon Califonia | B2: A-CA
A3: Amazon Hytech | B3: A-HY
A4: Amazon Silion | B4: A-SL
A5: Amazon SimondStore | B5: A-SS
A6: EBAY CALIFONIA | B6: E-CA
A7: Ebay Hytech | B7: E-HY
A8: Ebay Simondstore | B8: E-SS
A9: Walmart Store | B9: WALMART
A10: Amazon Hytech - FBA | B10: A-HY
A11: Amazon Silion - FBA | B11: A-SL
A12: Amazon Canada - FBA | B12: A-CAN
... A20: Amazon Silion Mexico - FBA | B20: A-SL(MX)

Sheet FREIGHT BACKUP
B1: 45627
A2: SKU | B2: Freight-FBA | C2: Freight-Canada
A3: B10 | B3: -16.759967 | C3: -52.7
A4: B10J | B4: -7.004 | C4: -2.4853295
A5: B10X | B5: -8.57825 | C5: -9.3312077
A6: B11 | B6: -16.317833 | C6: -31.54
A7: B12 | B7: -19.018656 | C7: -38.300555
A8: B12F | B8: -1.554 | C8: -3.57
A9: B12H | B9: -7.3943852 | C9: -8.277391
A10: B12J | B10: -4.75 | C10: -12.200814
A11: B12X | B11: -13.209306 | C11: -7.5770381
A12: B9J | B12: -6.2852985 | C12: -2.8322584
A13: BS10 | B13: -13.158981 | C13: -29.8
A14: BS13 | B14: -9.872619 | C14: -6.63
A15: BS9 | B15: -8.4990151 | C15: -12.39
A16: CM-B209 | B16: NA | C16: NA
A17: CP-1-2425F | B17: -6.0722035 | C17: -1.9356284
A18: CP-2-2425F | B18: -6.2123333 | C18: NA
A19: CP-3-2425F | B19: -7.1414359 | C19: -3.8545329
A20: CT-AM04 | B20: -1.3919848 | C20: -0.8
A21: CT-AM125 | B21: -4.87 | C21: NA
A22: CT-AS10 | B22: NA | C22: NA
A23: CT-TC22 | B23: -11.527667 | C23: -1.9868576
A24: CT-WK22 | B24: -11.998333 | C24: NA
A25: EH-03 | B25: -0.67 | C25: -0.38
A26: FB-0303 | B26: NA | C26: NA
A27: FP-61 | B27: -0.62086688 | C27: -0.42867746
A28: FP-64 | B28: -0.56860465 | C28: NA
A29: FP-66 | B29: NA | C29: NA
A30: FP-68 | B30: -0.61014815 | C30: -0.12
A31: FP-69 | B31: NA | C31: NA
A32: FP-70 | B32: -1.9028571 | C32: NA
A33: FP-71 | B33: -1.3831818 | C33: -1.4809243
A34: FP-72 | B34: -3.06375 | C34: NA
A35: FP-73 | B35: -11.911917 | C35: NA
A36: FPB-01 | B36: -11.719702 | C36: -3.8763852
A37: FPB-02 | B37: -3.7722222 | C37: NA
A38: FPB-03 | B38: -11.131111 | C38: -4.5323888
A39: GT-12 | B39: NA | C39: NA
A40: HB-10P | B40: -6.351224 | C40: -5.4783643
A41: HB-18 | B41: -4.21 | C41: -16.651551
A42: HB-25 | B42: -8.375 | C42: -20.125094
A43: HB-35 | B43: -9.4679 | C43: -43.190765
A44: IB-A06 | B44: -4.3046042 | C44: -3.7730392
A45: IB-A16 | B45: -9.1904254 | C45: -11.385153
A46: IB-C05 | B46: -6.2700417 | C46: -3.514046
A47: IB-C11M | B47: -10.802778 | C47: -19.62947
A48: IB-C12 | B48: -10.126307 | C48: -7.2306863
A49: IB-D10 | B49: -11.815 | C49: -11.5434
A50: IB-E03 | B50: NA | C50: NA
A51: IB-E08 | B51: -13.139167 | C51: NA
A52: IB-F08 | B52: -9.4857188 | C52: -20.864074
A53: IB-G08 | B53: -8.6113379 | C53: -14.534708
A54: IC-1206 | B54: NA | C54: NA
A55: IC-1212 | B55: NA | C55: NA
A56: IC-1218 | B56: NA | C56: NA
A57: IC-1224 | B57: NA | C57: NA
A58: IC-1806 | B58: NA | C58: NA
A59: IC-1812 | B59: NA | C59: NA
A60: IC-1818 | B60: NA | C60: NA
A61: IC-2406 | B61: NA | C61: NA
A62: IC-2418 | B62: NA | C62: NA
A63: IC-3006 | B63: NA | C63: NA
A64: IC-3024 | B64: NA | C64: NA
A65: IC-3606 | B65: NA | C65: NA
... A78: IC-6024 | B78: NA | C78: NA
A79: JMT-01 | B79: -18.070833 | C79: -41.337005
A80: JMT-02 | B80: -18.412328 | C80: -31.465189
A81: JMT-03 | B81: -21.808333 | C81: -39.025253
A82: JMT-04 | B82: -1.246875 | C82: NA
A83: JMT-09 | B83: NA | C83: NA
A84: JMT-103 | B84: -0.8215 | C84: -0.40616381
A85: JMT-110 | B85: NA | C85: NA
A86: JMT-112 | B86: NA | C86: NA
A87: JMT-118 | B87: -1.3677826 | C87: -0.81093903
A88: JMT-121 | B88: -1.9496457 | C88: NA
A89: JMT-25 | B89: -11.519167 | C89: -3.7375334
A90: JMT-37 | B90: NA | C90: NA
A91: JMT-59 | B91: -7.5016492 | C91: -3.34
A92: JMT-81 | B92: NA | C92: NA
A93: JMT-88 | B93: NA | C93: NA
A94: JMT-89 | B94: NA | C94: NA
A95: JMT-90 | B95: NA | C95: NA
A96: JMT-93 | B96: -5.771 | C96: NA
A97: JMT-96 | B97: -6.24 | C97: -4.43
A98: JMT-97 | B98: -6.5845556 | C98: NA
A99: KW-06 | B99: NA | C99: NA
A100: KW-07 | B100: NA | C100: NA
A101: KW-10 | B101: NA | C101: NA
A102: KW-11 | B102: NA | C102: NA
A103: KW-17 | B103: NA | C103: NA
A104: KW-18 | B104: NA | C104: NA
A105: KW-19 | B105: NA | C105: NA
A106: MFI-10 | B106: -11.804792 | C106: -44.078716
A107: MFI-12 | B107: -17.1384 | C107: -41.598739
A108: MFI-13 | B108: -37.47 | C108: NA
A109: PF-11 | B109: NA | C109: -29.830581
A110: PF-11I | B110: NA | C110: NA
A111: PF-20 | B111: -12.468333 | C111: NA
A112: PF-21 | B112: -15.446 | C112: -44.031241
...
